package com.google.android.gms.internal;

import android.os.Binder;
import android.os.IBinder;
import android.os.IInterface;
import android.os.Parcel;
import android.os.RemoteException;
import com.google.android.gms.dynamic.d;
import com.google.android.gms.dynamic.d.a;

public abstract interface ar
  extends IInterface
{
  public abstract d P()
    throws RemoteException;
  
  public abstract am Q()
    throws RemoteException;
  
  public abstract void a(am paramam)
    throws RemoteException;
  
  public abstract void a(aq paramaq)
    throws RemoteException;
  
  public abstract void a(at paramat)
    throws RemoteException;
  
  public abstract void a(dd paramdd)
    throws RemoteException;
  
  public abstract void a(dh paramdh, String paramString)
    throws RemoteException;
  
  public abstract boolean a(aj paramaj)
    throws RemoteException;
  
  public abstract void ab()
    throws RemoteException;
  
  public abstract void destroy()
    throws RemoteException;
  
  public abstract boolean isReady()
    throws RemoteException;
  
  public abstract void pause()
    throws RemoteException;
  
  public abstract void resume()
    throws RemoteException;
  
  public abstract void showInterstitial()
    throws RemoteException;
  
  public abstract void stopLoading()
    throws RemoteException;
  
  public static abstract class a
    extends Binder
    implements ar
  {
    public a()
    {
      attachInterface(this, "com.google.android.gms.ads.internal.client.IAdManager");
    }
    
    public static ar f(IBinder paramIBinder)
    {
      Object localObject;
      if (paramIBinder != null)
      {
        localObject = paramIBinder.queryLocalInterface("com.google.android.gms.ads.internal.client.IAdManager");
        if ((localObject == null) || (!(localObject instanceof ar))) {
          localObject = new a(paramIBinder);
        } else {
          localObject = (ar)localObject;
        }
      }
      else
      {
        localObject = null;
      }
      return localObject;
    }
    
    public IBinder asBinder()
    {
      return this;
    }
    
    public boolean onTransact(int paramInt1, Parcel paramParcel1, Parcel paramParcel2, int paramInt2)
      throws RemoteException
    {
      IBinder localIBinder = null;
      int j = 0;
      d locald1 = 1;
      d locald2;
      am localam;
      switch (paramInt1)
      {
      default: 
        locald1 = super.onTransact(paramInt1, paramParcel1, paramParcel2, paramInt2);
        break;
      case 1: 
        paramParcel1.enforceInterface("com.google.android.gms.ads.internal.client.IAdManager");
        locald2 = P();
        paramParcel2.writeNoException();
        if (locald2 != null) {
          localIBinder = locald2.asBinder();
        }
        paramParcel2.writeStrongBinder(localIBinder);
        break;
      case 2: 
        paramParcel1.enforceInterface("com.google.android.gms.ads.internal.client.IAdManager");
        destroy();
        paramParcel2.writeNoException();
        break;
      case 3: 
        paramParcel1.enforceInterface("com.google.android.gms.ads.internal.client.IAdManager");
        int i = isReady();
        paramParcel2.writeNoException();
        if (i == 0) {
          i = 0;
        } else {
          i = locald1;
        }
        paramParcel2.writeInt(i);
        break;
      case 4: 
        paramParcel1.enforceInterface("com.google.android.gms.ads.internal.client.IAdManager");
        aj localaj;
        if (paramParcel1.readInt() != 0) {
          localaj = aj.CREATOR.b(paramParcel1);
        }
        boolean bool = a(localaj);
        paramParcel2.writeNoException();
        if (bool) {
          locald2 = locald1;
        }
        paramParcel2.writeInt(locald2);
        break;
      case 5: 
        paramParcel1.enforceInterface("com.google.android.gms.ads.internal.client.IAdManager");
        pause();
        paramParcel2.writeNoException();
        break;
      case 6: 
        paramParcel1.enforceInterface("com.google.android.gms.ads.internal.client.IAdManager");
        resume();
        paramParcel2.writeNoException();
        break;
      case 7: 
        paramParcel1.enforceInterface("com.google.android.gms.ads.internal.client.IAdManager");
        a(aq.a.e(paramParcel1.readStrongBinder()));
        paramParcel2.writeNoException();
        break;
      case 8: 
        paramParcel1.enforceInterface("com.google.android.gms.ads.internal.client.IAdManager");
        a(at.a.h(paramParcel1.readStrongBinder()));
        paramParcel2.writeNoException();
        break;
      case 9: 
        paramParcel1.enforceInterface("com.google.android.gms.ads.internal.client.IAdManager");
        showInterstitial();
        paramParcel2.writeNoException();
        break;
      case 10: 
        paramParcel1.enforceInterface("com.google.android.gms.ads.internal.client.IAdManager");
        stopLoading();
        paramParcel2.writeNoException();
        break;
      case 11: 
        paramParcel1.enforceInterface("com.google.android.gms.ads.internal.client.IAdManager");
        ab();
        paramParcel2.writeNoException();
        break;
      case 12: 
        paramParcel1.enforceInterface("com.google.android.gms.ads.internal.client.IAdManager");
        localam = Q();
        paramParcel2.writeNoException();
        if (localam == null)
        {
          paramParcel2.writeInt(0);
        }
        else
        {
          paramParcel2.writeInt(locald1);
          localam.writeToParcel(paramParcel2, locald1);
        }
        break;
      case 13: 
        paramParcel1.enforceInterface("com.google.android.gms.ads.internal.client.IAdManager");
        if (paramParcel1.readInt() != 0) {
          localam = am.CREATOR.c(paramParcel1);
        }
        a(localam);
        paramParcel2.writeNoException();
        break;
      case 14: 
        paramParcel1.enforceInterface("com.google.android.gms.ads.internal.client.IAdManager");
        a(dd.a.q(paramParcel1.readStrongBinder()));
        paramParcel2.writeNoException();
        break;
      case 15: 
        paramParcel1.enforceInterface("com.google.android.gms.ads.internal.client.IAdManager");
        a(dh.a.u(paramParcel1.readStrongBinder()), paramParcel1.readString());
        paramParcel2.writeNoException();
        break;
      case 1598968902: 
        paramParcel2.writeString("com.google.android.gms.ads.internal.client.IAdManager");
      }
      return locald1;
    }
    
    private static class a
      implements ar
    {
      private IBinder ko;
      
      a(IBinder paramIBinder)
      {
        this.ko = paramIBinder;
      }
      
      public d P()
        throws RemoteException
      {
        Parcel localParcel1 = Parcel.obtain();
        Parcel localParcel2 = Parcel.obtain();
        try
        {
          localParcel1.writeInterfaceToken("com.google.android.gms.ads.internal.client.IAdManager");
          this.ko.transact(1, localParcel1, localParcel2, 0);
          localParcel2.readException();
          d locald = d.a.ag(localParcel2.readStrongBinder());
          return locald;
        }
        finally
        {
          localParcel2.recycle();
          localParcel1.recycle();
        }
      }
      
      /* Error */
      public am Q()
        throws RemoteException
      {
        // Byte code:
        //   0: invokestatic 28	android/os/Parcel:obtain	()Landroid/os/Parcel;
        //   3: astore_1
        //   4: invokestatic 28	android/os/Parcel:obtain	()Landroid/os/Parcel;
        //   7: astore_2
        //   8: aload_1
        //   9: ldc 30
        //   11: invokevirtual 34	android/os/Parcel:writeInterfaceToken	(Ljava/lang/String;)V
        //   14: aload_0
        //   15: getfield 18	com/google/android/gms/internal/ar$a$a:ko	Landroid/os/IBinder;
        //   18: bipush 12
        //   20: aload_1
        //   21: aload_2
        //   22: iconst_0
        //   23: invokeinterface 40 5 0
        //   28: pop
        //   29: aload_2
        //   30: invokevirtual 43	android/os/Parcel:readException	()V
        //   33: aload_2
        //   34: invokevirtual 62	android/os/Parcel:readInt	()I
        //   37: ifeq +23 -> 60
        //   40: getstatic 68	com/google/android/gms/internal/am:CREATOR	Lcom/google/android/gms/internal/an;
        //   43: aload_2
        //   44: invokevirtual 74	com/google/android/gms/internal/an:c	(Landroid/os/Parcel;)Lcom/google/android/gms/internal/am;
        //   47: astore_3
        //   48: aload_3
        //   49: astore_3
        //   50: aload_2
        //   51: invokevirtual 56	android/os/Parcel:recycle	()V
        //   54: aload_1
        //   55: invokevirtual 56	android/os/Parcel:recycle	()V
        //   58: aload_3
        //   59: areturn
        //   60: aconst_null
        //   61: astore_3
        //   62: goto -12 -> 50
        //   65: astore_3
        //   66: aload_2
        //   67: invokevirtual 56	android/os/Parcel:recycle	()V
        //   70: aload_1
        //   71: invokevirtual 56	android/os/Parcel:recycle	()V
        //   74: aload_3
        //   75: athrow
        // Local variable table:
        //   start	length	slot	name	signature
        //   0	76	0	this	a
        //   3	68	1	localParcel1	Parcel
        //   7	60	2	localParcel2	Parcel
        //   47	15	3	localam	am
        //   65	10	3	localObject	Object
        // Exception table:
        //   from	to	target	type
        //   8	48	65	finally
      }
      
      /* Error */
      public void a(am paramam)
        throws RemoteException
      {
        // Byte code:
        //   0: invokestatic 28	android/os/Parcel:obtain	()Landroid/os/Parcel;
        //   3: astore_3
        //   4: invokestatic 28	android/os/Parcel:obtain	()Landroid/os/Parcel;
        //   7: astore 4
        //   9: aload_3
        //   10: ldc 30
        //   12: invokevirtual 34	android/os/Parcel:writeInterfaceToken	(Ljava/lang/String;)V
        //   15: aload_1
        //   16: ifnull +45 -> 61
        //   19: aload_3
        //   20: iconst_1
        //   21: invokevirtual 79	android/os/Parcel:writeInt	(I)V
        //   24: aload_1
        //   25: aload_3
        //   26: iconst_0
        //   27: invokevirtual 83	com/google/android/gms/internal/am:writeToParcel	(Landroid/os/Parcel;I)V
        //   30: aload_0
        //   31: getfield 18	com/google/android/gms/internal/ar$a$a:ko	Landroid/os/IBinder;
        //   34: bipush 13
        //   36: aload_3
        //   37: aload 4
        //   39: iconst_0
        //   40: invokeinterface 40 5 0
        //   45: pop
        //   46: aload 4
        //   48: invokevirtual 43	android/os/Parcel:readException	()V
        //   51: aload 4
        //   53: invokevirtual 56	android/os/Parcel:recycle	()V
        //   56: aload_3
        //   57: invokevirtual 56	android/os/Parcel:recycle	()V
        //   60: return
        //   61: aload_3
        //   62: iconst_0
        //   63: invokevirtual 79	android/os/Parcel:writeInt	(I)V
        //   66: goto -36 -> 30
        //   69: astore_2
        //   70: aload 4
        //   72: invokevirtual 56	android/os/Parcel:recycle	()V
        //   75: aload_3
        //   76: invokevirtual 56	android/os/Parcel:recycle	()V
        //   79: aload_2
        //   80: athrow
        // Local variable table:
        //   start	length	slot	name	signature
        //   0	81	0	this	a
        //   0	81	1	paramam	am
        //   69	11	2	localObject	Object
        //   3	73	3	localParcel1	Parcel
        //   7	64	4	localParcel2	Parcel
        // Exception table:
        //   from	to	target	type
        //   9	51	69	finally
        //   61	66	69	finally
      }
      
      /* Error */
      public void a(aq paramaq)
        throws RemoteException
      {
        // Byte code:
        //   0: invokestatic 28	android/os/Parcel:obtain	()Landroid/os/Parcel;
        //   3: astore_2
        //   4: invokestatic 28	android/os/Parcel:obtain	()Landroid/os/Parcel;
        //   7: astore_3
        //   8: aload_2
        //   9: ldc 30
        //   11: invokevirtual 34	android/os/Parcel:writeInterfaceToken	(Ljava/lang/String;)V
        //   14: aload_1
        //   15: ifnull +45 -> 60
        //   18: aload_1
        //   19: invokeinterface 89 1 0
        //   24: astore 4
        //   26: aload_2
        //   27: aload 4
        //   29: invokevirtual 92	android/os/Parcel:writeStrongBinder	(Landroid/os/IBinder;)V
        //   32: aload_0
        //   33: getfield 18	com/google/android/gms/internal/ar$a$a:ko	Landroid/os/IBinder;
        //   36: bipush 7
        //   38: aload_2
        //   39: aload_3
        //   40: iconst_0
        //   41: invokeinterface 40 5 0
        //   46: pop
        //   47: aload_3
        //   48: invokevirtual 43	android/os/Parcel:readException	()V
        //   51: aload_3
        //   52: invokevirtual 56	android/os/Parcel:recycle	()V
        //   55: aload_2
        //   56: invokevirtual 56	android/os/Parcel:recycle	()V
        //   59: return
        //   60: aconst_null
        //   61: astore 4
        //   63: goto -37 -> 26
        //   66: astore 4
        //   68: aload_3
        //   69: invokevirtual 56	android/os/Parcel:recycle	()V
        //   72: aload_2
        //   73: invokevirtual 56	android/os/Parcel:recycle	()V
        //   76: aload 4
        //   78: athrow
        // Local variable table:
        //   start	length	slot	name	signature
        //   0	79	0	this	a
        //   0	79	1	paramaq	aq
        //   3	70	2	localParcel1	Parcel
        //   7	62	3	localParcel2	Parcel
        //   24	38	4	localIBinder	IBinder
        //   66	11	4	localObject	Object
        // Exception table:
        //   from	to	target	type
        //   8	51	66	finally
      }
      
      /* Error */
      public void a(at paramat)
        throws RemoteException
      {
        // Byte code:
        //   0: invokestatic 28	android/os/Parcel:obtain	()Landroid/os/Parcel;
        //   3: astore_3
        //   4: invokestatic 28	android/os/Parcel:obtain	()Landroid/os/Parcel;
        //   7: astore_2
        //   8: aload_3
        //   9: ldc 30
        //   11: invokevirtual 34	android/os/Parcel:writeInterfaceToken	(Ljava/lang/String;)V
        //   14: aload_1
        //   15: ifnull +45 -> 60
        //   18: aload_1
        //   19: invokeinterface 96 1 0
        //   24: astore 4
        //   26: aload_3
        //   27: aload 4
        //   29: invokevirtual 92	android/os/Parcel:writeStrongBinder	(Landroid/os/IBinder;)V
        //   32: aload_0
        //   33: getfield 18	com/google/android/gms/internal/ar$a$a:ko	Landroid/os/IBinder;
        //   36: bipush 8
        //   38: aload_3
        //   39: aload_2
        //   40: iconst_0
        //   41: invokeinterface 40 5 0
        //   46: pop
        //   47: aload_2
        //   48: invokevirtual 43	android/os/Parcel:readException	()V
        //   51: aload_2
        //   52: invokevirtual 56	android/os/Parcel:recycle	()V
        //   55: aload_3
        //   56: invokevirtual 56	android/os/Parcel:recycle	()V
        //   59: return
        //   60: aconst_null
        //   61: astore 4
        //   63: goto -37 -> 26
        //   66: astore 4
        //   68: aload_2
        //   69: invokevirtual 56	android/os/Parcel:recycle	()V
        //   72: aload_3
        //   73: invokevirtual 56	android/os/Parcel:recycle	()V
        //   76: aload 4
        //   78: athrow
        // Local variable table:
        //   start	length	slot	name	signature
        //   0	79	0	this	a
        //   0	79	1	paramat	at
        //   7	62	2	localParcel1	Parcel
        //   3	70	3	localParcel2	Parcel
        //   24	38	4	localIBinder	IBinder
        //   66	11	4	localObject	Object
        // Exception table:
        //   from	to	target	type
        //   8	51	66	finally
      }
      
      /* Error */
      public void a(dd paramdd)
        throws RemoteException
      {
        // Byte code:
        //   0: invokestatic 28	android/os/Parcel:obtain	()Landroid/os/Parcel;
        //   3: astore_3
        //   4: invokestatic 28	android/os/Parcel:obtain	()Landroid/os/Parcel;
        //   7: astore_2
        //   8: aload_3
        //   9: ldc 30
        //   11: invokevirtual 34	android/os/Parcel:writeInterfaceToken	(Ljava/lang/String;)V
        //   14: aload_1
        //   15: ifnull +45 -> 60
        //   18: aload_1
        //   19: invokeinterface 100 1 0
        //   24: astore 4
        //   26: aload_3
        //   27: aload 4
        //   29: invokevirtual 92	android/os/Parcel:writeStrongBinder	(Landroid/os/IBinder;)V
        //   32: aload_0
        //   33: getfield 18	com/google/android/gms/internal/ar$a$a:ko	Landroid/os/IBinder;
        //   36: bipush 14
        //   38: aload_3
        //   39: aload_2
        //   40: iconst_0
        //   41: invokeinterface 40 5 0
        //   46: pop
        //   47: aload_2
        //   48: invokevirtual 43	android/os/Parcel:readException	()V
        //   51: aload_2
        //   52: invokevirtual 56	android/os/Parcel:recycle	()V
        //   55: aload_3
        //   56: invokevirtual 56	android/os/Parcel:recycle	()V
        //   59: return
        //   60: aconst_null
        //   61: astore 4
        //   63: goto -37 -> 26
        //   66: astore 4
        //   68: aload_2
        //   69: invokevirtual 56	android/os/Parcel:recycle	()V
        //   72: aload_3
        //   73: invokevirtual 56	android/os/Parcel:recycle	()V
        //   76: aload 4
        //   78: athrow
        // Local variable table:
        //   start	length	slot	name	signature
        //   0	79	0	this	a
        //   0	79	1	paramdd	dd
        //   7	62	2	localParcel1	Parcel
        //   3	70	3	localParcel2	Parcel
        //   24	38	4	localIBinder	IBinder
        //   66	11	4	localObject	Object
        // Exception table:
        //   from	to	target	type
        //   8	51	66	finally
      }
      
      /* Error */
      public void a(dh paramdh, String paramString)
        throws RemoteException
      {
        // Byte code:
        //   0: invokestatic 28	android/os/Parcel:obtain	()Landroid/os/Parcel;
        //   3: astore 4
        //   5: invokestatic 28	android/os/Parcel:obtain	()Landroid/os/Parcel;
        //   8: astore_3
        //   9: aload 4
        //   11: ldc 30
        //   13: invokevirtual 34	android/os/Parcel:writeInterfaceToken	(Ljava/lang/String;)V
        //   16: aload_1
        //   17: ifnull +54 -> 71
        //   20: aload_1
        //   21: invokeinterface 104 1 0
        //   26: astore 5
        //   28: aload 4
        //   30: aload 5
        //   32: invokevirtual 92	android/os/Parcel:writeStrongBinder	(Landroid/os/IBinder;)V
        //   35: aload 4
        //   37: aload_2
        //   38: invokevirtual 107	android/os/Parcel:writeString	(Ljava/lang/String;)V
        //   41: aload_0
        //   42: getfield 18	com/google/android/gms/internal/ar$a$a:ko	Landroid/os/IBinder;
        //   45: bipush 15
        //   47: aload 4
        //   49: aload_3
        //   50: iconst_0
        //   51: invokeinterface 40 5 0
        //   56: pop
        //   57: aload_3
        //   58: invokevirtual 43	android/os/Parcel:readException	()V
        //   61: aload_3
        //   62: invokevirtual 56	android/os/Parcel:recycle	()V
        //   65: aload 4
        //   67: invokevirtual 56	android/os/Parcel:recycle	()V
        //   70: return
        //   71: aconst_null
        //   72: astore 5
        //   74: goto -46 -> 28
        //   77: astore 5
        //   79: aload_3
        //   80: invokevirtual 56	android/os/Parcel:recycle	()V
        //   83: aload 4
        //   85: invokevirtual 56	android/os/Parcel:recycle	()V
        //   88: aload 5
        //   90: athrow
        // Local variable table:
        //   start	length	slot	name	signature
        //   0	91	0	this	a
        //   0	91	1	paramdh	dh
        //   0	91	2	paramString	String
        //   8	72	3	localParcel1	Parcel
        //   3	81	4	localParcel2	Parcel
        //   26	47	5	localIBinder	IBinder
        //   77	12	5	localObject	Object
        // Exception table:
        //   from	to	target	type
        //   9	61	77	finally
      }
      
      public boolean a(aj paramaj)
        throws RemoteException
      {
        boolean bool = true;
        Parcel localParcel2 = Parcel.obtain();
        Parcel localParcel1 = Parcel.obtain();
        for (;;)
        {
          try
          {
            localParcel2.writeInterfaceToken("com.google.android.gms.ads.internal.client.IAdManager");
            if (paramaj != null)
            {
              localParcel2.writeInt(1);
              paramaj.writeToParcel(localParcel2, 0);
              this.ko.transact(4, localParcel2, localParcel1, 0);
              localParcel1.readException();
              int i = localParcel1.readInt();
              if (i != 0) {
                return bool;
              }
            }
            else
            {
              localParcel2.writeInt(0);
              continue;
            }
            bool = false;
          }
          finally
          {
            localParcel1.recycle();
            localParcel2.recycle();
          }
        }
      }
      
      public void ab()
        throws RemoteException
      {
        Parcel localParcel2 = Parcel.obtain();
        Parcel localParcel1 = Parcel.obtain();
        try
        {
          localParcel2.writeInterfaceToken("com.google.android.gms.ads.internal.client.IAdManager");
          this.ko.transact(11, localParcel2, localParcel1, 0);
          localParcel1.readException();
          return;
        }
        finally
        {
          localParcel1.recycle();
          localParcel2.recycle();
        }
      }
      
      public IBinder asBinder()
      {
        return this.ko;
      }
      
      public void destroy()
        throws RemoteException
      {
        Parcel localParcel1 = Parcel.obtain();
        Parcel localParcel2 = Parcel.obtain();
        try
        {
          localParcel1.writeInterfaceToken("com.google.android.gms.ads.internal.client.IAdManager");
          this.ko.transact(2, localParcel1, localParcel2, 0);
          localParcel2.readException();
          return;
        }
        finally
        {
          localParcel2.recycle();
          localParcel1.recycle();
        }
      }
      
      public boolean isReady()
        throws RemoteException
      {
        boolean bool = false;
        Parcel localParcel1 = Parcel.obtain();
        Parcel localParcel2 = Parcel.obtain();
        try
        {
          localParcel1.writeInterfaceToken("com.google.android.gms.ads.internal.client.IAdManager");
          this.ko.transact(3, localParcel1, localParcel2, 0);
          localParcel2.readException();
          int i = localParcel2.readInt();
          if (i != 0) {
            bool = true;
          }
          return bool;
        }
        finally
        {
          localParcel2.recycle();
          localParcel1.recycle();
        }
      }
      
      public void pause()
        throws RemoteException
      {
        Parcel localParcel2 = Parcel.obtain();
        Parcel localParcel1 = Parcel.obtain();
        try
        {
          localParcel2.writeInterfaceToken("com.google.android.gms.ads.internal.client.IAdManager");
          this.ko.transact(5, localParcel2, localParcel1, 0);
          localParcel1.readException();
          return;
        }
        finally
        {
          localParcel1.recycle();
          localParcel2.recycle();
        }
      }
      
      public void resume()
        throws RemoteException
      {
        Parcel localParcel2 = Parcel.obtain();
        Parcel localParcel1 = Parcel.obtain();
        try
        {
          localParcel2.writeInterfaceToken("com.google.android.gms.ads.internal.client.IAdManager");
          this.ko.transact(6, localParcel2, localParcel1, 0);
          localParcel1.readException();
          return;
        }
        finally
        {
          localParcel1.recycle();
          localParcel2.recycle();
        }
      }
      
      public void showInterstitial()
        throws RemoteException
      {
        Parcel localParcel1 = Parcel.obtain();
        Parcel localParcel2 = Parcel.obtain();
        try
        {
          localParcel1.writeInterfaceToken("com.google.android.gms.ads.internal.client.IAdManager");
          this.ko.transact(9, localParcel1, localParcel2, 0);
          localParcel2.readException();
          return;
        }
        finally
        {
          localParcel2.recycle();
          localParcel1.recycle();
        }
      }
      
      public void stopLoading()
        throws RemoteException
      {
        Parcel localParcel1 = Parcel.obtain();
        Parcel localParcel2 = Parcel.obtain();
        try
        {
          localParcel1.writeInterfaceToken("com.google.android.gms.ads.internal.client.IAdManager");
          this.ko.transact(10, localParcel1, localParcel2, 0);
          localParcel2.readException();
          return;
        }
        finally
        {
          localParcel2.recycle();
          localParcel1.recycle();
        }
      }
    }
  }
}


/* Location:           E:\android\Androidvn\dex2jar\classes_dex2jar.jar
 * Qualified Name:     com.google.android.gms.internal.ar
 * JD-Core Version:    0.7.0.1
 */