package com.google.android.gms.internal;

import android.os.Binder;
import android.os.Bundle;
import android.os.IBinder;
import android.os.IInterface;
import android.os.Parcel;
import android.os.Parcelable.Creator;
import android.os.RemoteException;

public abstract interface hj
  extends IInterface
{
  public abstract void a(hi paramhi, int paramInt)
    throws RemoteException;
  
  public abstract void a(hi paramhi, int paramInt, String paramString)
    throws RemoteException;
  
  public abstract void a(hi paramhi, int paramInt, String paramString, Bundle paramBundle)
    throws RemoteException;
  
  public abstract void a(hi paramhi, int paramInt, String paramString, IBinder paramIBinder, Bundle paramBundle)
    throws RemoteException;
  
  public abstract void a(hi paramhi, int paramInt, String paramString1, String paramString2)
    throws RemoteException;
  
  public abstract void a(hi paramhi, int paramInt, String paramString1, String paramString2, String paramString3, String[] paramArrayOfString)
    throws RemoteException;
  
  public abstract void a(hi paramhi, int paramInt, String paramString1, String paramString2, String[] paramArrayOfString)
    throws RemoteException;
  
  public abstract void a(hi paramhi, int paramInt, String paramString1, String paramString2, String[] paramArrayOfString, Bundle paramBundle)
    throws RemoteException;
  
  public abstract void a(hi paramhi, int paramInt, String paramString1, String paramString2, String[] paramArrayOfString, String paramString3, Bundle paramBundle)
    throws RemoteException;
  
  public abstract void a(hi paramhi, int paramInt, String paramString1, String paramString2, String[] paramArrayOfString, String paramString3, IBinder paramIBinder, String paramString4, Bundle paramBundle)
    throws RemoteException;
  
  public abstract void a(hi paramhi, int paramInt, String paramString1, String[] paramArrayOfString, String paramString2, Bundle paramBundle)
    throws RemoteException;
  
  public abstract void b(hi paramhi, int paramInt, String paramString)
    throws RemoteException;
  
  public abstract void b(hi paramhi, int paramInt, String paramString, Bundle paramBundle)
    throws RemoteException;
  
  public abstract void b(hi paramhi, int paramInt, String paramString1, String paramString2, String[] paramArrayOfString)
    throws RemoteException;
  
  public abstract void c(hi paramhi, int paramInt, String paramString)
    throws RemoteException;
  
  public abstract void c(hi paramhi, int paramInt, String paramString, Bundle paramBundle)
    throws RemoteException;
  
  public abstract void d(hi paramhi, int paramInt, String paramString)
    throws RemoteException;
  
  public abstract void d(hi paramhi, int paramInt, String paramString, Bundle paramBundle)
    throws RemoteException;
  
  public abstract void e(hi paramhi, int paramInt, String paramString)
    throws RemoteException;
  
  public abstract void e(hi paramhi, int paramInt, String paramString, Bundle paramBundle)
    throws RemoteException;
  
  public abstract void f(hi paramhi, int paramInt, String paramString)
    throws RemoteException;
  
  public abstract void f(hi paramhi, int paramInt, String paramString, Bundle paramBundle)
    throws RemoteException;
  
  public abstract void g(hi paramhi, int paramInt, String paramString)
    throws RemoteException;
  
  public abstract void g(hi paramhi, int paramInt, String paramString, Bundle paramBundle)
    throws RemoteException;
  
  public abstract void h(hi paramhi, int paramInt, String paramString)
    throws RemoteException;
  
  public abstract void h(hi paramhi, int paramInt, String paramString, Bundle paramBundle)
    throws RemoteException;
  
  public abstract void i(hi paramhi, int paramInt, String paramString)
    throws RemoteException;
  
  public abstract void i(hi paramhi, int paramInt, String paramString, Bundle paramBundle)
    throws RemoteException;
  
  public abstract void j(hi paramhi, int paramInt, String paramString, Bundle paramBundle)
    throws RemoteException;
  
  public abstract void k(hi paramhi, int paramInt, String paramString, Bundle paramBundle)
    throws RemoteException;
  
  public abstract void l(hi paramhi, int paramInt, String paramString, Bundle paramBundle)
    throws RemoteException;
  
  public abstract void m(hi paramhi, int paramInt, String paramString, Bundle paramBundle)
    throws RemoteException;
  
  public abstract void n(hi paramhi, int paramInt, String paramString, Bundle paramBundle)
    throws RemoteException;
  
  public abstract void o(hi paramhi, int paramInt, String paramString, Bundle paramBundle)
    throws RemoteException;
  
  public abstract void p(hi paramhi, int paramInt, String paramString, Bundle paramBundle)
    throws RemoteException;
  
  public static abstract class a
    extends Binder
    implements hj
  {
    public static hj L(IBinder paramIBinder)
    {
      Object localObject;
      if (paramIBinder != null)
      {
        localObject = paramIBinder.queryLocalInterface("com.google.android.gms.common.internal.IGmsServiceBroker");
        if ((localObject == null) || (!(localObject instanceof hj))) {
          localObject = new a(paramIBinder);
        } else {
          localObject = (hj)localObject;
        }
      }
      else
      {
        localObject = null;
      }
      return localObject;
    }
    
    public boolean onTransact(int paramInt1, Parcel paramParcel1, Parcel paramParcel2, int paramInt2)
      throws RemoteException
    {
      Object localObject1 = null;
      String str4;
      Object localObject8;
      Object localObject10;
      Object localObject11;
      int j;
      Object localObject2;
      int i21;
      Object localObject5;
      int i18;
      int i2;
      Object localObject3;
      Object localObject6;
      int i26;
      int i24;
      Object localObject9;
      int i12;
      Object localObject7;
      int i13;
      Object localObject4;
      int i27;
      int i14;
      int i15;
      boolean bool2;
      switch (paramInt1)
      {
      default: 
        boolean bool1 = super.onTransact(paramInt1, paramParcel1, paramParcel2, paramInt2);
        break;
      case 1: 
        paramParcel1.enforceInterface("com.google.android.gms.common.internal.IGmsServiceBroker");
        hi localhi2 = hi.a.K(paramParcel1.readStrongBinder());
        int i16 = paramParcel1.readInt();
        str4 = paramParcel1.readString();
        localObject8 = paramParcel1.readString();
        localObject10 = paramParcel1.createStringArray();
        String str1 = paramParcel1.readString();
        if (paramParcel1.readInt() == 0) {
          localObject11 = null;
        } else {
          localObject11 = (Bundle)Bundle.CREATOR.createFromParcel(paramParcel1);
        }
        a(localhi2, i16, str4, (String)localObject8, (String[])localObject10, str1, (Bundle)localObject11);
        paramParcel2.writeNoException();
        int i = 1;
        break;
      case 2: 
        paramParcel1.enforceInterface("com.google.android.gms.common.internal.IGmsServiceBroker");
        hi localhi1 = hi.a.K(paramParcel1.readStrongBinder());
        int i20 = paramParcel1.readInt();
        localObject8 = paramParcel1.readString();
        Bundle localBundle1;
        if (paramParcel1.readInt() != 0) {
          localBundle1 = (Bundle)Bundle.CREATOR.createFromParcel(paramParcel1);
        }
        a(localhi1, i20, (String)localObject8, localBundle1);
        paramParcel2.writeNoException();
        j = 1;
        break;
      case 3: 
        paramParcel1.enforceInterface("com.google.android.gms.common.internal.IGmsServiceBroker");
        a(hi.a.K(paramParcel1.readStrongBinder()), paramParcel1.readInt(), paramParcel1.readString());
        paramParcel2.writeNoException();
        j = 1;
        break;
      case 4: 
        paramParcel1.enforceInterface("com.google.android.gms.common.internal.IGmsServiceBroker");
        a(hi.a.K(paramParcel1.readStrongBinder()), paramParcel1.readInt());
        paramParcel2.writeNoException();
        j = 1;
        break;
      case 5: 
        paramParcel1.enforceInterface("com.google.android.gms.common.internal.IGmsServiceBroker");
        hi localhi3 = hi.a.K(paramParcel1.readStrongBinder());
        int i17 = paramParcel1.readInt();
        localObject8 = paramParcel1.readString();
        Bundle localBundle2;
        if (paramParcel1.readInt() != 0) {
          localBundle2 = (Bundle)Bundle.CREATOR.createFromParcel(paramParcel1);
        }
        b(localhi3, i17, (String)localObject8, localBundle2);
        paramParcel2.writeNoException();
        int k = 1;
        break;
      case 6: 
        paramParcel1.enforceInterface("com.google.android.gms.common.internal.IGmsServiceBroker");
        localObject2 = hi.a.K(paramParcel1.readStrongBinder());
        i21 = paramParcel1.readInt();
        localObject8 = paramParcel1.readString();
        Bundle localBundle3;
        if (paramParcel1.readInt() != 0) {
          localBundle3 = (Bundle)Bundle.CREATOR.createFromParcel(paramParcel1);
        }
        c((hi)localObject2, i21, (String)localObject8, localBundle3);
        paramParcel2.writeNoException();
        int m = 1;
        break;
      case 7: 
        paramParcel1.enforceInterface("com.google.android.gms.common.internal.IGmsServiceBroker");
        localObject8 = hi.a.K(paramParcel1.readStrongBinder());
        i21 = paramParcel1.readInt();
        localObject2 = paramParcel1.readString();
        Bundle localBundle4;
        if (paramParcel1.readInt() != 0) {
          localBundle4 = (Bundle)Bundle.CREATOR.createFromParcel(paramParcel1);
        }
        d((hi)localObject8, i21, (String)localObject2, localBundle4);
        paramParcel2.writeNoException();
        int n = 1;
        break;
      case 8: 
        paramParcel1.enforceInterface("com.google.android.gms.common.internal.IGmsServiceBroker");
        localObject5 = hi.a.K(paramParcel1.readStrongBinder());
        i18 = paramParcel1.readInt();
        localObject8 = paramParcel1.readString();
        Bundle localBundle5;
        if (paramParcel1.readInt() != 0) {
          localBundle5 = (Bundle)Bundle.CREATOR.createFromParcel(paramParcel1);
        }
        e((hi)localObject5, i18, (String)localObject8, localBundle5);
        paramParcel2.writeNoException();
        int i1 = 1;
        break;
      case 9: 
        paramParcel1.enforceInterface("com.google.android.gms.common.internal.IGmsServiceBroker");
        hi localhi5 = hi.a.K(paramParcel1.readStrongBinder());
        i18 = paramParcel1.readInt();
        localObject10 = paramParcel1.readString();
        String str5 = paramParcel1.readString();
        String[] arrayOfString1 = paramParcel1.createStringArray();
        str4 = paramParcel1.readString();
        localObject11 = paramParcel1.readStrongBinder();
        localObject5 = paramParcel1.readString();
        if (paramParcel1.readInt() == 0) {
          localObject8 = null;
        } else {
          localObject8 = (Bundle)Bundle.CREATOR.createFromParcel(paramParcel1);
        }
        a(localhi5, i18, (String)localObject10, str5, arrayOfString1, str4, (IBinder)localObject11, (String)localObject5, (Bundle)localObject8);
        paramParcel2.writeNoException();
        i2 = 1;
        break;
      case 10: 
        paramParcel1.enforceInterface("com.google.android.gms.common.internal.IGmsServiceBroker");
        a(hi.a.K(paramParcel1.readStrongBinder()), paramParcel1.readInt(), paramParcel1.readString(), paramParcel1.readString(), paramParcel1.createStringArray());
        paramParcel2.writeNoException();
        i2 = 1;
        break;
      case 11: 
        paramParcel1.enforceInterface("com.google.android.gms.common.internal.IGmsServiceBroker");
        localObject8 = hi.a.K(paramParcel1.readStrongBinder());
        int i22 = paramParcel1.readInt();
        localObject3 = paramParcel1.readString();
        Bundle localBundle6;
        if (paramParcel1.readInt() != 0) {
          localBundle6 = (Bundle)Bundle.CREATOR.createFromParcel(paramParcel1);
        }
        f((hi)localObject8, i22, (String)localObject3, localBundle6);
        paramParcel2.writeNoException();
        int i3 = 1;
        break;
      case 12: 
        paramParcel1.enforceInterface("com.google.android.gms.common.internal.IGmsServiceBroker");
        localObject3 = hi.a.K(paramParcel1.readStrongBinder());
        int i25 = paramParcel1.readInt();
        String str2 = paramParcel1.readString();
        Bundle localBundle7;
        if (paramParcel1.readInt() != 0) {
          localBundle7 = (Bundle)Bundle.CREATOR.createFromParcel(paramParcel1);
        }
        g((hi)localObject3, i25, str2, localBundle7);
        paramParcel2.writeNoException();
        int i4 = 1;
        break;
      case 13: 
        paramParcel1.enforceInterface("com.google.android.gms.common.internal.IGmsServiceBroker");
        hi localhi4 = hi.a.K(paramParcel1.readStrongBinder());
        int i23 = paramParcel1.readInt();
        localObject3 = paramParcel1.readString();
        Bundle localBundle8;
        if (paramParcel1.readInt() != 0) {
          localBundle8 = (Bundle)Bundle.CREATOR.createFromParcel(paramParcel1);
        }
        h(localhi4, i23, (String)localObject3, localBundle8);
        paramParcel2.writeNoException();
        int i5 = 1;
        break;
      case 14: 
        paramParcel1.enforceInterface("com.google.android.gms.common.internal.IGmsServiceBroker");
        localObject6 = hi.a.K(paramParcel1.readStrongBinder());
        i26 = paramParcel1.readInt();
        localObject3 = paramParcel1.readString();
        Bundle localBundle9;
        if (paramParcel1.readInt() != 0) {
          localBundle9 = (Bundle)Bundle.CREATOR.createFromParcel(paramParcel1);
        }
        i((hi)localObject6, i26, (String)localObject3, localBundle9);
        paramParcel2.writeNoException();
        int i6 = 1;
        break;
      case 15: 
        paramParcel1.enforceInterface("com.google.android.gms.common.internal.IGmsServiceBroker");
        localObject6 = hi.a.K(paramParcel1.readStrongBinder());
        i26 = paramParcel1.readInt();
        localObject3 = paramParcel1.readString();
        Bundle localBundle10;
        if (paramParcel1.readInt() != 0) {
          localBundle10 = (Bundle)Bundle.CREATOR.createFromParcel(paramParcel1);
        }
        j((hi)localObject6, i26, (String)localObject3, localBundle10);
        paramParcel2.writeNoException();
        int i7 = 1;
        break;
      case 16: 
        paramParcel1.enforceInterface("com.google.android.gms.common.internal.IGmsServiceBroker");
        localObject3 = hi.a.K(paramParcel1.readStrongBinder());
        i26 = paramParcel1.readInt();
        localObject6 = paramParcel1.readString();
        Bundle localBundle11;
        if (paramParcel1.readInt() != 0) {
          localBundle11 = (Bundle)Bundle.CREATOR.createFromParcel(paramParcel1);
        }
        k((hi)localObject3, i26, (String)localObject6, localBundle11);
        paramParcel2.writeNoException();
        int i8 = 1;
        break;
      case 17: 
        paramParcel1.enforceInterface("com.google.android.gms.common.internal.IGmsServiceBroker");
        localObject3 = hi.a.K(paramParcel1.readStrongBinder());
        i24 = paramParcel1.readInt();
        localObject9 = paramParcel1.readString();
        Bundle localBundle12;
        if (paramParcel1.readInt() != 0) {
          localBundle12 = (Bundle)Bundle.CREATOR.createFromParcel(paramParcel1);
        }
        l((hi)localObject3, i24, (String)localObject9, localBundle12);
        paramParcel2.writeNoException();
        int i9 = 1;
        break;
      case 18: 
        paramParcel1.enforceInterface("com.google.android.gms.common.internal.IGmsServiceBroker");
        localObject3 = hi.a.K(paramParcel1.readStrongBinder());
        i24 = paramParcel1.readInt();
        localObject9 = paramParcel1.readString();
        Bundle localBundle13;
        if (paramParcel1.readInt() != 0) {
          localBundle13 = (Bundle)Bundle.CREATOR.createFromParcel(paramParcel1);
        }
        m((hi)localObject3, i24, (String)localObject9, localBundle13);
        paramParcel2.writeNoException();
        int i10 = 1;
        break;
      case 19: 
        paramParcel1.enforceInterface("com.google.android.gms.common.internal.IGmsServiceBroker");
        localObject9 = hi.a.K(paramParcel1.readStrongBinder());
        i24 = paramParcel1.readInt();
        localObject10 = paramParcel1.readString();
        localObject3 = paramParcel1.readStrongBinder();
        Bundle localBundle14;
        if (paramParcel1.readInt() == 0) {
          localBundle14 = null;
        } else {
          localBundle14 = (Bundle)Bundle.CREATOR.createFromParcel(paramParcel1);
        }
        a((hi)localObject9, i24, (String)localObject10, (IBinder)localObject3, localBundle14);
        paramParcel2.writeNoException();
        int i11 = 1;
        break;
      case 20: 
        paramParcel1.enforceInterface("com.google.android.gms.common.internal.IGmsServiceBroker");
        localObject9 = hi.a.K(paramParcel1.readStrongBinder());
        i24 = paramParcel1.readInt();
        str4 = paramParcel1.readString();
        localObject3 = paramParcel1.createStringArray();
        localObject10 = paramParcel1.readString();
        Bundle localBundle15;
        if (paramParcel1.readInt() == 0) {
          localBundle15 = null;
        } else {
          localBundle15 = (Bundle)Bundle.CREATOR.createFromParcel(paramParcel1);
        }
        a((hi)localObject9, i24, str4, (String[])localObject3, (String)localObject10, localBundle15);
        paramParcel2.writeNoException();
        i12 = 1;
        break;
      case 21: 
        paramParcel1.enforceInterface("com.google.android.gms.common.internal.IGmsServiceBroker");
        b(hi.a.K(paramParcel1.readStrongBinder()), paramParcel1.readInt(), paramParcel1.readString());
        paramParcel2.writeNoException();
        i12 = 1;
        break;
      case 22: 
        paramParcel1.enforceInterface("com.google.android.gms.common.internal.IGmsServiceBroker");
        c(hi.a.K(paramParcel1.readStrongBinder()), paramParcel1.readInt(), paramParcel1.readString());
        paramParcel2.writeNoException();
        i12 = 1;
        break;
      case 23: 
        paramParcel1.enforceInterface("com.google.android.gms.common.internal.IGmsServiceBroker");
        localObject7 = hi.a.K(paramParcel1.readStrongBinder());
        int i19 = paramParcel1.readInt();
        localObject9 = paramParcel1.readString();
        Bundle localBundle16;
        if (paramParcel1.readInt() != 0) {
          localBundle16 = (Bundle)Bundle.CREATOR.createFromParcel(paramParcel1);
        }
        n((hi)localObject7, i19, (String)localObject9, localBundle16);
        paramParcel2.writeNoException();
        i13 = 1;
        break;
      case 24: 
        paramParcel1.enforceInterface("com.google.android.gms.common.internal.IGmsServiceBroker");
        d(hi.a.K(paramParcel1.readStrongBinder()), paramParcel1.readInt(), paramParcel1.readString());
        paramParcel2.writeNoException();
        i13 = 1;
        break;
      case 25: 
        paramParcel1.enforceInterface("com.google.android.gms.common.internal.IGmsServiceBroker");
        localObject4 = hi.a.K(paramParcel1.readStrongBinder());
        i27 = paramParcel1.readInt();
        localObject7 = paramParcel1.readString();
        Bundle localBundle17;
        if (paramParcel1.readInt() != 0) {
          localBundle17 = (Bundle)Bundle.CREATOR.createFromParcel(paramParcel1);
        }
        o((hi)localObject4, i27, (String)localObject7, localBundle17);
        paramParcel2.writeNoException();
        i14 = 1;
        break;
      case 26: 
        paramParcel1.enforceInterface("com.google.android.gms.common.internal.IGmsServiceBroker");
        e(hi.a.K(paramParcel1.readStrongBinder()), paramParcel1.readInt(), paramParcel1.readString());
        paramParcel2.writeNoException();
        i14 = 1;
        break;
      case 27: 
        paramParcel1.enforceInterface("com.google.android.gms.common.internal.IGmsServiceBroker");
        localObject4 = hi.a.K(paramParcel1.readStrongBinder());
        i27 = paramParcel1.readInt();
        localObject7 = paramParcel1.readString();
        Bundle localBundle18;
        if (paramParcel1.readInt() != 0) {
          localBundle18 = (Bundle)Bundle.CREATOR.createFromParcel(paramParcel1);
        }
        p((hi)localObject4, i27, (String)localObject7, localBundle18);
        paramParcel2.writeNoException();
        i15 = 1;
        break;
      case 28: 
        paramParcel1.enforceInterface("com.google.android.gms.common.internal.IGmsServiceBroker");
        b(hi.a.K(paramParcel1.readStrongBinder()), paramParcel1.readInt(), paramParcel1.readString(), paramParcel1.readString(), paramParcel1.createStringArray());
        paramParcel2.writeNoException();
        i15 = 1;
        break;
      case 30: 
        paramParcel1.enforceInterface("com.google.android.gms.common.internal.IGmsServiceBroker");
        localObject7 = hi.a.K(paramParcel1.readStrongBinder());
        int i28 = paramParcel1.readInt();
        String str3 = paramParcel1.readString();
        localObject10 = paramParcel1.readString();
        String[] arrayOfString2 = paramParcel1.createStringArray();
        if (paramParcel1.readInt() == 0) {
          localObject4 = null;
        } else {
          localObject4 = (Bundle)Bundle.CREATOR.createFromParcel(paramParcel1);
        }
        a((hi)localObject7, i28, str3, (String)localObject10, arrayOfString2, (Bundle)localObject4);
        paramParcel2.writeNoException();
        bool2 = true;
        break;
      case 31: 
        paramParcel1.enforceInterface("com.google.android.gms.common.internal.IGmsServiceBroker");
        f(hi.a.K(paramParcel1.readStrongBinder()), paramParcel1.readInt(), paramParcel1.readString());
        paramParcel2.writeNoException();
        bool2 = true;
        break;
      case 32: 
        paramParcel1.enforceInterface("com.google.android.gms.common.internal.IGmsServiceBroker");
        g(hi.a.K(paramParcel1.readStrongBinder()), paramParcel1.readInt(), paramParcel1.readString());
        paramParcel2.writeNoException();
        bool2 = true;
        break;
      case 33: 
        paramParcel1.enforceInterface("com.google.android.gms.common.internal.IGmsServiceBroker");
        a(hi.a.K(paramParcel1.readStrongBinder()), paramParcel1.readInt(), paramParcel1.readString(), paramParcel1.readString(), paramParcel1.readString(), paramParcel1.createStringArray());
        paramParcel2.writeNoException();
        bool2 = true;
        break;
      case 34: 
        paramParcel1.enforceInterface("com.google.android.gms.common.internal.IGmsServiceBroker");
        a(hi.a.K(paramParcel1.readStrongBinder()), paramParcel1.readInt(), paramParcel1.readString(), paramParcel1.readString());
        paramParcel2.writeNoException();
        bool2 = true;
        break;
      case 35: 
        paramParcel1.enforceInterface("com.google.android.gms.common.internal.IGmsServiceBroker");
        h(hi.a.K(paramParcel1.readStrongBinder()), paramParcel1.readInt(), paramParcel1.readString());
        paramParcel2.writeNoException();
        bool2 = true;
        break;
      case 36: 
        paramParcel1.enforceInterface("com.google.android.gms.common.internal.IGmsServiceBroker");
        i(hi.a.K(paramParcel1.readStrongBinder()), paramParcel1.readInt(), paramParcel1.readString());
        paramParcel2.writeNoException();
        bool2 = true;
        break;
      case 1598968902: 
        paramParcel2.writeString("com.google.android.gms.common.internal.IGmsServiceBroker");
        bool2 = true;
      }
      return bool2;
    }
    
    private static class a
      implements hj
    {
      private IBinder ko;
      
      a(IBinder paramIBinder)
      {
        this.ko = paramIBinder;
      }
      
      /* Error */
      public void a(hi paramhi, int paramInt)
        throws RemoteException
      {
        // Byte code:
        //   0: invokestatic 27	android/os/Parcel:obtain	()Landroid/os/Parcel;
        //   3: astore_3
        //   4: invokestatic 27	android/os/Parcel:obtain	()Landroid/os/Parcel;
        //   7: astore 4
        //   9: aload_3
        //   10: ldc 29
        //   12: invokevirtual 33	android/os/Parcel:writeInterfaceToken	(Ljava/lang/String;)V
        //   15: aload_1
        //   16: ifnull +52 -> 68
        //   19: aload_1
        //   20: invokeinterface 39 1 0
        //   25: astore 5
        //   27: aload_3
        //   28: aload 5
        //   30: invokevirtual 42	android/os/Parcel:writeStrongBinder	(Landroid/os/IBinder;)V
        //   33: aload_3
        //   34: iload_2
        //   35: invokevirtual 46	android/os/Parcel:writeInt	(I)V
        //   38: aload_0
        //   39: getfield 18	com/google/android/gms/internal/hj$a$a:ko	Landroid/os/IBinder;
        //   42: iconst_4
        //   43: aload_3
        //   44: aload 4
        //   46: iconst_0
        //   47: invokeinterface 52 5 0
        //   52: pop
        //   53: aload 4
        //   55: invokevirtual 55	android/os/Parcel:readException	()V
        //   58: aload 4
        //   60: invokevirtual 58	android/os/Parcel:recycle	()V
        //   63: aload_3
        //   64: invokevirtual 58	android/os/Parcel:recycle	()V
        //   67: return
        //   68: aconst_null
        //   69: astore 5
        //   71: goto -44 -> 27
        //   74: astore 5
        //   76: aload 4
        //   78: invokevirtual 58	android/os/Parcel:recycle	()V
        //   81: aload_3
        //   82: invokevirtual 58	android/os/Parcel:recycle	()V
        //   85: aload 5
        //   87: athrow
        // Local variable table:
        //   start	length	slot	name	signature
        //   0	88	0	this	a
        //   0	88	1	paramhi	hi
        //   0	88	2	paramInt	int
        //   3	79	3	localParcel1	Parcel
        //   7	70	4	localParcel2	Parcel
        //   25	45	5	localIBinder	IBinder
        //   74	12	5	localObject	Object
        // Exception table:
        //   from	to	target	type
        //   9	58	74	finally
      }
      
      /* Error */
      public void a(hi paramhi, int paramInt, String paramString)
        throws RemoteException
      {
        // Byte code:
        //   0: invokestatic 27	android/os/Parcel:obtain	()Landroid/os/Parcel;
        //   3: astore 4
        //   5: invokestatic 27	android/os/Parcel:obtain	()Landroid/os/Parcel;
        //   8: astore 5
        //   10: aload 4
        //   12: ldc 29
        //   14: invokevirtual 33	android/os/Parcel:writeInterfaceToken	(Ljava/lang/String;)V
        //   17: aload_1
        //   18: ifnull +62 -> 80
        //   21: aload_1
        //   22: invokeinterface 39 1 0
        //   27: astore 6
        //   29: aload 4
        //   31: aload 6
        //   33: invokevirtual 42	android/os/Parcel:writeStrongBinder	(Landroid/os/IBinder;)V
        //   36: aload 4
        //   38: iload_2
        //   39: invokevirtual 46	android/os/Parcel:writeInt	(I)V
        //   42: aload 4
        //   44: aload_3
        //   45: invokevirtual 62	android/os/Parcel:writeString	(Ljava/lang/String;)V
        //   48: aload_0
        //   49: getfield 18	com/google/android/gms/internal/hj$a$a:ko	Landroid/os/IBinder;
        //   52: iconst_3
        //   53: aload 4
        //   55: aload 5
        //   57: iconst_0
        //   58: invokeinterface 52 5 0
        //   63: pop
        //   64: aload 5
        //   66: invokevirtual 55	android/os/Parcel:readException	()V
        //   69: aload 5
        //   71: invokevirtual 58	android/os/Parcel:recycle	()V
        //   74: aload 4
        //   76: invokevirtual 58	android/os/Parcel:recycle	()V
        //   79: return
        //   80: aconst_null
        //   81: astore 6
        //   83: goto -54 -> 29
        //   86: astore 6
        //   88: aload 5
        //   90: invokevirtual 58	android/os/Parcel:recycle	()V
        //   93: aload 4
        //   95: invokevirtual 58	android/os/Parcel:recycle	()V
        //   98: aload 6
        //   100: athrow
        // Local variable table:
        //   start	length	slot	name	signature
        //   0	101	0	this	a
        //   0	101	1	paramhi	hi
        //   0	101	2	paramInt	int
        //   0	101	3	paramString	String
        //   3	91	4	localParcel1	Parcel
        //   8	81	5	localParcel2	Parcel
        //   27	55	6	localIBinder	IBinder
        //   86	13	6	localObject	Object
        // Exception table:
        //   from	to	target	type
        //   10	69	86	finally
      }
      
      /* Error */
      public void a(hi paramhi, int paramInt, String paramString, Bundle paramBundle)
        throws RemoteException
      {
        // Byte code:
        //   0: invokestatic 27	android/os/Parcel:obtain	()Landroid/os/Parcel;
        //   3: astore 5
        //   5: invokestatic 27	android/os/Parcel:obtain	()Landroid/os/Parcel;
        //   8: astore 6
        //   10: aload 5
        //   12: ldc 29
        //   14: invokevirtual 33	android/os/Parcel:writeInterfaceToken	(Ljava/lang/String;)V
        //   17: aload_1
        //   18: ifnull +81 -> 99
        //   21: aload_1
        //   22: invokeinterface 39 1 0
        //   27: astore 7
        //   29: aload 5
        //   31: aload 7
        //   33: invokevirtual 42	android/os/Parcel:writeStrongBinder	(Landroid/os/IBinder;)V
        //   36: aload 5
        //   38: iload_2
        //   39: invokevirtual 46	android/os/Parcel:writeInt	(I)V
        //   42: aload 5
        //   44: aload_3
        //   45: invokevirtual 62	android/os/Parcel:writeString	(Ljava/lang/String;)V
        //   48: aload 4
        //   50: ifnull +55 -> 105
        //   53: aload 5
        //   55: iconst_1
        //   56: invokevirtual 46	android/os/Parcel:writeInt	(I)V
        //   59: aload 4
        //   61: aload 5
        //   63: iconst_0
        //   64: invokevirtual 69	android/os/Bundle:writeToParcel	(Landroid/os/Parcel;I)V
        //   67: aload_0
        //   68: getfield 18	com/google/android/gms/internal/hj$a$a:ko	Landroid/os/IBinder;
        //   71: iconst_2
        //   72: aload 5
        //   74: aload 6
        //   76: iconst_0
        //   77: invokeinterface 52 5 0
        //   82: pop
        //   83: aload 6
        //   85: invokevirtual 55	android/os/Parcel:readException	()V
        //   88: aload 6
        //   90: invokevirtual 58	android/os/Parcel:recycle	()V
        //   93: aload 5
        //   95: invokevirtual 58	android/os/Parcel:recycle	()V
        //   98: return
        //   99: aconst_null
        //   100: astore 7
        //   102: goto -73 -> 29
        //   105: aload 5
        //   107: iconst_0
        //   108: invokevirtual 46	android/os/Parcel:writeInt	(I)V
        //   111: goto -44 -> 67
        //   114: astore 7
        //   116: aload 6
        //   118: invokevirtual 58	android/os/Parcel:recycle	()V
        //   121: aload 5
        //   123: invokevirtual 58	android/os/Parcel:recycle	()V
        //   126: aload 7
        //   128: athrow
        // Local variable table:
        //   start	length	slot	name	signature
        //   0	129	0	this	a
        //   0	129	1	paramhi	hi
        //   0	129	2	paramInt	int
        //   0	129	3	paramString	String
        //   0	129	4	paramBundle	Bundle
        //   3	119	5	localParcel1	Parcel
        //   8	109	6	localParcel2	Parcel
        //   27	74	7	localIBinder	IBinder
        //   114	13	7	localObject	Object
        // Exception table:
        //   from	to	target	type
        //   10	88	114	finally
        //   105	111	114	finally
      }
      
      /* Error */
      public void a(hi paramhi, int paramInt, String paramString, IBinder paramIBinder, Bundle paramBundle)
        throws RemoteException
      {
        // Byte code:
        //   0: invokestatic 27	android/os/Parcel:obtain	()Landroid/os/Parcel;
        //   3: astore 7
        //   5: invokestatic 27	android/os/Parcel:obtain	()Landroid/os/Parcel;
        //   8: astore 6
        //   10: aload 7
        //   12: ldc 29
        //   14: invokevirtual 33	android/os/Parcel:writeInterfaceToken	(Ljava/lang/String;)V
        //   17: aload_1
        //   18: ifnull +89 -> 107
        //   21: aload_1
        //   22: invokeinterface 39 1 0
        //   27: astore 8
        //   29: aload 7
        //   31: aload 8
        //   33: invokevirtual 42	android/os/Parcel:writeStrongBinder	(Landroid/os/IBinder;)V
        //   36: aload 7
        //   38: iload_2
        //   39: invokevirtual 46	android/os/Parcel:writeInt	(I)V
        //   42: aload 7
        //   44: aload_3
        //   45: invokevirtual 62	android/os/Parcel:writeString	(Ljava/lang/String;)V
        //   48: aload 7
        //   50: aload 4
        //   52: invokevirtual 42	android/os/Parcel:writeStrongBinder	(Landroid/os/IBinder;)V
        //   55: aload 5
        //   57: ifnull +56 -> 113
        //   60: aload 7
        //   62: iconst_1
        //   63: invokevirtual 46	android/os/Parcel:writeInt	(I)V
        //   66: aload 5
        //   68: aload 7
        //   70: iconst_0
        //   71: invokevirtual 69	android/os/Bundle:writeToParcel	(Landroid/os/Parcel;I)V
        //   74: aload_0
        //   75: getfield 18	com/google/android/gms/internal/hj$a$a:ko	Landroid/os/IBinder;
        //   78: bipush 19
        //   80: aload 7
        //   82: aload 6
        //   84: iconst_0
        //   85: invokeinterface 52 5 0
        //   90: pop
        //   91: aload 6
        //   93: invokevirtual 55	android/os/Parcel:readException	()V
        //   96: aload 6
        //   98: invokevirtual 58	android/os/Parcel:recycle	()V
        //   101: aload 7
        //   103: invokevirtual 58	android/os/Parcel:recycle	()V
        //   106: return
        //   107: aconst_null
        //   108: astore 8
        //   110: goto -81 -> 29
        //   113: aload 7
        //   115: iconst_0
        //   116: invokevirtual 46	android/os/Parcel:writeInt	(I)V
        //   119: goto -45 -> 74
        //   122: astore 8
        //   124: aload 6
        //   126: invokevirtual 58	android/os/Parcel:recycle	()V
        //   129: aload 7
        //   131: invokevirtual 58	android/os/Parcel:recycle	()V
        //   134: aload 8
        //   136: athrow
        // Local variable table:
        //   start	length	slot	name	signature
        //   0	137	0	this	a
        //   0	137	1	paramhi	hi
        //   0	137	2	paramInt	int
        //   0	137	3	paramString	String
        //   0	137	4	paramIBinder	IBinder
        //   0	137	5	paramBundle	Bundle
        //   8	117	6	localParcel1	Parcel
        //   3	127	7	localParcel2	Parcel
        //   27	82	8	localIBinder	IBinder
        //   122	13	8	localObject	Object
        // Exception table:
        //   from	to	target	type
        //   10	96	122	finally
        //   113	119	122	finally
      }
      
      /* Error */
      public void a(hi paramhi, int paramInt, String paramString1, String paramString2)
        throws RemoteException
      {
        // Byte code:
        //   0: invokestatic 27	android/os/Parcel:obtain	()Landroid/os/Parcel;
        //   3: astore 6
        //   5: invokestatic 27	android/os/Parcel:obtain	()Landroid/os/Parcel;
        //   8: astore 5
        //   10: aload 6
        //   12: ldc 29
        //   14: invokevirtual 33	android/os/Parcel:writeInterfaceToken	(Ljava/lang/String;)V
        //   17: aload_1
        //   18: ifnull +70 -> 88
        //   21: aload_1
        //   22: invokeinterface 39 1 0
        //   27: astore 7
        //   29: aload 6
        //   31: aload 7
        //   33: invokevirtual 42	android/os/Parcel:writeStrongBinder	(Landroid/os/IBinder;)V
        //   36: aload 6
        //   38: iload_2
        //   39: invokevirtual 46	android/os/Parcel:writeInt	(I)V
        //   42: aload 6
        //   44: aload_3
        //   45: invokevirtual 62	android/os/Parcel:writeString	(Ljava/lang/String;)V
        //   48: aload 6
        //   50: aload 4
        //   52: invokevirtual 62	android/os/Parcel:writeString	(Ljava/lang/String;)V
        //   55: aload_0
        //   56: getfield 18	com/google/android/gms/internal/hj$a$a:ko	Landroid/os/IBinder;
        //   59: bipush 34
        //   61: aload 6
        //   63: aload 5
        //   65: iconst_0
        //   66: invokeinterface 52 5 0
        //   71: pop
        //   72: aload 5
        //   74: invokevirtual 55	android/os/Parcel:readException	()V
        //   77: aload 5
        //   79: invokevirtual 58	android/os/Parcel:recycle	()V
        //   82: aload 6
        //   84: invokevirtual 58	android/os/Parcel:recycle	()V
        //   87: return
        //   88: aconst_null
        //   89: astore 7
        //   91: goto -62 -> 29
        //   94: astore 7
        //   96: aload 5
        //   98: invokevirtual 58	android/os/Parcel:recycle	()V
        //   101: aload 6
        //   103: invokevirtual 58	android/os/Parcel:recycle	()V
        //   106: aload 7
        //   108: athrow
        // Local variable table:
        //   start	length	slot	name	signature
        //   0	109	0	this	a
        //   0	109	1	paramhi	hi
        //   0	109	2	paramInt	int
        //   0	109	3	paramString1	String
        //   0	109	4	paramString2	String
        //   8	89	5	localParcel1	Parcel
        //   3	99	6	localParcel2	Parcel
        //   27	63	7	localIBinder	IBinder
        //   94	13	7	localObject	Object
        // Exception table:
        //   from	to	target	type
        //   10	77	94	finally
      }
      
      /* Error */
      public void a(hi paramhi, int paramInt, String paramString1, String paramString2, String paramString3, String[] paramArrayOfString)
        throws RemoteException
      {
        // Byte code:
        //   0: invokestatic 27	android/os/Parcel:obtain	()Landroid/os/Parcel;
        //   3: astore 7
        //   5: invokestatic 27	android/os/Parcel:obtain	()Landroid/os/Parcel;
        //   8: astore 8
        //   10: aload 7
        //   12: ldc 29
        //   14: invokevirtual 33	android/os/Parcel:writeInterfaceToken	(Ljava/lang/String;)V
        //   17: aload_1
        //   18: ifnull +84 -> 102
        //   21: aload_1
        //   22: invokeinterface 39 1 0
        //   27: astore 9
        //   29: aload 7
        //   31: aload 9
        //   33: invokevirtual 42	android/os/Parcel:writeStrongBinder	(Landroid/os/IBinder;)V
        //   36: aload 7
        //   38: iload_2
        //   39: invokevirtual 46	android/os/Parcel:writeInt	(I)V
        //   42: aload 7
        //   44: aload_3
        //   45: invokevirtual 62	android/os/Parcel:writeString	(Ljava/lang/String;)V
        //   48: aload 7
        //   50: aload 4
        //   52: invokevirtual 62	android/os/Parcel:writeString	(Ljava/lang/String;)V
        //   55: aload 7
        //   57: aload 5
        //   59: invokevirtual 62	android/os/Parcel:writeString	(Ljava/lang/String;)V
        //   62: aload 7
        //   64: aload 6
        //   66: invokevirtual 76	android/os/Parcel:writeStringArray	([Ljava/lang/String;)V
        //   69: aload_0
        //   70: getfield 18	com/google/android/gms/internal/hj$a$a:ko	Landroid/os/IBinder;
        //   73: bipush 33
        //   75: aload 7
        //   77: aload 8
        //   79: iconst_0
        //   80: invokeinterface 52 5 0
        //   85: pop
        //   86: aload 8
        //   88: invokevirtual 55	android/os/Parcel:readException	()V
        //   91: aload 8
        //   93: invokevirtual 58	android/os/Parcel:recycle	()V
        //   96: aload 7
        //   98: invokevirtual 58	android/os/Parcel:recycle	()V
        //   101: return
        //   102: aconst_null
        //   103: astore 9
        //   105: goto -76 -> 29
        //   108: astore 9
        //   110: aload 8
        //   112: invokevirtual 58	android/os/Parcel:recycle	()V
        //   115: aload 7
        //   117: invokevirtual 58	android/os/Parcel:recycle	()V
        //   120: aload 9
        //   122: athrow
        // Local variable table:
        //   start	length	slot	name	signature
        //   0	123	0	this	a
        //   0	123	1	paramhi	hi
        //   0	123	2	paramInt	int
        //   0	123	3	paramString1	String
        //   0	123	4	paramString2	String
        //   0	123	5	paramString3	String
        //   0	123	6	paramArrayOfString	String[]
        //   3	113	7	localParcel1	Parcel
        //   8	103	8	localParcel2	Parcel
        //   27	77	9	localIBinder	IBinder
        //   108	13	9	localObject	Object
        // Exception table:
        //   from	to	target	type
        //   10	91	108	finally
      }
      
      /* Error */
      public void a(hi paramhi, int paramInt, String paramString1, String paramString2, String[] paramArrayOfString)
        throws RemoteException
      {
        // Byte code:
        //   0: invokestatic 27	android/os/Parcel:obtain	()Landroid/os/Parcel;
        //   3: astore 6
        //   5: invokestatic 27	android/os/Parcel:obtain	()Landroid/os/Parcel;
        //   8: astore 7
        //   10: aload 6
        //   12: ldc 29
        //   14: invokevirtual 33	android/os/Parcel:writeInterfaceToken	(Ljava/lang/String;)V
        //   17: aload_1
        //   18: ifnull +77 -> 95
        //   21: aload_1
        //   22: invokeinterface 39 1 0
        //   27: astore 8
        //   29: aload 6
        //   31: aload 8
        //   33: invokevirtual 42	android/os/Parcel:writeStrongBinder	(Landroid/os/IBinder;)V
        //   36: aload 6
        //   38: iload_2
        //   39: invokevirtual 46	android/os/Parcel:writeInt	(I)V
        //   42: aload 6
        //   44: aload_3
        //   45: invokevirtual 62	android/os/Parcel:writeString	(Ljava/lang/String;)V
        //   48: aload 6
        //   50: aload 4
        //   52: invokevirtual 62	android/os/Parcel:writeString	(Ljava/lang/String;)V
        //   55: aload 6
        //   57: aload 5
        //   59: invokevirtual 76	android/os/Parcel:writeStringArray	([Ljava/lang/String;)V
        //   62: aload_0
        //   63: getfield 18	com/google/android/gms/internal/hj$a$a:ko	Landroid/os/IBinder;
        //   66: bipush 10
        //   68: aload 6
        //   70: aload 7
        //   72: iconst_0
        //   73: invokeinterface 52 5 0
        //   78: pop
        //   79: aload 7
        //   81: invokevirtual 55	android/os/Parcel:readException	()V
        //   84: aload 7
        //   86: invokevirtual 58	android/os/Parcel:recycle	()V
        //   89: aload 6
        //   91: invokevirtual 58	android/os/Parcel:recycle	()V
        //   94: return
        //   95: aconst_null
        //   96: astore 8
        //   98: goto -69 -> 29
        //   101: astore 8
        //   103: aload 7
        //   105: invokevirtual 58	android/os/Parcel:recycle	()V
        //   108: aload 6
        //   110: invokevirtual 58	android/os/Parcel:recycle	()V
        //   113: aload 8
        //   115: athrow
        // Local variable table:
        //   start	length	slot	name	signature
        //   0	116	0	this	a
        //   0	116	1	paramhi	hi
        //   0	116	2	paramInt	int
        //   0	116	3	paramString1	String
        //   0	116	4	paramString2	String
        //   0	116	5	paramArrayOfString	String[]
        //   3	106	6	localParcel1	Parcel
        //   8	96	7	localParcel2	Parcel
        //   27	70	8	localIBinder	IBinder
        //   101	13	8	localObject	Object
        // Exception table:
        //   from	to	target	type
        //   10	84	101	finally
      }
      
      /* Error */
      public void a(hi paramhi, int paramInt, String paramString1, String paramString2, String[] paramArrayOfString, Bundle paramBundle)
        throws RemoteException
      {
        // Byte code:
        //   0: invokestatic 27	android/os/Parcel:obtain	()Landroid/os/Parcel;
        //   3: astore 8
        //   5: invokestatic 27	android/os/Parcel:obtain	()Landroid/os/Parcel;
        //   8: astore 7
        //   10: aload 8
        //   12: ldc 29
        //   14: invokevirtual 33	android/os/Parcel:writeInterfaceToken	(Ljava/lang/String;)V
        //   17: aload_1
        //   18: ifnull +96 -> 114
        //   21: aload_1
        //   22: invokeinterface 39 1 0
        //   27: astore 9
        //   29: aload 8
        //   31: aload 9
        //   33: invokevirtual 42	android/os/Parcel:writeStrongBinder	(Landroid/os/IBinder;)V
        //   36: aload 8
        //   38: iload_2
        //   39: invokevirtual 46	android/os/Parcel:writeInt	(I)V
        //   42: aload 8
        //   44: aload_3
        //   45: invokevirtual 62	android/os/Parcel:writeString	(Ljava/lang/String;)V
        //   48: aload 8
        //   50: aload 4
        //   52: invokevirtual 62	android/os/Parcel:writeString	(Ljava/lang/String;)V
        //   55: aload 8
        //   57: aload 5
        //   59: invokevirtual 76	android/os/Parcel:writeStringArray	([Ljava/lang/String;)V
        //   62: aload 6
        //   64: ifnull +56 -> 120
        //   67: aload 8
        //   69: iconst_1
        //   70: invokevirtual 46	android/os/Parcel:writeInt	(I)V
        //   73: aload 6
        //   75: aload 8
        //   77: iconst_0
        //   78: invokevirtual 69	android/os/Bundle:writeToParcel	(Landroid/os/Parcel;I)V
        //   81: aload_0
        //   82: getfield 18	com/google/android/gms/internal/hj$a$a:ko	Landroid/os/IBinder;
        //   85: bipush 30
        //   87: aload 8
        //   89: aload 7
        //   91: iconst_0
        //   92: invokeinterface 52 5 0
        //   97: pop
        //   98: aload 7
        //   100: invokevirtual 55	android/os/Parcel:readException	()V
        //   103: aload 7
        //   105: invokevirtual 58	android/os/Parcel:recycle	()V
        //   108: aload 8
        //   110: invokevirtual 58	android/os/Parcel:recycle	()V
        //   113: return
        //   114: aconst_null
        //   115: astore 9
        //   117: goto -88 -> 29
        //   120: aload 8
        //   122: iconst_0
        //   123: invokevirtual 46	android/os/Parcel:writeInt	(I)V
        //   126: goto -45 -> 81
        //   129: astore 9
        //   131: aload 7
        //   133: invokevirtual 58	android/os/Parcel:recycle	()V
        //   136: aload 8
        //   138: invokevirtual 58	android/os/Parcel:recycle	()V
        //   141: aload 9
        //   143: athrow
        // Local variable table:
        //   start	length	slot	name	signature
        //   0	144	0	this	a
        //   0	144	1	paramhi	hi
        //   0	144	2	paramInt	int
        //   0	144	3	paramString1	String
        //   0	144	4	paramString2	String
        //   0	144	5	paramArrayOfString	String[]
        //   0	144	6	paramBundle	Bundle
        //   8	124	7	localParcel1	Parcel
        //   3	134	8	localParcel2	Parcel
        //   27	89	9	localIBinder	IBinder
        //   129	13	9	localObject	Object
        // Exception table:
        //   from	to	target	type
        //   10	103	129	finally
        //   120	126	129	finally
      }
      
      /* Error */
      public void a(hi paramhi, int paramInt, String paramString1, String paramString2, String[] paramArrayOfString, String paramString3, Bundle paramBundle)
        throws RemoteException
      {
        // Byte code:
        //   0: invokestatic 27	android/os/Parcel:obtain	()Landroid/os/Parcel;
        //   3: astore 8
        //   5: invokestatic 27	android/os/Parcel:obtain	()Landroid/os/Parcel;
        //   8: astore 9
        //   10: aload 8
        //   12: ldc 29
        //   14: invokevirtual 33	android/os/Parcel:writeInterfaceToken	(Ljava/lang/String;)V
        //   17: aload_1
        //   18: ifnull +102 -> 120
        //   21: aload_1
        //   22: invokeinterface 39 1 0
        //   27: astore 10
        //   29: aload 8
        //   31: aload 10
        //   33: invokevirtual 42	android/os/Parcel:writeStrongBinder	(Landroid/os/IBinder;)V
        //   36: aload 8
        //   38: iload_2
        //   39: invokevirtual 46	android/os/Parcel:writeInt	(I)V
        //   42: aload 8
        //   44: aload_3
        //   45: invokevirtual 62	android/os/Parcel:writeString	(Ljava/lang/String;)V
        //   48: aload 8
        //   50: aload 4
        //   52: invokevirtual 62	android/os/Parcel:writeString	(Ljava/lang/String;)V
        //   55: aload 8
        //   57: aload 5
        //   59: invokevirtual 76	android/os/Parcel:writeStringArray	([Ljava/lang/String;)V
        //   62: aload 8
        //   64: aload 6
        //   66: invokevirtual 62	android/os/Parcel:writeString	(Ljava/lang/String;)V
        //   69: aload 7
        //   71: ifnull +55 -> 126
        //   74: aload 8
        //   76: iconst_1
        //   77: invokevirtual 46	android/os/Parcel:writeInt	(I)V
        //   80: aload 7
        //   82: aload 8
        //   84: iconst_0
        //   85: invokevirtual 69	android/os/Bundle:writeToParcel	(Landroid/os/Parcel;I)V
        //   88: aload_0
        //   89: getfield 18	com/google/android/gms/internal/hj$a$a:ko	Landroid/os/IBinder;
        //   92: iconst_1
        //   93: aload 8
        //   95: aload 9
        //   97: iconst_0
        //   98: invokeinterface 52 5 0
        //   103: pop
        //   104: aload 9
        //   106: invokevirtual 55	android/os/Parcel:readException	()V
        //   109: aload 9
        //   111: invokevirtual 58	android/os/Parcel:recycle	()V
        //   114: aload 8
        //   116: invokevirtual 58	android/os/Parcel:recycle	()V
        //   119: return
        //   120: aconst_null
        //   121: astore 10
        //   123: goto -94 -> 29
        //   126: aload 8
        //   128: iconst_0
        //   129: invokevirtual 46	android/os/Parcel:writeInt	(I)V
        //   132: goto -44 -> 88
        //   135: astore 10
        //   137: aload 9
        //   139: invokevirtual 58	android/os/Parcel:recycle	()V
        //   142: aload 8
        //   144: invokevirtual 58	android/os/Parcel:recycle	()V
        //   147: aload 10
        //   149: athrow
        // Local variable table:
        //   start	length	slot	name	signature
        //   0	150	0	this	a
        //   0	150	1	paramhi	hi
        //   0	150	2	paramInt	int
        //   0	150	3	paramString1	String
        //   0	150	4	paramString2	String
        //   0	150	5	paramArrayOfString	String[]
        //   0	150	6	paramString3	String
        //   0	150	7	paramBundle	Bundle
        //   3	140	8	localParcel1	Parcel
        //   8	130	9	localParcel2	Parcel
        //   27	95	10	localIBinder	IBinder
        //   135	13	10	localObject	Object
        // Exception table:
        //   from	to	target	type
        //   10	109	135	finally
        //   126	132	135	finally
      }
      
      /* Error */
      public void a(hi paramhi, int paramInt, String paramString1, String paramString2, String[] paramArrayOfString, String paramString3, IBinder paramIBinder, String paramString4, Bundle paramBundle)
        throws RemoteException
      {
        // Byte code:
        //   0: invokestatic 27	android/os/Parcel:obtain	()Landroid/os/Parcel;
        //   3: astore 11
        //   5: invokestatic 27	android/os/Parcel:obtain	()Landroid/os/Parcel;
        //   8: astore 10
        //   10: aload 11
        //   12: ldc 29
        //   14: invokevirtual 33	android/os/Parcel:writeInterfaceToken	(Ljava/lang/String;)V
        //   17: aload_1
        //   18: ifnull +117 -> 135
        //   21: aload_1
        //   22: invokeinterface 39 1 0
        //   27: astore 12
        //   29: aload 11
        //   31: aload 12
        //   33: invokevirtual 42	android/os/Parcel:writeStrongBinder	(Landroid/os/IBinder;)V
        //   36: aload 11
        //   38: iload_2
        //   39: invokevirtual 46	android/os/Parcel:writeInt	(I)V
        //   42: aload 11
        //   44: aload_3
        //   45: invokevirtual 62	android/os/Parcel:writeString	(Ljava/lang/String;)V
        //   48: aload 11
        //   50: aload 4
        //   52: invokevirtual 62	android/os/Parcel:writeString	(Ljava/lang/String;)V
        //   55: aload 11
        //   57: aload 5
        //   59: invokevirtual 76	android/os/Parcel:writeStringArray	([Ljava/lang/String;)V
        //   62: aload 11
        //   64: aload 6
        //   66: invokevirtual 62	android/os/Parcel:writeString	(Ljava/lang/String;)V
        //   69: aload 11
        //   71: aload 7
        //   73: invokevirtual 42	android/os/Parcel:writeStrongBinder	(Landroid/os/IBinder;)V
        //   76: aload 11
        //   78: aload 8
        //   80: invokevirtual 62	android/os/Parcel:writeString	(Ljava/lang/String;)V
        //   83: aload 9
        //   85: ifnull +56 -> 141
        //   88: aload 11
        //   90: iconst_1
        //   91: invokevirtual 46	android/os/Parcel:writeInt	(I)V
        //   94: aload 9
        //   96: aload 11
        //   98: iconst_0
        //   99: invokevirtual 69	android/os/Bundle:writeToParcel	(Landroid/os/Parcel;I)V
        //   102: aload_0
        //   103: getfield 18	com/google/android/gms/internal/hj$a$a:ko	Landroid/os/IBinder;
        //   106: bipush 9
        //   108: aload 11
        //   110: aload 10
        //   112: iconst_0
        //   113: invokeinterface 52 5 0
        //   118: pop
        //   119: aload 10
        //   121: invokevirtual 55	android/os/Parcel:readException	()V
        //   124: aload 10
        //   126: invokevirtual 58	android/os/Parcel:recycle	()V
        //   129: aload 11
        //   131: invokevirtual 58	android/os/Parcel:recycle	()V
        //   134: return
        //   135: aconst_null
        //   136: astore 12
        //   138: goto -109 -> 29
        //   141: aload 11
        //   143: iconst_0
        //   144: invokevirtual 46	android/os/Parcel:writeInt	(I)V
        //   147: goto -45 -> 102
        //   150: astore 12
        //   152: aload 10
        //   154: invokevirtual 58	android/os/Parcel:recycle	()V
        //   157: aload 11
        //   159: invokevirtual 58	android/os/Parcel:recycle	()V
        //   162: aload 12
        //   164: athrow
        // Local variable table:
        //   start	length	slot	name	signature
        //   0	165	0	this	a
        //   0	165	1	paramhi	hi
        //   0	165	2	paramInt	int
        //   0	165	3	paramString1	String
        //   0	165	4	paramString2	String
        //   0	165	5	paramArrayOfString	String[]
        //   0	165	6	paramString3	String
        //   0	165	7	paramIBinder	IBinder
        //   0	165	8	paramString4	String
        //   0	165	9	paramBundle	Bundle
        //   8	145	10	localParcel1	Parcel
        //   3	155	11	localParcel2	Parcel
        //   27	110	12	localIBinder	IBinder
        //   150	13	12	localObject	Object
        // Exception table:
        //   from	to	target	type
        //   10	124	150	finally
        //   141	147	150	finally
      }
      
      /* Error */
      public void a(hi paramhi, int paramInt, String paramString1, String[] paramArrayOfString, String paramString2, Bundle paramBundle)
        throws RemoteException
      {
        // Byte code:
        //   0: invokestatic 27	android/os/Parcel:obtain	()Landroid/os/Parcel;
        //   3: astore 8
        //   5: invokestatic 27	android/os/Parcel:obtain	()Landroid/os/Parcel;
        //   8: astore 7
        //   10: aload 8
        //   12: ldc 29
        //   14: invokevirtual 33	android/os/Parcel:writeInterfaceToken	(Ljava/lang/String;)V
        //   17: aload_1
        //   18: ifnull +96 -> 114
        //   21: aload_1
        //   22: invokeinterface 39 1 0
        //   27: astore 9
        //   29: aload 8
        //   31: aload 9
        //   33: invokevirtual 42	android/os/Parcel:writeStrongBinder	(Landroid/os/IBinder;)V
        //   36: aload 8
        //   38: iload_2
        //   39: invokevirtual 46	android/os/Parcel:writeInt	(I)V
        //   42: aload 8
        //   44: aload_3
        //   45: invokevirtual 62	android/os/Parcel:writeString	(Ljava/lang/String;)V
        //   48: aload 8
        //   50: aload 4
        //   52: invokevirtual 76	android/os/Parcel:writeStringArray	([Ljava/lang/String;)V
        //   55: aload 8
        //   57: aload 5
        //   59: invokevirtual 62	android/os/Parcel:writeString	(Ljava/lang/String;)V
        //   62: aload 6
        //   64: ifnull +56 -> 120
        //   67: aload 8
        //   69: iconst_1
        //   70: invokevirtual 46	android/os/Parcel:writeInt	(I)V
        //   73: aload 6
        //   75: aload 8
        //   77: iconst_0
        //   78: invokevirtual 69	android/os/Bundle:writeToParcel	(Landroid/os/Parcel;I)V
        //   81: aload_0
        //   82: getfield 18	com/google/android/gms/internal/hj$a$a:ko	Landroid/os/IBinder;
        //   85: bipush 20
        //   87: aload 8
        //   89: aload 7
        //   91: iconst_0
        //   92: invokeinterface 52 5 0
        //   97: pop
        //   98: aload 7
        //   100: invokevirtual 55	android/os/Parcel:readException	()V
        //   103: aload 7
        //   105: invokevirtual 58	android/os/Parcel:recycle	()V
        //   108: aload 8
        //   110: invokevirtual 58	android/os/Parcel:recycle	()V
        //   113: return
        //   114: aconst_null
        //   115: astore 9
        //   117: goto -88 -> 29
        //   120: aload 8
        //   122: iconst_0
        //   123: invokevirtual 46	android/os/Parcel:writeInt	(I)V
        //   126: goto -45 -> 81
        //   129: astore 9
        //   131: aload 7
        //   133: invokevirtual 58	android/os/Parcel:recycle	()V
        //   136: aload 8
        //   138: invokevirtual 58	android/os/Parcel:recycle	()V
        //   141: aload 9
        //   143: athrow
        // Local variable table:
        //   start	length	slot	name	signature
        //   0	144	0	this	a
        //   0	144	1	paramhi	hi
        //   0	144	2	paramInt	int
        //   0	144	3	paramString1	String
        //   0	144	4	paramArrayOfString	String[]
        //   0	144	5	paramString2	String
        //   0	144	6	paramBundle	Bundle
        //   8	124	7	localParcel1	Parcel
        //   3	134	8	localParcel2	Parcel
        //   27	89	9	localIBinder	IBinder
        //   129	13	9	localObject	Object
        // Exception table:
        //   from	to	target	type
        //   10	103	129	finally
        //   120	126	129	finally
      }
      
      public IBinder asBinder()
      {
        return this.ko;
      }
      
      /* Error */
      public void b(hi paramhi, int paramInt, String paramString)
        throws RemoteException
      {
        // Byte code:
        //   0: invokestatic 27	android/os/Parcel:obtain	()Landroid/os/Parcel;
        //   3: astore 4
        //   5: invokestatic 27	android/os/Parcel:obtain	()Landroid/os/Parcel;
        //   8: astore 5
        //   10: aload 4
        //   12: ldc 29
        //   14: invokevirtual 33	android/os/Parcel:writeInterfaceToken	(Ljava/lang/String;)V
        //   17: aload_1
        //   18: ifnull +63 -> 81
        //   21: aload_1
        //   22: invokeinterface 39 1 0
        //   27: astore 6
        //   29: aload 4
        //   31: aload 6
        //   33: invokevirtual 42	android/os/Parcel:writeStrongBinder	(Landroid/os/IBinder;)V
        //   36: aload 4
        //   38: iload_2
        //   39: invokevirtual 46	android/os/Parcel:writeInt	(I)V
        //   42: aload 4
        //   44: aload_3
        //   45: invokevirtual 62	android/os/Parcel:writeString	(Ljava/lang/String;)V
        //   48: aload_0
        //   49: getfield 18	com/google/android/gms/internal/hj$a$a:ko	Landroid/os/IBinder;
        //   52: bipush 21
        //   54: aload 4
        //   56: aload 5
        //   58: iconst_0
        //   59: invokeinterface 52 5 0
        //   64: pop
        //   65: aload 5
        //   67: invokevirtual 55	android/os/Parcel:readException	()V
        //   70: aload 5
        //   72: invokevirtual 58	android/os/Parcel:recycle	()V
        //   75: aload 4
        //   77: invokevirtual 58	android/os/Parcel:recycle	()V
        //   80: return
        //   81: aconst_null
        //   82: astore 6
        //   84: goto -55 -> 29
        //   87: astore 6
        //   89: aload 5
        //   91: invokevirtual 58	android/os/Parcel:recycle	()V
        //   94: aload 4
        //   96: invokevirtual 58	android/os/Parcel:recycle	()V
        //   99: aload 6
        //   101: athrow
        // Local variable table:
        //   start	length	slot	name	signature
        //   0	102	0	this	a
        //   0	102	1	paramhi	hi
        //   0	102	2	paramInt	int
        //   0	102	3	paramString	String
        //   3	92	4	localParcel1	Parcel
        //   8	82	5	localParcel2	Parcel
        //   27	56	6	localIBinder	IBinder
        //   87	13	6	localObject	Object
        // Exception table:
        //   from	to	target	type
        //   10	70	87	finally
      }
      
      /* Error */
      public void b(hi paramhi, int paramInt, String paramString, Bundle paramBundle)
        throws RemoteException
      {
        // Byte code:
        //   0: invokestatic 27	android/os/Parcel:obtain	()Landroid/os/Parcel;
        //   3: astore 6
        //   5: invokestatic 27	android/os/Parcel:obtain	()Landroid/os/Parcel;
        //   8: astore 5
        //   10: aload 6
        //   12: ldc 29
        //   14: invokevirtual 33	android/os/Parcel:writeInterfaceToken	(Ljava/lang/String;)V
        //   17: aload_1
        //   18: ifnull +81 -> 99
        //   21: aload_1
        //   22: invokeinterface 39 1 0
        //   27: astore 7
        //   29: aload 6
        //   31: aload 7
        //   33: invokevirtual 42	android/os/Parcel:writeStrongBinder	(Landroid/os/IBinder;)V
        //   36: aload 6
        //   38: iload_2
        //   39: invokevirtual 46	android/os/Parcel:writeInt	(I)V
        //   42: aload 6
        //   44: aload_3
        //   45: invokevirtual 62	android/os/Parcel:writeString	(Ljava/lang/String;)V
        //   48: aload 4
        //   50: ifnull +55 -> 105
        //   53: aload 6
        //   55: iconst_1
        //   56: invokevirtual 46	android/os/Parcel:writeInt	(I)V
        //   59: aload 4
        //   61: aload 6
        //   63: iconst_0
        //   64: invokevirtual 69	android/os/Bundle:writeToParcel	(Landroid/os/Parcel;I)V
        //   67: aload_0
        //   68: getfield 18	com/google/android/gms/internal/hj$a$a:ko	Landroid/os/IBinder;
        //   71: iconst_5
        //   72: aload 6
        //   74: aload 5
        //   76: iconst_0
        //   77: invokeinterface 52 5 0
        //   82: pop
        //   83: aload 5
        //   85: invokevirtual 55	android/os/Parcel:readException	()V
        //   88: aload 5
        //   90: invokevirtual 58	android/os/Parcel:recycle	()V
        //   93: aload 6
        //   95: invokevirtual 58	android/os/Parcel:recycle	()V
        //   98: return
        //   99: aconst_null
        //   100: astore 7
        //   102: goto -73 -> 29
        //   105: aload 6
        //   107: iconst_0
        //   108: invokevirtual 46	android/os/Parcel:writeInt	(I)V
        //   111: goto -44 -> 67
        //   114: astore 7
        //   116: aload 5
        //   118: invokevirtual 58	android/os/Parcel:recycle	()V
        //   121: aload 6
        //   123: invokevirtual 58	android/os/Parcel:recycle	()V
        //   126: aload 7
        //   128: athrow
        // Local variable table:
        //   start	length	slot	name	signature
        //   0	129	0	this	a
        //   0	129	1	paramhi	hi
        //   0	129	2	paramInt	int
        //   0	129	3	paramString	String
        //   0	129	4	paramBundle	Bundle
        //   8	109	5	localParcel1	Parcel
        //   3	119	6	localParcel2	Parcel
        //   27	74	7	localIBinder	IBinder
        //   114	13	7	localObject	Object
        // Exception table:
        //   from	to	target	type
        //   10	88	114	finally
        //   105	111	114	finally
      }
      
      /* Error */
      public void b(hi paramhi, int paramInt, String paramString1, String paramString2, String[] paramArrayOfString)
        throws RemoteException
      {
        // Byte code:
        //   0: invokestatic 27	android/os/Parcel:obtain	()Landroid/os/Parcel;
        //   3: astore 6
        //   5: invokestatic 27	android/os/Parcel:obtain	()Landroid/os/Parcel;
        //   8: astore 7
        //   10: aload 6
        //   12: ldc 29
        //   14: invokevirtual 33	android/os/Parcel:writeInterfaceToken	(Ljava/lang/String;)V
        //   17: aload_1
        //   18: ifnull +77 -> 95
        //   21: aload_1
        //   22: invokeinterface 39 1 0
        //   27: astore 8
        //   29: aload 6
        //   31: aload 8
        //   33: invokevirtual 42	android/os/Parcel:writeStrongBinder	(Landroid/os/IBinder;)V
        //   36: aload 6
        //   38: iload_2
        //   39: invokevirtual 46	android/os/Parcel:writeInt	(I)V
        //   42: aload 6
        //   44: aload_3
        //   45: invokevirtual 62	android/os/Parcel:writeString	(Ljava/lang/String;)V
        //   48: aload 6
        //   50: aload 4
        //   52: invokevirtual 62	android/os/Parcel:writeString	(Ljava/lang/String;)V
        //   55: aload 6
        //   57: aload 5
        //   59: invokevirtual 76	android/os/Parcel:writeStringArray	([Ljava/lang/String;)V
        //   62: aload_0
        //   63: getfield 18	com/google/android/gms/internal/hj$a$a:ko	Landroid/os/IBinder;
        //   66: bipush 28
        //   68: aload 6
        //   70: aload 7
        //   72: iconst_0
        //   73: invokeinterface 52 5 0
        //   78: pop
        //   79: aload 7
        //   81: invokevirtual 55	android/os/Parcel:readException	()V
        //   84: aload 7
        //   86: invokevirtual 58	android/os/Parcel:recycle	()V
        //   89: aload 6
        //   91: invokevirtual 58	android/os/Parcel:recycle	()V
        //   94: return
        //   95: aconst_null
        //   96: astore 8
        //   98: goto -69 -> 29
        //   101: astore 8
        //   103: aload 7
        //   105: invokevirtual 58	android/os/Parcel:recycle	()V
        //   108: aload 6
        //   110: invokevirtual 58	android/os/Parcel:recycle	()V
        //   113: aload 8
        //   115: athrow
        // Local variable table:
        //   start	length	slot	name	signature
        //   0	116	0	this	a
        //   0	116	1	paramhi	hi
        //   0	116	2	paramInt	int
        //   0	116	3	paramString1	String
        //   0	116	4	paramString2	String
        //   0	116	5	paramArrayOfString	String[]
        //   3	106	6	localParcel1	Parcel
        //   8	96	7	localParcel2	Parcel
        //   27	70	8	localIBinder	IBinder
        //   101	13	8	localObject	Object
        // Exception table:
        //   from	to	target	type
        //   10	84	101	finally
      }
      
      /* Error */
      public void c(hi paramhi, int paramInt, String paramString)
        throws RemoteException
      {
        // Byte code:
        //   0: invokestatic 27	android/os/Parcel:obtain	()Landroid/os/Parcel;
        //   3: astore 4
        //   5: invokestatic 27	android/os/Parcel:obtain	()Landroid/os/Parcel;
        //   8: astore 5
        //   10: aload 4
        //   12: ldc 29
        //   14: invokevirtual 33	android/os/Parcel:writeInterfaceToken	(Ljava/lang/String;)V
        //   17: aload_1
        //   18: ifnull +63 -> 81
        //   21: aload_1
        //   22: invokeinterface 39 1 0
        //   27: astore 6
        //   29: aload 4
        //   31: aload 6
        //   33: invokevirtual 42	android/os/Parcel:writeStrongBinder	(Landroid/os/IBinder;)V
        //   36: aload 4
        //   38: iload_2
        //   39: invokevirtual 46	android/os/Parcel:writeInt	(I)V
        //   42: aload 4
        //   44: aload_3
        //   45: invokevirtual 62	android/os/Parcel:writeString	(Ljava/lang/String;)V
        //   48: aload_0
        //   49: getfield 18	com/google/android/gms/internal/hj$a$a:ko	Landroid/os/IBinder;
        //   52: bipush 22
        //   54: aload 4
        //   56: aload 5
        //   58: iconst_0
        //   59: invokeinterface 52 5 0
        //   64: pop
        //   65: aload 5
        //   67: invokevirtual 55	android/os/Parcel:readException	()V
        //   70: aload 5
        //   72: invokevirtual 58	android/os/Parcel:recycle	()V
        //   75: aload 4
        //   77: invokevirtual 58	android/os/Parcel:recycle	()V
        //   80: return
        //   81: aconst_null
        //   82: astore 6
        //   84: goto -55 -> 29
        //   87: astore 6
        //   89: aload 5
        //   91: invokevirtual 58	android/os/Parcel:recycle	()V
        //   94: aload 4
        //   96: invokevirtual 58	android/os/Parcel:recycle	()V
        //   99: aload 6
        //   101: athrow
        // Local variable table:
        //   start	length	slot	name	signature
        //   0	102	0	this	a
        //   0	102	1	paramhi	hi
        //   0	102	2	paramInt	int
        //   0	102	3	paramString	String
        //   3	92	4	localParcel1	Parcel
        //   8	82	5	localParcel2	Parcel
        //   27	56	6	localIBinder	IBinder
        //   87	13	6	localObject	Object
        // Exception table:
        //   from	to	target	type
        //   10	70	87	finally
      }
      
      /* Error */
      public void c(hi paramhi, int paramInt, String paramString, Bundle paramBundle)
        throws RemoteException
      {
        // Byte code:
        //   0: invokestatic 27	android/os/Parcel:obtain	()Landroid/os/Parcel;
        //   3: astore 6
        //   5: invokestatic 27	android/os/Parcel:obtain	()Landroid/os/Parcel;
        //   8: astore 5
        //   10: aload 6
        //   12: ldc 29
        //   14: invokevirtual 33	android/os/Parcel:writeInterfaceToken	(Ljava/lang/String;)V
        //   17: aload_1
        //   18: ifnull +82 -> 100
        //   21: aload_1
        //   22: invokeinterface 39 1 0
        //   27: astore 7
        //   29: aload 6
        //   31: aload 7
        //   33: invokevirtual 42	android/os/Parcel:writeStrongBinder	(Landroid/os/IBinder;)V
        //   36: aload 6
        //   38: iload_2
        //   39: invokevirtual 46	android/os/Parcel:writeInt	(I)V
        //   42: aload 6
        //   44: aload_3
        //   45: invokevirtual 62	android/os/Parcel:writeString	(Ljava/lang/String;)V
        //   48: aload 4
        //   50: ifnull +56 -> 106
        //   53: aload 6
        //   55: iconst_1
        //   56: invokevirtual 46	android/os/Parcel:writeInt	(I)V
        //   59: aload 4
        //   61: aload 6
        //   63: iconst_0
        //   64: invokevirtual 69	android/os/Bundle:writeToParcel	(Landroid/os/Parcel;I)V
        //   67: aload_0
        //   68: getfield 18	com/google/android/gms/internal/hj$a$a:ko	Landroid/os/IBinder;
        //   71: bipush 6
        //   73: aload 6
        //   75: aload 5
        //   77: iconst_0
        //   78: invokeinterface 52 5 0
        //   83: pop
        //   84: aload 5
        //   86: invokevirtual 55	android/os/Parcel:readException	()V
        //   89: aload 5
        //   91: invokevirtual 58	android/os/Parcel:recycle	()V
        //   94: aload 6
        //   96: invokevirtual 58	android/os/Parcel:recycle	()V
        //   99: return
        //   100: aconst_null
        //   101: astore 7
        //   103: goto -74 -> 29
        //   106: aload 6
        //   108: iconst_0
        //   109: invokevirtual 46	android/os/Parcel:writeInt	(I)V
        //   112: goto -45 -> 67
        //   115: astore 7
        //   117: aload 5
        //   119: invokevirtual 58	android/os/Parcel:recycle	()V
        //   122: aload 6
        //   124: invokevirtual 58	android/os/Parcel:recycle	()V
        //   127: aload 7
        //   129: athrow
        // Local variable table:
        //   start	length	slot	name	signature
        //   0	130	0	this	a
        //   0	130	1	paramhi	hi
        //   0	130	2	paramInt	int
        //   0	130	3	paramString	String
        //   0	130	4	paramBundle	Bundle
        //   8	110	5	localParcel1	Parcel
        //   3	120	6	localParcel2	Parcel
        //   27	75	7	localIBinder	IBinder
        //   115	13	7	localObject	Object
        // Exception table:
        //   from	to	target	type
        //   10	89	115	finally
        //   106	112	115	finally
      }
      
      /* Error */
      public void d(hi paramhi, int paramInt, String paramString)
        throws RemoteException
      {
        // Byte code:
        //   0: invokestatic 27	android/os/Parcel:obtain	()Landroid/os/Parcel;
        //   3: astore 5
        //   5: invokestatic 27	android/os/Parcel:obtain	()Landroid/os/Parcel;
        //   8: astore 4
        //   10: aload 5
        //   12: ldc 29
        //   14: invokevirtual 33	android/os/Parcel:writeInterfaceToken	(Ljava/lang/String;)V
        //   17: aload_1
        //   18: ifnull +63 -> 81
        //   21: aload_1
        //   22: invokeinterface 39 1 0
        //   27: astore 6
        //   29: aload 5
        //   31: aload 6
        //   33: invokevirtual 42	android/os/Parcel:writeStrongBinder	(Landroid/os/IBinder;)V
        //   36: aload 5
        //   38: iload_2
        //   39: invokevirtual 46	android/os/Parcel:writeInt	(I)V
        //   42: aload 5
        //   44: aload_3
        //   45: invokevirtual 62	android/os/Parcel:writeString	(Ljava/lang/String;)V
        //   48: aload_0
        //   49: getfield 18	com/google/android/gms/internal/hj$a$a:ko	Landroid/os/IBinder;
        //   52: bipush 24
        //   54: aload 5
        //   56: aload 4
        //   58: iconst_0
        //   59: invokeinterface 52 5 0
        //   64: pop
        //   65: aload 4
        //   67: invokevirtual 55	android/os/Parcel:readException	()V
        //   70: aload 4
        //   72: invokevirtual 58	android/os/Parcel:recycle	()V
        //   75: aload 5
        //   77: invokevirtual 58	android/os/Parcel:recycle	()V
        //   80: return
        //   81: aconst_null
        //   82: astore 6
        //   84: goto -55 -> 29
        //   87: astore 6
        //   89: aload 4
        //   91: invokevirtual 58	android/os/Parcel:recycle	()V
        //   94: aload 5
        //   96: invokevirtual 58	android/os/Parcel:recycle	()V
        //   99: aload 6
        //   101: athrow
        // Local variable table:
        //   start	length	slot	name	signature
        //   0	102	0	this	a
        //   0	102	1	paramhi	hi
        //   0	102	2	paramInt	int
        //   0	102	3	paramString	String
        //   8	82	4	localParcel1	Parcel
        //   3	92	5	localParcel2	Parcel
        //   27	56	6	localIBinder	IBinder
        //   87	13	6	localObject	Object
        // Exception table:
        //   from	to	target	type
        //   10	70	87	finally
      }
      
      /* Error */
      public void d(hi paramhi, int paramInt, String paramString, Bundle paramBundle)
        throws RemoteException
      {
        // Byte code:
        //   0: invokestatic 27	android/os/Parcel:obtain	()Landroid/os/Parcel;
        //   3: astore 6
        //   5: invokestatic 27	android/os/Parcel:obtain	()Landroid/os/Parcel;
        //   8: astore 5
        //   10: aload 6
        //   12: ldc 29
        //   14: invokevirtual 33	android/os/Parcel:writeInterfaceToken	(Ljava/lang/String;)V
        //   17: aload_1
        //   18: ifnull +82 -> 100
        //   21: aload_1
        //   22: invokeinterface 39 1 0
        //   27: astore 7
        //   29: aload 6
        //   31: aload 7
        //   33: invokevirtual 42	android/os/Parcel:writeStrongBinder	(Landroid/os/IBinder;)V
        //   36: aload 6
        //   38: iload_2
        //   39: invokevirtual 46	android/os/Parcel:writeInt	(I)V
        //   42: aload 6
        //   44: aload_3
        //   45: invokevirtual 62	android/os/Parcel:writeString	(Ljava/lang/String;)V
        //   48: aload 4
        //   50: ifnull +56 -> 106
        //   53: aload 6
        //   55: iconst_1
        //   56: invokevirtual 46	android/os/Parcel:writeInt	(I)V
        //   59: aload 4
        //   61: aload 6
        //   63: iconst_0
        //   64: invokevirtual 69	android/os/Bundle:writeToParcel	(Landroid/os/Parcel;I)V
        //   67: aload_0
        //   68: getfield 18	com/google/android/gms/internal/hj$a$a:ko	Landroid/os/IBinder;
        //   71: bipush 7
        //   73: aload 6
        //   75: aload 5
        //   77: iconst_0
        //   78: invokeinterface 52 5 0
        //   83: pop
        //   84: aload 5
        //   86: invokevirtual 55	android/os/Parcel:readException	()V
        //   89: aload 5
        //   91: invokevirtual 58	android/os/Parcel:recycle	()V
        //   94: aload 6
        //   96: invokevirtual 58	android/os/Parcel:recycle	()V
        //   99: return
        //   100: aconst_null
        //   101: astore 7
        //   103: goto -74 -> 29
        //   106: aload 6
        //   108: iconst_0
        //   109: invokevirtual 46	android/os/Parcel:writeInt	(I)V
        //   112: goto -45 -> 67
        //   115: astore 7
        //   117: aload 5
        //   119: invokevirtual 58	android/os/Parcel:recycle	()V
        //   122: aload 6
        //   124: invokevirtual 58	android/os/Parcel:recycle	()V
        //   127: aload 7
        //   129: athrow
        // Local variable table:
        //   start	length	slot	name	signature
        //   0	130	0	this	a
        //   0	130	1	paramhi	hi
        //   0	130	2	paramInt	int
        //   0	130	3	paramString	String
        //   0	130	4	paramBundle	Bundle
        //   8	110	5	localParcel1	Parcel
        //   3	120	6	localParcel2	Parcel
        //   27	75	7	localIBinder	IBinder
        //   115	13	7	localObject	Object
        // Exception table:
        //   from	to	target	type
        //   10	89	115	finally
        //   106	112	115	finally
      }
      
      /* Error */
      public void e(hi paramhi, int paramInt, String paramString)
        throws RemoteException
      {
        // Byte code:
        //   0: invokestatic 27	android/os/Parcel:obtain	()Landroid/os/Parcel;
        //   3: astore 4
        //   5: invokestatic 27	android/os/Parcel:obtain	()Landroid/os/Parcel;
        //   8: astore 5
        //   10: aload 4
        //   12: ldc 29
        //   14: invokevirtual 33	android/os/Parcel:writeInterfaceToken	(Ljava/lang/String;)V
        //   17: aload_1
        //   18: ifnull +63 -> 81
        //   21: aload_1
        //   22: invokeinterface 39 1 0
        //   27: astore 6
        //   29: aload 4
        //   31: aload 6
        //   33: invokevirtual 42	android/os/Parcel:writeStrongBinder	(Landroid/os/IBinder;)V
        //   36: aload 4
        //   38: iload_2
        //   39: invokevirtual 46	android/os/Parcel:writeInt	(I)V
        //   42: aload 4
        //   44: aload_3
        //   45: invokevirtual 62	android/os/Parcel:writeString	(Ljava/lang/String;)V
        //   48: aload_0
        //   49: getfield 18	com/google/android/gms/internal/hj$a$a:ko	Landroid/os/IBinder;
        //   52: bipush 26
        //   54: aload 4
        //   56: aload 5
        //   58: iconst_0
        //   59: invokeinterface 52 5 0
        //   64: pop
        //   65: aload 5
        //   67: invokevirtual 55	android/os/Parcel:readException	()V
        //   70: aload 5
        //   72: invokevirtual 58	android/os/Parcel:recycle	()V
        //   75: aload 4
        //   77: invokevirtual 58	android/os/Parcel:recycle	()V
        //   80: return
        //   81: aconst_null
        //   82: astore 6
        //   84: goto -55 -> 29
        //   87: astore 6
        //   89: aload 5
        //   91: invokevirtual 58	android/os/Parcel:recycle	()V
        //   94: aload 4
        //   96: invokevirtual 58	android/os/Parcel:recycle	()V
        //   99: aload 6
        //   101: athrow
        // Local variable table:
        //   start	length	slot	name	signature
        //   0	102	0	this	a
        //   0	102	1	paramhi	hi
        //   0	102	2	paramInt	int
        //   0	102	3	paramString	String
        //   3	92	4	localParcel1	Parcel
        //   8	82	5	localParcel2	Parcel
        //   27	56	6	localIBinder	IBinder
        //   87	13	6	localObject	Object
        // Exception table:
        //   from	to	target	type
        //   10	70	87	finally
      }
      
      /* Error */
      public void e(hi paramhi, int paramInt, String paramString, Bundle paramBundle)
        throws RemoteException
      {
        // Byte code:
        //   0: invokestatic 27	android/os/Parcel:obtain	()Landroid/os/Parcel;
        //   3: astore 6
        //   5: invokestatic 27	android/os/Parcel:obtain	()Landroid/os/Parcel;
        //   8: astore 5
        //   10: aload 6
        //   12: ldc 29
        //   14: invokevirtual 33	android/os/Parcel:writeInterfaceToken	(Ljava/lang/String;)V
        //   17: aload_1
        //   18: ifnull +82 -> 100
        //   21: aload_1
        //   22: invokeinterface 39 1 0
        //   27: astore 7
        //   29: aload 6
        //   31: aload 7
        //   33: invokevirtual 42	android/os/Parcel:writeStrongBinder	(Landroid/os/IBinder;)V
        //   36: aload 6
        //   38: iload_2
        //   39: invokevirtual 46	android/os/Parcel:writeInt	(I)V
        //   42: aload 6
        //   44: aload_3
        //   45: invokevirtual 62	android/os/Parcel:writeString	(Ljava/lang/String;)V
        //   48: aload 4
        //   50: ifnull +56 -> 106
        //   53: aload 6
        //   55: iconst_1
        //   56: invokevirtual 46	android/os/Parcel:writeInt	(I)V
        //   59: aload 4
        //   61: aload 6
        //   63: iconst_0
        //   64: invokevirtual 69	android/os/Bundle:writeToParcel	(Landroid/os/Parcel;I)V
        //   67: aload_0
        //   68: getfield 18	com/google/android/gms/internal/hj$a$a:ko	Landroid/os/IBinder;
        //   71: bipush 8
        //   73: aload 6
        //   75: aload 5
        //   77: iconst_0
        //   78: invokeinterface 52 5 0
        //   83: pop
        //   84: aload 5
        //   86: invokevirtual 55	android/os/Parcel:readException	()V
        //   89: aload 5
        //   91: invokevirtual 58	android/os/Parcel:recycle	()V
        //   94: aload 6
        //   96: invokevirtual 58	android/os/Parcel:recycle	()V
        //   99: return
        //   100: aconst_null
        //   101: astore 7
        //   103: goto -74 -> 29
        //   106: aload 6
        //   108: iconst_0
        //   109: invokevirtual 46	android/os/Parcel:writeInt	(I)V
        //   112: goto -45 -> 67
        //   115: astore 7
        //   117: aload 5
        //   119: invokevirtual 58	android/os/Parcel:recycle	()V
        //   122: aload 6
        //   124: invokevirtual 58	android/os/Parcel:recycle	()V
        //   127: aload 7
        //   129: athrow
        // Local variable table:
        //   start	length	slot	name	signature
        //   0	130	0	this	a
        //   0	130	1	paramhi	hi
        //   0	130	2	paramInt	int
        //   0	130	3	paramString	String
        //   0	130	4	paramBundle	Bundle
        //   8	110	5	localParcel1	Parcel
        //   3	120	6	localParcel2	Parcel
        //   27	75	7	localIBinder	IBinder
        //   115	13	7	localObject	Object
        // Exception table:
        //   from	to	target	type
        //   10	89	115	finally
        //   106	112	115	finally
      }
      
      /* Error */
      public void f(hi paramhi, int paramInt, String paramString)
        throws RemoteException
      {
        // Byte code:
        //   0: invokestatic 27	android/os/Parcel:obtain	()Landroid/os/Parcel;
        //   3: astore 4
        //   5: invokestatic 27	android/os/Parcel:obtain	()Landroid/os/Parcel;
        //   8: astore 5
        //   10: aload 4
        //   12: ldc 29
        //   14: invokevirtual 33	android/os/Parcel:writeInterfaceToken	(Ljava/lang/String;)V
        //   17: aload_1
        //   18: ifnull +63 -> 81
        //   21: aload_1
        //   22: invokeinterface 39 1 0
        //   27: astore 6
        //   29: aload 4
        //   31: aload 6
        //   33: invokevirtual 42	android/os/Parcel:writeStrongBinder	(Landroid/os/IBinder;)V
        //   36: aload 4
        //   38: iload_2
        //   39: invokevirtual 46	android/os/Parcel:writeInt	(I)V
        //   42: aload 4
        //   44: aload_3
        //   45: invokevirtual 62	android/os/Parcel:writeString	(Ljava/lang/String;)V
        //   48: aload_0
        //   49: getfield 18	com/google/android/gms/internal/hj$a$a:ko	Landroid/os/IBinder;
        //   52: bipush 31
        //   54: aload 4
        //   56: aload 5
        //   58: iconst_0
        //   59: invokeinterface 52 5 0
        //   64: pop
        //   65: aload 5
        //   67: invokevirtual 55	android/os/Parcel:readException	()V
        //   70: aload 5
        //   72: invokevirtual 58	android/os/Parcel:recycle	()V
        //   75: aload 4
        //   77: invokevirtual 58	android/os/Parcel:recycle	()V
        //   80: return
        //   81: aconst_null
        //   82: astore 6
        //   84: goto -55 -> 29
        //   87: astore 6
        //   89: aload 5
        //   91: invokevirtual 58	android/os/Parcel:recycle	()V
        //   94: aload 4
        //   96: invokevirtual 58	android/os/Parcel:recycle	()V
        //   99: aload 6
        //   101: athrow
        // Local variable table:
        //   start	length	slot	name	signature
        //   0	102	0	this	a
        //   0	102	1	paramhi	hi
        //   0	102	2	paramInt	int
        //   0	102	3	paramString	String
        //   3	92	4	localParcel1	Parcel
        //   8	82	5	localParcel2	Parcel
        //   27	56	6	localIBinder	IBinder
        //   87	13	6	localObject	Object
        // Exception table:
        //   from	to	target	type
        //   10	70	87	finally
      }
      
      /* Error */
      public void f(hi paramhi, int paramInt, String paramString, Bundle paramBundle)
        throws RemoteException
      {
        // Byte code:
        //   0: invokestatic 27	android/os/Parcel:obtain	()Landroid/os/Parcel;
        //   3: astore 6
        //   5: invokestatic 27	android/os/Parcel:obtain	()Landroid/os/Parcel;
        //   8: astore 5
        //   10: aload 6
        //   12: ldc 29
        //   14: invokevirtual 33	android/os/Parcel:writeInterfaceToken	(Ljava/lang/String;)V
        //   17: aload_1
        //   18: ifnull +82 -> 100
        //   21: aload_1
        //   22: invokeinterface 39 1 0
        //   27: astore 7
        //   29: aload 6
        //   31: aload 7
        //   33: invokevirtual 42	android/os/Parcel:writeStrongBinder	(Landroid/os/IBinder;)V
        //   36: aload 6
        //   38: iload_2
        //   39: invokevirtual 46	android/os/Parcel:writeInt	(I)V
        //   42: aload 6
        //   44: aload_3
        //   45: invokevirtual 62	android/os/Parcel:writeString	(Ljava/lang/String;)V
        //   48: aload 4
        //   50: ifnull +56 -> 106
        //   53: aload 6
        //   55: iconst_1
        //   56: invokevirtual 46	android/os/Parcel:writeInt	(I)V
        //   59: aload 4
        //   61: aload 6
        //   63: iconst_0
        //   64: invokevirtual 69	android/os/Bundle:writeToParcel	(Landroid/os/Parcel;I)V
        //   67: aload_0
        //   68: getfield 18	com/google/android/gms/internal/hj$a$a:ko	Landroid/os/IBinder;
        //   71: bipush 11
        //   73: aload 6
        //   75: aload 5
        //   77: iconst_0
        //   78: invokeinterface 52 5 0
        //   83: pop
        //   84: aload 5
        //   86: invokevirtual 55	android/os/Parcel:readException	()V
        //   89: aload 5
        //   91: invokevirtual 58	android/os/Parcel:recycle	()V
        //   94: aload 6
        //   96: invokevirtual 58	android/os/Parcel:recycle	()V
        //   99: return
        //   100: aconst_null
        //   101: astore 7
        //   103: goto -74 -> 29
        //   106: aload 6
        //   108: iconst_0
        //   109: invokevirtual 46	android/os/Parcel:writeInt	(I)V
        //   112: goto -45 -> 67
        //   115: astore 7
        //   117: aload 5
        //   119: invokevirtual 58	android/os/Parcel:recycle	()V
        //   122: aload 6
        //   124: invokevirtual 58	android/os/Parcel:recycle	()V
        //   127: aload 7
        //   129: athrow
        // Local variable table:
        //   start	length	slot	name	signature
        //   0	130	0	this	a
        //   0	130	1	paramhi	hi
        //   0	130	2	paramInt	int
        //   0	130	3	paramString	String
        //   0	130	4	paramBundle	Bundle
        //   8	110	5	localParcel1	Parcel
        //   3	120	6	localParcel2	Parcel
        //   27	75	7	localIBinder	IBinder
        //   115	13	7	localObject	Object
        // Exception table:
        //   from	to	target	type
        //   10	89	115	finally
        //   106	112	115	finally
      }
      
      /* Error */
      public void g(hi paramhi, int paramInt, String paramString)
        throws RemoteException
      {
        // Byte code:
        //   0: invokestatic 27	android/os/Parcel:obtain	()Landroid/os/Parcel;
        //   3: astore 5
        //   5: invokestatic 27	android/os/Parcel:obtain	()Landroid/os/Parcel;
        //   8: astore 4
        //   10: aload 5
        //   12: ldc 29
        //   14: invokevirtual 33	android/os/Parcel:writeInterfaceToken	(Ljava/lang/String;)V
        //   17: aload_1
        //   18: ifnull +63 -> 81
        //   21: aload_1
        //   22: invokeinterface 39 1 0
        //   27: astore 6
        //   29: aload 5
        //   31: aload 6
        //   33: invokevirtual 42	android/os/Parcel:writeStrongBinder	(Landroid/os/IBinder;)V
        //   36: aload 5
        //   38: iload_2
        //   39: invokevirtual 46	android/os/Parcel:writeInt	(I)V
        //   42: aload 5
        //   44: aload_3
        //   45: invokevirtual 62	android/os/Parcel:writeString	(Ljava/lang/String;)V
        //   48: aload_0
        //   49: getfield 18	com/google/android/gms/internal/hj$a$a:ko	Landroid/os/IBinder;
        //   52: bipush 32
        //   54: aload 5
        //   56: aload 4
        //   58: iconst_0
        //   59: invokeinterface 52 5 0
        //   64: pop
        //   65: aload 4
        //   67: invokevirtual 55	android/os/Parcel:readException	()V
        //   70: aload 4
        //   72: invokevirtual 58	android/os/Parcel:recycle	()V
        //   75: aload 5
        //   77: invokevirtual 58	android/os/Parcel:recycle	()V
        //   80: return
        //   81: aconst_null
        //   82: astore 6
        //   84: goto -55 -> 29
        //   87: astore 6
        //   89: aload 4
        //   91: invokevirtual 58	android/os/Parcel:recycle	()V
        //   94: aload 5
        //   96: invokevirtual 58	android/os/Parcel:recycle	()V
        //   99: aload 6
        //   101: athrow
        // Local variable table:
        //   start	length	slot	name	signature
        //   0	102	0	this	a
        //   0	102	1	paramhi	hi
        //   0	102	2	paramInt	int
        //   0	102	3	paramString	String
        //   8	82	4	localParcel1	Parcel
        //   3	92	5	localParcel2	Parcel
        //   27	56	6	localIBinder	IBinder
        //   87	13	6	localObject	Object
        // Exception table:
        //   from	to	target	type
        //   10	70	87	finally
      }
      
      /* Error */
      public void g(hi paramhi, int paramInt, String paramString, Bundle paramBundle)
        throws RemoteException
      {
        // Byte code:
        //   0: invokestatic 27	android/os/Parcel:obtain	()Landroid/os/Parcel;
        //   3: astore 5
        //   5: invokestatic 27	android/os/Parcel:obtain	()Landroid/os/Parcel;
        //   8: astore 6
        //   10: aload 5
        //   12: ldc 29
        //   14: invokevirtual 33	android/os/Parcel:writeInterfaceToken	(Ljava/lang/String;)V
        //   17: aload_1
        //   18: ifnull +82 -> 100
        //   21: aload_1
        //   22: invokeinterface 39 1 0
        //   27: astore 7
        //   29: aload 5
        //   31: aload 7
        //   33: invokevirtual 42	android/os/Parcel:writeStrongBinder	(Landroid/os/IBinder;)V
        //   36: aload 5
        //   38: iload_2
        //   39: invokevirtual 46	android/os/Parcel:writeInt	(I)V
        //   42: aload 5
        //   44: aload_3
        //   45: invokevirtual 62	android/os/Parcel:writeString	(Ljava/lang/String;)V
        //   48: aload 4
        //   50: ifnull +56 -> 106
        //   53: aload 5
        //   55: iconst_1
        //   56: invokevirtual 46	android/os/Parcel:writeInt	(I)V
        //   59: aload 4
        //   61: aload 5
        //   63: iconst_0
        //   64: invokevirtual 69	android/os/Bundle:writeToParcel	(Landroid/os/Parcel;I)V
        //   67: aload_0
        //   68: getfield 18	com/google/android/gms/internal/hj$a$a:ko	Landroid/os/IBinder;
        //   71: bipush 12
        //   73: aload 5
        //   75: aload 6
        //   77: iconst_0
        //   78: invokeinterface 52 5 0
        //   83: pop
        //   84: aload 6
        //   86: invokevirtual 55	android/os/Parcel:readException	()V
        //   89: aload 6
        //   91: invokevirtual 58	android/os/Parcel:recycle	()V
        //   94: aload 5
        //   96: invokevirtual 58	android/os/Parcel:recycle	()V
        //   99: return
        //   100: aconst_null
        //   101: astore 7
        //   103: goto -74 -> 29
        //   106: aload 5
        //   108: iconst_0
        //   109: invokevirtual 46	android/os/Parcel:writeInt	(I)V
        //   112: goto -45 -> 67
        //   115: astore 7
        //   117: aload 6
        //   119: invokevirtual 58	android/os/Parcel:recycle	()V
        //   122: aload 5
        //   124: invokevirtual 58	android/os/Parcel:recycle	()V
        //   127: aload 7
        //   129: athrow
        // Local variable table:
        //   start	length	slot	name	signature
        //   0	130	0	this	a
        //   0	130	1	paramhi	hi
        //   0	130	2	paramInt	int
        //   0	130	3	paramString	String
        //   0	130	4	paramBundle	Bundle
        //   3	120	5	localParcel1	Parcel
        //   8	110	6	localParcel2	Parcel
        //   27	75	7	localIBinder	IBinder
        //   115	13	7	localObject	Object
        // Exception table:
        //   from	to	target	type
        //   10	89	115	finally
        //   106	112	115	finally
      }
      
      /* Error */
      public void h(hi paramhi, int paramInt, String paramString)
        throws RemoteException
      {
        // Byte code:
        //   0: invokestatic 27	android/os/Parcel:obtain	()Landroid/os/Parcel;
        //   3: astore 5
        //   5: invokestatic 27	android/os/Parcel:obtain	()Landroid/os/Parcel;
        //   8: astore 4
        //   10: aload 5
        //   12: ldc 29
        //   14: invokevirtual 33	android/os/Parcel:writeInterfaceToken	(Ljava/lang/String;)V
        //   17: aload_1
        //   18: ifnull +63 -> 81
        //   21: aload_1
        //   22: invokeinterface 39 1 0
        //   27: astore 6
        //   29: aload 5
        //   31: aload 6
        //   33: invokevirtual 42	android/os/Parcel:writeStrongBinder	(Landroid/os/IBinder;)V
        //   36: aload 5
        //   38: iload_2
        //   39: invokevirtual 46	android/os/Parcel:writeInt	(I)V
        //   42: aload 5
        //   44: aload_3
        //   45: invokevirtual 62	android/os/Parcel:writeString	(Ljava/lang/String;)V
        //   48: aload_0
        //   49: getfield 18	com/google/android/gms/internal/hj$a$a:ko	Landroid/os/IBinder;
        //   52: bipush 35
        //   54: aload 5
        //   56: aload 4
        //   58: iconst_0
        //   59: invokeinterface 52 5 0
        //   64: pop
        //   65: aload 4
        //   67: invokevirtual 55	android/os/Parcel:readException	()V
        //   70: aload 4
        //   72: invokevirtual 58	android/os/Parcel:recycle	()V
        //   75: aload 5
        //   77: invokevirtual 58	android/os/Parcel:recycle	()V
        //   80: return
        //   81: aconst_null
        //   82: astore 6
        //   84: goto -55 -> 29
        //   87: astore 6
        //   89: aload 4
        //   91: invokevirtual 58	android/os/Parcel:recycle	()V
        //   94: aload 5
        //   96: invokevirtual 58	android/os/Parcel:recycle	()V
        //   99: aload 6
        //   101: athrow
        // Local variable table:
        //   start	length	slot	name	signature
        //   0	102	0	this	a
        //   0	102	1	paramhi	hi
        //   0	102	2	paramInt	int
        //   0	102	3	paramString	String
        //   8	82	4	localParcel1	Parcel
        //   3	92	5	localParcel2	Parcel
        //   27	56	6	localIBinder	IBinder
        //   87	13	6	localObject	Object
        // Exception table:
        //   from	to	target	type
        //   10	70	87	finally
      }
      
      /* Error */
      public void h(hi paramhi, int paramInt, String paramString, Bundle paramBundle)
        throws RemoteException
      {
        // Byte code:
        //   0: invokestatic 27	android/os/Parcel:obtain	()Landroid/os/Parcel;
        //   3: astore 6
        //   5: invokestatic 27	android/os/Parcel:obtain	()Landroid/os/Parcel;
        //   8: astore 5
        //   10: aload 6
        //   12: ldc 29
        //   14: invokevirtual 33	android/os/Parcel:writeInterfaceToken	(Ljava/lang/String;)V
        //   17: aload_1
        //   18: ifnull +82 -> 100
        //   21: aload_1
        //   22: invokeinterface 39 1 0
        //   27: astore 7
        //   29: aload 6
        //   31: aload 7
        //   33: invokevirtual 42	android/os/Parcel:writeStrongBinder	(Landroid/os/IBinder;)V
        //   36: aload 6
        //   38: iload_2
        //   39: invokevirtual 46	android/os/Parcel:writeInt	(I)V
        //   42: aload 6
        //   44: aload_3
        //   45: invokevirtual 62	android/os/Parcel:writeString	(Ljava/lang/String;)V
        //   48: aload 4
        //   50: ifnull +56 -> 106
        //   53: aload 6
        //   55: iconst_1
        //   56: invokevirtual 46	android/os/Parcel:writeInt	(I)V
        //   59: aload 4
        //   61: aload 6
        //   63: iconst_0
        //   64: invokevirtual 69	android/os/Bundle:writeToParcel	(Landroid/os/Parcel;I)V
        //   67: aload_0
        //   68: getfield 18	com/google/android/gms/internal/hj$a$a:ko	Landroid/os/IBinder;
        //   71: bipush 13
        //   73: aload 6
        //   75: aload 5
        //   77: iconst_0
        //   78: invokeinterface 52 5 0
        //   83: pop
        //   84: aload 5
        //   86: invokevirtual 55	android/os/Parcel:readException	()V
        //   89: aload 5
        //   91: invokevirtual 58	android/os/Parcel:recycle	()V
        //   94: aload 6
        //   96: invokevirtual 58	android/os/Parcel:recycle	()V
        //   99: return
        //   100: aconst_null
        //   101: astore 7
        //   103: goto -74 -> 29
        //   106: aload 6
        //   108: iconst_0
        //   109: invokevirtual 46	android/os/Parcel:writeInt	(I)V
        //   112: goto -45 -> 67
        //   115: astore 7
        //   117: aload 5
        //   119: invokevirtual 58	android/os/Parcel:recycle	()V
        //   122: aload 6
        //   124: invokevirtual 58	android/os/Parcel:recycle	()V
        //   127: aload 7
        //   129: athrow
        // Local variable table:
        //   start	length	slot	name	signature
        //   0	130	0	this	a
        //   0	130	1	paramhi	hi
        //   0	130	2	paramInt	int
        //   0	130	3	paramString	String
        //   0	130	4	paramBundle	Bundle
        //   8	110	5	localParcel1	Parcel
        //   3	120	6	localParcel2	Parcel
        //   27	75	7	localIBinder	IBinder
        //   115	13	7	localObject	Object
        // Exception table:
        //   from	to	target	type
        //   10	89	115	finally
        //   106	112	115	finally
      }
      
      /* Error */
      public void i(hi paramhi, int paramInt, String paramString)
        throws RemoteException
      {
        // Byte code:
        //   0: invokestatic 27	android/os/Parcel:obtain	()Landroid/os/Parcel;
        //   3: astore 4
        //   5: invokestatic 27	android/os/Parcel:obtain	()Landroid/os/Parcel;
        //   8: astore 5
        //   10: aload 4
        //   12: ldc 29
        //   14: invokevirtual 33	android/os/Parcel:writeInterfaceToken	(Ljava/lang/String;)V
        //   17: aload_1
        //   18: ifnull +63 -> 81
        //   21: aload_1
        //   22: invokeinterface 39 1 0
        //   27: astore 6
        //   29: aload 4
        //   31: aload 6
        //   33: invokevirtual 42	android/os/Parcel:writeStrongBinder	(Landroid/os/IBinder;)V
        //   36: aload 4
        //   38: iload_2
        //   39: invokevirtual 46	android/os/Parcel:writeInt	(I)V
        //   42: aload 4
        //   44: aload_3
        //   45: invokevirtual 62	android/os/Parcel:writeString	(Ljava/lang/String;)V
        //   48: aload_0
        //   49: getfield 18	com/google/android/gms/internal/hj$a$a:ko	Landroid/os/IBinder;
        //   52: bipush 36
        //   54: aload 4
        //   56: aload 5
        //   58: iconst_0
        //   59: invokeinterface 52 5 0
        //   64: pop
        //   65: aload 5
        //   67: invokevirtual 55	android/os/Parcel:readException	()V
        //   70: aload 5
        //   72: invokevirtual 58	android/os/Parcel:recycle	()V
        //   75: aload 4
        //   77: invokevirtual 58	android/os/Parcel:recycle	()V
        //   80: return
        //   81: aconst_null
        //   82: astore 6
        //   84: goto -55 -> 29
        //   87: astore 6
        //   89: aload 5
        //   91: invokevirtual 58	android/os/Parcel:recycle	()V
        //   94: aload 4
        //   96: invokevirtual 58	android/os/Parcel:recycle	()V
        //   99: aload 6
        //   101: athrow
        // Local variable table:
        //   start	length	slot	name	signature
        //   0	102	0	this	a
        //   0	102	1	paramhi	hi
        //   0	102	2	paramInt	int
        //   0	102	3	paramString	String
        //   3	92	4	localParcel1	Parcel
        //   8	82	5	localParcel2	Parcel
        //   27	56	6	localIBinder	IBinder
        //   87	13	6	localObject	Object
        // Exception table:
        //   from	to	target	type
        //   10	70	87	finally
      }
      
      /* Error */
      public void i(hi paramhi, int paramInt, String paramString, Bundle paramBundle)
        throws RemoteException
      {
        // Byte code:
        //   0: invokestatic 27	android/os/Parcel:obtain	()Landroid/os/Parcel;
        //   3: astore 6
        //   5: invokestatic 27	android/os/Parcel:obtain	()Landroid/os/Parcel;
        //   8: astore 5
        //   10: aload 6
        //   12: ldc 29
        //   14: invokevirtual 33	android/os/Parcel:writeInterfaceToken	(Ljava/lang/String;)V
        //   17: aload_1
        //   18: ifnull +82 -> 100
        //   21: aload_1
        //   22: invokeinterface 39 1 0
        //   27: astore 7
        //   29: aload 6
        //   31: aload 7
        //   33: invokevirtual 42	android/os/Parcel:writeStrongBinder	(Landroid/os/IBinder;)V
        //   36: aload 6
        //   38: iload_2
        //   39: invokevirtual 46	android/os/Parcel:writeInt	(I)V
        //   42: aload 6
        //   44: aload_3
        //   45: invokevirtual 62	android/os/Parcel:writeString	(Ljava/lang/String;)V
        //   48: aload 4
        //   50: ifnull +56 -> 106
        //   53: aload 6
        //   55: iconst_1
        //   56: invokevirtual 46	android/os/Parcel:writeInt	(I)V
        //   59: aload 4
        //   61: aload 6
        //   63: iconst_0
        //   64: invokevirtual 69	android/os/Bundle:writeToParcel	(Landroid/os/Parcel;I)V
        //   67: aload_0
        //   68: getfield 18	com/google/android/gms/internal/hj$a$a:ko	Landroid/os/IBinder;
        //   71: bipush 14
        //   73: aload 6
        //   75: aload 5
        //   77: iconst_0
        //   78: invokeinterface 52 5 0
        //   83: pop
        //   84: aload 5
        //   86: invokevirtual 55	android/os/Parcel:readException	()V
        //   89: aload 5
        //   91: invokevirtual 58	android/os/Parcel:recycle	()V
        //   94: aload 6
        //   96: invokevirtual 58	android/os/Parcel:recycle	()V
        //   99: return
        //   100: aconst_null
        //   101: astore 7
        //   103: goto -74 -> 29
        //   106: aload 6
        //   108: iconst_0
        //   109: invokevirtual 46	android/os/Parcel:writeInt	(I)V
        //   112: goto -45 -> 67
        //   115: astore 7
        //   117: aload 5
        //   119: invokevirtual 58	android/os/Parcel:recycle	()V
        //   122: aload 6
        //   124: invokevirtual 58	android/os/Parcel:recycle	()V
        //   127: aload 7
        //   129: athrow
        // Local variable table:
        //   start	length	slot	name	signature
        //   0	130	0	this	a
        //   0	130	1	paramhi	hi
        //   0	130	2	paramInt	int
        //   0	130	3	paramString	String
        //   0	130	4	paramBundle	Bundle
        //   8	110	5	localParcel1	Parcel
        //   3	120	6	localParcel2	Parcel
        //   27	75	7	localIBinder	IBinder
        //   115	13	7	localObject	Object
        // Exception table:
        //   from	to	target	type
        //   10	89	115	finally
        //   106	112	115	finally
      }
      
      /* Error */
      public void j(hi paramhi, int paramInt, String paramString, Bundle paramBundle)
        throws RemoteException
      {
        // Byte code:
        //   0: invokestatic 27	android/os/Parcel:obtain	()Landroid/os/Parcel;
        //   3: astore 6
        //   5: invokestatic 27	android/os/Parcel:obtain	()Landroid/os/Parcel;
        //   8: astore 5
        //   10: aload 6
        //   12: ldc 29
        //   14: invokevirtual 33	android/os/Parcel:writeInterfaceToken	(Ljava/lang/String;)V
        //   17: aload_1
        //   18: ifnull +82 -> 100
        //   21: aload_1
        //   22: invokeinterface 39 1 0
        //   27: astore 7
        //   29: aload 6
        //   31: aload 7
        //   33: invokevirtual 42	android/os/Parcel:writeStrongBinder	(Landroid/os/IBinder;)V
        //   36: aload 6
        //   38: iload_2
        //   39: invokevirtual 46	android/os/Parcel:writeInt	(I)V
        //   42: aload 6
        //   44: aload_3
        //   45: invokevirtual 62	android/os/Parcel:writeString	(Ljava/lang/String;)V
        //   48: aload 4
        //   50: ifnull +56 -> 106
        //   53: aload 6
        //   55: iconst_1
        //   56: invokevirtual 46	android/os/Parcel:writeInt	(I)V
        //   59: aload 4
        //   61: aload 6
        //   63: iconst_0
        //   64: invokevirtual 69	android/os/Bundle:writeToParcel	(Landroid/os/Parcel;I)V
        //   67: aload_0
        //   68: getfield 18	com/google/android/gms/internal/hj$a$a:ko	Landroid/os/IBinder;
        //   71: bipush 15
        //   73: aload 6
        //   75: aload 5
        //   77: iconst_0
        //   78: invokeinterface 52 5 0
        //   83: pop
        //   84: aload 5
        //   86: invokevirtual 55	android/os/Parcel:readException	()V
        //   89: aload 5
        //   91: invokevirtual 58	android/os/Parcel:recycle	()V
        //   94: aload 6
        //   96: invokevirtual 58	android/os/Parcel:recycle	()V
        //   99: return
        //   100: aconst_null
        //   101: astore 7
        //   103: goto -74 -> 29
        //   106: aload 6
        //   108: iconst_0
        //   109: invokevirtual 46	android/os/Parcel:writeInt	(I)V
        //   112: goto -45 -> 67
        //   115: astore 7
        //   117: aload 5
        //   119: invokevirtual 58	android/os/Parcel:recycle	()V
        //   122: aload 6
        //   124: invokevirtual 58	android/os/Parcel:recycle	()V
        //   127: aload 7
        //   129: athrow
        // Local variable table:
        //   start	length	slot	name	signature
        //   0	130	0	this	a
        //   0	130	1	paramhi	hi
        //   0	130	2	paramInt	int
        //   0	130	3	paramString	String
        //   0	130	4	paramBundle	Bundle
        //   8	110	5	localParcel1	Parcel
        //   3	120	6	localParcel2	Parcel
        //   27	75	7	localIBinder	IBinder
        //   115	13	7	localObject	Object
        // Exception table:
        //   from	to	target	type
        //   10	89	115	finally
        //   106	112	115	finally
      }
      
      /* Error */
      public void k(hi paramhi, int paramInt, String paramString, Bundle paramBundle)
        throws RemoteException
      {
        // Byte code:
        //   0: invokestatic 27	android/os/Parcel:obtain	()Landroid/os/Parcel;
        //   3: astore 5
        //   5: invokestatic 27	android/os/Parcel:obtain	()Landroid/os/Parcel;
        //   8: astore 6
        //   10: aload 5
        //   12: ldc 29
        //   14: invokevirtual 33	android/os/Parcel:writeInterfaceToken	(Ljava/lang/String;)V
        //   17: aload_1
        //   18: ifnull +82 -> 100
        //   21: aload_1
        //   22: invokeinterface 39 1 0
        //   27: astore 7
        //   29: aload 5
        //   31: aload 7
        //   33: invokevirtual 42	android/os/Parcel:writeStrongBinder	(Landroid/os/IBinder;)V
        //   36: aload 5
        //   38: iload_2
        //   39: invokevirtual 46	android/os/Parcel:writeInt	(I)V
        //   42: aload 5
        //   44: aload_3
        //   45: invokevirtual 62	android/os/Parcel:writeString	(Ljava/lang/String;)V
        //   48: aload 4
        //   50: ifnull +56 -> 106
        //   53: aload 5
        //   55: iconst_1
        //   56: invokevirtual 46	android/os/Parcel:writeInt	(I)V
        //   59: aload 4
        //   61: aload 5
        //   63: iconst_0
        //   64: invokevirtual 69	android/os/Bundle:writeToParcel	(Landroid/os/Parcel;I)V
        //   67: aload_0
        //   68: getfield 18	com/google/android/gms/internal/hj$a$a:ko	Landroid/os/IBinder;
        //   71: bipush 16
        //   73: aload 5
        //   75: aload 6
        //   77: iconst_0
        //   78: invokeinterface 52 5 0
        //   83: pop
        //   84: aload 6
        //   86: invokevirtual 55	android/os/Parcel:readException	()V
        //   89: aload 6
        //   91: invokevirtual 58	android/os/Parcel:recycle	()V
        //   94: aload 5
        //   96: invokevirtual 58	android/os/Parcel:recycle	()V
        //   99: return
        //   100: aconst_null
        //   101: astore 7
        //   103: goto -74 -> 29
        //   106: aload 5
        //   108: iconst_0
        //   109: invokevirtual 46	android/os/Parcel:writeInt	(I)V
        //   112: goto -45 -> 67
        //   115: astore 7
        //   117: aload 6
        //   119: invokevirtual 58	android/os/Parcel:recycle	()V
        //   122: aload 5
        //   124: invokevirtual 58	android/os/Parcel:recycle	()V
        //   127: aload 7
        //   129: athrow
        // Local variable table:
        //   start	length	slot	name	signature
        //   0	130	0	this	a
        //   0	130	1	paramhi	hi
        //   0	130	2	paramInt	int
        //   0	130	3	paramString	String
        //   0	130	4	paramBundle	Bundle
        //   3	120	5	localParcel1	Parcel
        //   8	110	6	localParcel2	Parcel
        //   27	75	7	localIBinder	IBinder
        //   115	13	7	localObject	Object
        // Exception table:
        //   from	to	target	type
        //   10	89	115	finally
        //   106	112	115	finally
      }
      
      /* Error */
      public void l(hi paramhi, int paramInt, String paramString, Bundle paramBundle)
        throws RemoteException
      {
        // Byte code:
        //   0: invokestatic 27	android/os/Parcel:obtain	()Landroid/os/Parcel;
        //   3: astore 5
        //   5: invokestatic 27	android/os/Parcel:obtain	()Landroid/os/Parcel;
        //   8: astore 6
        //   10: aload 5
        //   12: ldc 29
        //   14: invokevirtual 33	android/os/Parcel:writeInterfaceToken	(Ljava/lang/String;)V
        //   17: aload_1
        //   18: ifnull +82 -> 100
        //   21: aload_1
        //   22: invokeinterface 39 1 0
        //   27: astore 7
        //   29: aload 5
        //   31: aload 7
        //   33: invokevirtual 42	android/os/Parcel:writeStrongBinder	(Landroid/os/IBinder;)V
        //   36: aload 5
        //   38: iload_2
        //   39: invokevirtual 46	android/os/Parcel:writeInt	(I)V
        //   42: aload 5
        //   44: aload_3
        //   45: invokevirtual 62	android/os/Parcel:writeString	(Ljava/lang/String;)V
        //   48: aload 4
        //   50: ifnull +56 -> 106
        //   53: aload 5
        //   55: iconst_1
        //   56: invokevirtual 46	android/os/Parcel:writeInt	(I)V
        //   59: aload 4
        //   61: aload 5
        //   63: iconst_0
        //   64: invokevirtual 69	android/os/Bundle:writeToParcel	(Landroid/os/Parcel;I)V
        //   67: aload_0
        //   68: getfield 18	com/google/android/gms/internal/hj$a$a:ko	Landroid/os/IBinder;
        //   71: bipush 17
        //   73: aload 5
        //   75: aload 6
        //   77: iconst_0
        //   78: invokeinterface 52 5 0
        //   83: pop
        //   84: aload 6
        //   86: invokevirtual 55	android/os/Parcel:readException	()V
        //   89: aload 6
        //   91: invokevirtual 58	android/os/Parcel:recycle	()V
        //   94: aload 5
        //   96: invokevirtual 58	android/os/Parcel:recycle	()V
        //   99: return
        //   100: aconst_null
        //   101: astore 7
        //   103: goto -74 -> 29
        //   106: aload 5
        //   108: iconst_0
        //   109: invokevirtual 46	android/os/Parcel:writeInt	(I)V
        //   112: goto -45 -> 67
        //   115: astore 7
        //   117: aload 6
        //   119: invokevirtual 58	android/os/Parcel:recycle	()V
        //   122: aload 5
        //   124: invokevirtual 58	android/os/Parcel:recycle	()V
        //   127: aload 7
        //   129: athrow
        // Local variable table:
        //   start	length	slot	name	signature
        //   0	130	0	this	a
        //   0	130	1	paramhi	hi
        //   0	130	2	paramInt	int
        //   0	130	3	paramString	String
        //   0	130	4	paramBundle	Bundle
        //   3	120	5	localParcel1	Parcel
        //   8	110	6	localParcel2	Parcel
        //   27	75	7	localIBinder	IBinder
        //   115	13	7	localObject	Object
        // Exception table:
        //   from	to	target	type
        //   10	89	115	finally
        //   106	112	115	finally
      }
      
      /* Error */
      public void m(hi paramhi, int paramInt, String paramString, Bundle paramBundle)
        throws RemoteException
      {
        // Byte code:
        //   0: invokestatic 27	android/os/Parcel:obtain	()Landroid/os/Parcel;
        //   3: astore 6
        //   5: invokestatic 27	android/os/Parcel:obtain	()Landroid/os/Parcel;
        //   8: astore 5
        //   10: aload 6
        //   12: ldc 29
        //   14: invokevirtual 33	android/os/Parcel:writeInterfaceToken	(Ljava/lang/String;)V
        //   17: aload_1
        //   18: ifnull +82 -> 100
        //   21: aload_1
        //   22: invokeinterface 39 1 0
        //   27: astore 7
        //   29: aload 6
        //   31: aload 7
        //   33: invokevirtual 42	android/os/Parcel:writeStrongBinder	(Landroid/os/IBinder;)V
        //   36: aload 6
        //   38: iload_2
        //   39: invokevirtual 46	android/os/Parcel:writeInt	(I)V
        //   42: aload 6
        //   44: aload_3
        //   45: invokevirtual 62	android/os/Parcel:writeString	(Ljava/lang/String;)V
        //   48: aload 4
        //   50: ifnull +56 -> 106
        //   53: aload 6
        //   55: iconst_1
        //   56: invokevirtual 46	android/os/Parcel:writeInt	(I)V
        //   59: aload 4
        //   61: aload 6
        //   63: iconst_0
        //   64: invokevirtual 69	android/os/Bundle:writeToParcel	(Landroid/os/Parcel;I)V
        //   67: aload_0
        //   68: getfield 18	com/google/android/gms/internal/hj$a$a:ko	Landroid/os/IBinder;
        //   71: bipush 18
        //   73: aload 6
        //   75: aload 5
        //   77: iconst_0
        //   78: invokeinterface 52 5 0
        //   83: pop
        //   84: aload 5
        //   86: invokevirtual 55	android/os/Parcel:readException	()V
        //   89: aload 5
        //   91: invokevirtual 58	android/os/Parcel:recycle	()V
        //   94: aload 6
        //   96: invokevirtual 58	android/os/Parcel:recycle	()V
        //   99: return
        //   100: aconst_null
        //   101: astore 7
        //   103: goto -74 -> 29
        //   106: aload 6
        //   108: iconst_0
        //   109: invokevirtual 46	android/os/Parcel:writeInt	(I)V
        //   112: goto -45 -> 67
        //   115: astore 7
        //   117: aload 5
        //   119: invokevirtual 58	android/os/Parcel:recycle	()V
        //   122: aload 6
        //   124: invokevirtual 58	android/os/Parcel:recycle	()V
        //   127: aload 7
        //   129: athrow
        // Local variable table:
        //   start	length	slot	name	signature
        //   0	130	0	this	a
        //   0	130	1	paramhi	hi
        //   0	130	2	paramInt	int
        //   0	130	3	paramString	String
        //   0	130	4	paramBundle	Bundle
        //   8	110	5	localParcel1	Parcel
        //   3	120	6	localParcel2	Parcel
        //   27	75	7	localIBinder	IBinder
        //   115	13	7	localObject	Object
        // Exception table:
        //   from	to	target	type
        //   10	89	115	finally
        //   106	112	115	finally
      }
      
      /* Error */
      public void n(hi paramhi, int paramInt, String paramString, Bundle paramBundle)
        throws RemoteException
      {
        // Byte code:
        //   0: invokestatic 27	android/os/Parcel:obtain	()Landroid/os/Parcel;
        //   3: astore 6
        //   5: invokestatic 27	android/os/Parcel:obtain	()Landroid/os/Parcel;
        //   8: astore 5
        //   10: aload 6
        //   12: ldc 29
        //   14: invokevirtual 33	android/os/Parcel:writeInterfaceToken	(Ljava/lang/String;)V
        //   17: aload_1
        //   18: ifnull +82 -> 100
        //   21: aload_1
        //   22: invokeinterface 39 1 0
        //   27: astore 7
        //   29: aload 6
        //   31: aload 7
        //   33: invokevirtual 42	android/os/Parcel:writeStrongBinder	(Landroid/os/IBinder;)V
        //   36: aload 6
        //   38: iload_2
        //   39: invokevirtual 46	android/os/Parcel:writeInt	(I)V
        //   42: aload 6
        //   44: aload_3
        //   45: invokevirtual 62	android/os/Parcel:writeString	(Ljava/lang/String;)V
        //   48: aload 4
        //   50: ifnull +56 -> 106
        //   53: aload 6
        //   55: iconst_1
        //   56: invokevirtual 46	android/os/Parcel:writeInt	(I)V
        //   59: aload 4
        //   61: aload 6
        //   63: iconst_0
        //   64: invokevirtual 69	android/os/Bundle:writeToParcel	(Landroid/os/Parcel;I)V
        //   67: aload_0
        //   68: getfield 18	com/google/android/gms/internal/hj$a$a:ko	Landroid/os/IBinder;
        //   71: bipush 23
        //   73: aload 6
        //   75: aload 5
        //   77: iconst_0
        //   78: invokeinterface 52 5 0
        //   83: pop
        //   84: aload 5
        //   86: invokevirtual 55	android/os/Parcel:readException	()V
        //   89: aload 5
        //   91: invokevirtual 58	android/os/Parcel:recycle	()V
        //   94: aload 6
        //   96: invokevirtual 58	android/os/Parcel:recycle	()V
        //   99: return
        //   100: aconst_null
        //   101: astore 7
        //   103: goto -74 -> 29
        //   106: aload 6
        //   108: iconst_0
        //   109: invokevirtual 46	android/os/Parcel:writeInt	(I)V
        //   112: goto -45 -> 67
        //   115: astore 7
        //   117: aload 5
        //   119: invokevirtual 58	android/os/Parcel:recycle	()V
        //   122: aload 6
        //   124: invokevirtual 58	android/os/Parcel:recycle	()V
        //   127: aload 7
        //   129: athrow
        // Local variable table:
        //   start	length	slot	name	signature
        //   0	130	0	this	a
        //   0	130	1	paramhi	hi
        //   0	130	2	paramInt	int
        //   0	130	3	paramString	String
        //   0	130	4	paramBundle	Bundle
        //   8	110	5	localParcel1	Parcel
        //   3	120	6	localParcel2	Parcel
        //   27	75	7	localIBinder	IBinder
        //   115	13	7	localObject	Object
        // Exception table:
        //   from	to	target	type
        //   10	89	115	finally
        //   106	112	115	finally
      }
      
      /* Error */
      public void o(hi paramhi, int paramInt, String paramString, Bundle paramBundle)
        throws RemoteException
      {
        // Byte code:
        //   0: invokestatic 27	android/os/Parcel:obtain	()Landroid/os/Parcel;
        //   3: astore 5
        //   5: invokestatic 27	android/os/Parcel:obtain	()Landroid/os/Parcel;
        //   8: astore 6
        //   10: aload 5
        //   12: ldc 29
        //   14: invokevirtual 33	android/os/Parcel:writeInterfaceToken	(Ljava/lang/String;)V
        //   17: aload_1
        //   18: ifnull +82 -> 100
        //   21: aload_1
        //   22: invokeinterface 39 1 0
        //   27: astore 7
        //   29: aload 5
        //   31: aload 7
        //   33: invokevirtual 42	android/os/Parcel:writeStrongBinder	(Landroid/os/IBinder;)V
        //   36: aload 5
        //   38: iload_2
        //   39: invokevirtual 46	android/os/Parcel:writeInt	(I)V
        //   42: aload 5
        //   44: aload_3
        //   45: invokevirtual 62	android/os/Parcel:writeString	(Ljava/lang/String;)V
        //   48: aload 4
        //   50: ifnull +56 -> 106
        //   53: aload 5
        //   55: iconst_1
        //   56: invokevirtual 46	android/os/Parcel:writeInt	(I)V
        //   59: aload 4
        //   61: aload 5
        //   63: iconst_0
        //   64: invokevirtual 69	android/os/Bundle:writeToParcel	(Landroid/os/Parcel;I)V
        //   67: aload_0
        //   68: getfield 18	com/google/android/gms/internal/hj$a$a:ko	Landroid/os/IBinder;
        //   71: bipush 25
        //   73: aload 5
        //   75: aload 6
        //   77: iconst_0
        //   78: invokeinterface 52 5 0
        //   83: pop
        //   84: aload 6
        //   86: invokevirtual 55	android/os/Parcel:readException	()V
        //   89: aload 6
        //   91: invokevirtual 58	android/os/Parcel:recycle	()V
        //   94: aload 5
        //   96: invokevirtual 58	android/os/Parcel:recycle	()V
        //   99: return
        //   100: aconst_null
        //   101: astore 7
        //   103: goto -74 -> 29
        //   106: aload 5
        //   108: iconst_0
        //   109: invokevirtual 46	android/os/Parcel:writeInt	(I)V
        //   112: goto -45 -> 67
        //   115: astore 7
        //   117: aload 6
        //   119: invokevirtual 58	android/os/Parcel:recycle	()V
        //   122: aload 5
        //   124: invokevirtual 58	android/os/Parcel:recycle	()V
        //   127: aload 7
        //   129: athrow
        // Local variable table:
        //   start	length	slot	name	signature
        //   0	130	0	this	a
        //   0	130	1	paramhi	hi
        //   0	130	2	paramInt	int
        //   0	130	3	paramString	String
        //   0	130	4	paramBundle	Bundle
        //   3	120	5	localParcel1	Parcel
        //   8	110	6	localParcel2	Parcel
        //   27	75	7	localIBinder	IBinder
        //   115	13	7	localObject	Object
        // Exception table:
        //   from	to	target	type
        //   10	89	115	finally
        //   106	112	115	finally
      }
      
      /* Error */
      public void p(hi paramhi, int paramInt, String paramString, Bundle paramBundle)
        throws RemoteException
      {
        // Byte code:
        //   0: invokestatic 27	android/os/Parcel:obtain	()Landroid/os/Parcel;
        //   3: astore 6
        //   5: invokestatic 27	android/os/Parcel:obtain	()Landroid/os/Parcel;
        //   8: astore 5
        //   10: aload 6
        //   12: ldc 29
        //   14: invokevirtual 33	android/os/Parcel:writeInterfaceToken	(Ljava/lang/String;)V
        //   17: aload_1
        //   18: ifnull +82 -> 100
        //   21: aload_1
        //   22: invokeinterface 39 1 0
        //   27: astore 7
        //   29: aload 6
        //   31: aload 7
        //   33: invokevirtual 42	android/os/Parcel:writeStrongBinder	(Landroid/os/IBinder;)V
        //   36: aload 6
        //   38: iload_2
        //   39: invokevirtual 46	android/os/Parcel:writeInt	(I)V
        //   42: aload 6
        //   44: aload_3
        //   45: invokevirtual 62	android/os/Parcel:writeString	(Ljava/lang/String;)V
        //   48: aload 4
        //   50: ifnull +56 -> 106
        //   53: aload 6
        //   55: iconst_1
        //   56: invokevirtual 46	android/os/Parcel:writeInt	(I)V
        //   59: aload 4
        //   61: aload 6
        //   63: iconst_0
        //   64: invokevirtual 69	android/os/Bundle:writeToParcel	(Landroid/os/Parcel;I)V
        //   67: aload_0
        //   68: getfield 18	com/google/android/gms/internal/hj$a$a:ko	Landroid/os/IBinder;
        //   71: bipush 27
        //   73: aload 6
        //   75: aload 5
        //   77: iconst_0
        //   78: invokeinterface 52 5 0
        //   83: pop
        //   84: aload 5
        //   86: invokevirtual 55	android/os/Parcel:readException	()V
        //   89: aload 5
        //   91: invokevirtual 58	android/os/Parcel:recycle	()V
        //   94: aload 6
        //   96: invokevirtual 58	android/os/Parcel:recycle	()V
        //   99: return
        //   100: aconst_null
        //   101: astore 7
        //   103: goto -74 -> 29
        //   106: aload 6
        //   108: iconst_0
        //   109: invokevirtual 46	android/os/Parcel:writeInt	(I)V
        //   112: goto -45 -> 67
        //   115: astore 7
        //   117: aload 5
        //   119: invokevirtual 58	android/os/Parcel:recycle	()V
        //   122: aload 6
        //   124: invokevirtual 58	android/os/Parcel:recycle	()V
        //   127: aload 7
        //   129: athrow
        // Local variable table:
        //   start	length	slot	name	signature
        //   0	130	0	this	a
        //   0	130	1	paramhi	hi
        //   0	130	2	paramInt	int
        //   0	130	3	paramString	String
        //   0	130	4	paramBundle	Bundle
        //   8	110	5	localParcel1	Parcel
        //   3	120	6	localParcel2	Parcel
        //   27	75	7	localIBinder	IBinder
        //   115	13	7	localObject	Object
        // Exception table:
        //   from	to	target	type
        //   10	89	115	finally
        //   106	112	115	finally
      }
    }
  }
}


/* Location:           E:\android\Androidvn\dex2jar\classes_dex2jar.jar
 * Qualified Name:     com.google.android.gms.internal.hj
 * JD-Core Version:    0.7.0.1
 */