package com.google.android.gms.location;

import android.location.Location;
import android.os.Binder;
import android.os.IBinder;
import android.os.IInterface;
import android.os.Parcel;
import android.os.Parcelable.Creator;
import android.os.RemoteException;

public abstract interface a
  extends IInterface
{
  public abstract void onLocationChanged(Location paramLocation)
    throws RemoteException;
  
  public static abstract class a
    extends Binder
    implements a
  {
    public a()
    {
      attachInterface(this, "com.google.android.gms.location.ILocationListener");
    }
    
    public static a aq(IBinder paramIBinder)
    {
      Object localObject;
      if (paramIBinder != null)
      {
        localObject = paramIBinder.queryLocalInterface("com.google.android.gms.location.ILocationListener");
        if ((localObject == null) || (!(localObject instanceof a))) {
          localObject = new a(paramIBinder);
        } else {
          localObject = (a)localObject;
        }
      }
      else
      {
        localObject = null;
      }
      return localObject;
    }
    
    public IBinder asBinder()
    {
      return this;
    }
    
    public boolean onTransact(int paramInt1, Parcel paramParcel1, Parcel paramParcel2, int paramInt2)
      throws RemoteException
    {
      boolean bool2;
      switch (paramInt1)
      {
      default: 
        boolean bool1 = super.onTransact(paramInt1, paramParcel1, paramParcel2, paramInt2);
        break;
      case 1: 
        paramParcel1.enforceInterface("com.google.android.gms.location.ILocationListener");
        Location localLocation;
        if (paramParcel1.readInt() == 0) {
          localLocation = null;
        } else {
          localLocation = (Location)Location.CREATOR.createFromParcel(paramParcel1);
        }
        onLocationChanged(localLocation);
        bool2 = true;
        break;
      case 1598968902: 
        paramParcel2.writeString("com.google.android.gms.location.ILocationListener");
        bool2 = true;
      }
      return bool2;
    }
    
    private static class a
      implements a
    {
      private IBinder ko;
      
      a(IBinder paramIBinder)
      {
        this.ko = paramIBinder;
      }
      
      public IBinder asBinder()
      {
        return this.ko;
      }
      
      /* Error */
      public void onLocationChanged(Location paramLocation)
        throws RemoteException
      {
        // Byte code:
        //   0: invokestatic 30	android/os/Parcel:obtain	()Landroid/os/Parcel;
        //   3: astore_2
        //   4: aload_2
        //   5: ldc 32
        //   7: invokevirtual 36	android/os/Parcel:writeInterfaceToken	(Ljava/lang/String;)V
        //   10: aload_1
        //   11: ifnull +33 -> 44
        //   14: aload_2
        //   15: iconst_1
        //   16: invokevirtual 40	android/os/Parcel:writeInt	(I)V
        //   19: aload_1
        //   20: aload_2
        //   21: iconst_0
        //   22: invokevirtual 46	android/location/Location:writeToParcel	(Landroid/os/Parcel;I)V
        //   25: aload_0
        //   26: getfield 18	com/google/android/gms/location/a$a$a:ko	Landroid/os/IBinder;
        //   29: iconst_1
        //   30: aload_2
        //   31: aconst_null
        //   32: iconst_1
        //   33: invokeinterface 52 5 0
        //   38: pop
        //   39: aload_2
        //   40: invokevirtual 55	android/os/Parcel:recycle	()V
        //   43: return
        //   44: aload_2
        //   45: iconst_0
        //   46: invokevirtual 40	android/os/Parcel:writeInt	(I)V
        //   49: goto -24 -> 25
        //   52: astore_3
        //   53: aload_2
        //   54: invokevirtual 55	android/os/Parcel:recycle	()V
        //   57: aload_3
        //   58: athrow
        // Local variable table:
        //   start	length	slot	name	signature
        //   0	59	0	this	a
        //   0	59	1	paramLocation	Location
        //   3	51	2	localParcel	Parcel
        //   52	6	3	localObject	Object
        // Exception table:
        //   from	to	target	type
        //   4	39	52	finally
        //   44	49	52	finally
      }
    }
  }
}


/* Location:           E:\android\Androidvn\dex2jar\classes_dex2jar.jar
 * Qualified Name:     com.google.android.gms.location.a
 * JD-Core Version:    0.7.0.1
 */