package com.google.android.gms.maps.internal;

import android.os.Binder;
import android.os.IBinder;
import android.os.IInterface;
import android.os.Parcel;
import android.os.RemoteException;

public abstract interface ILocationSourceDelegate
  extends IInterface
{
  public abstract void activate(h paramh)
    throws RemoteException;
  
  public abstract void deactivate()
    throws RemoteException;
  
  public static abstract class a
    extends Binder
    implements ILocationSourceDelegate
  {
    public a()
    {
      attachInterface(this, "com.google.android.gms.maps.internal.ILocationSourceDelegate");
    }
    
    public static ILocationSourceDelegate aA(IBinder paramIBinder)
    {
      Object localObject;
      if (paramIBinder != null)
      {
        localObject = paramIBinder.queryLocalInterface("com.google.android.gms.maps.internal.ILocationSourceDelegate");
        if ((localObject == null) || (!(localObject instanceof ILocationSourceDelegate))) {
          localObject = new a(paramIBinder);
        } else {
          localObject = (ILocationSourceDelegate)localObject;
        }
      }
      else
      {
        localObject = null;
      }
      return localObject;
    }
    
    public IBinder asBinder()
    {
      return this;
    }
    
    public boolean onTransact(int paramInt1, Parcel paramParcel1, Parcel paramParcel2, int paramInt2)
      throws RemoteException
    {
      boolean bool = true;
      switch (paramInt1)
      {
      default: 
        bool = super.onTransact(paramInt1, paramParcel1, paramParcel2, paramInt2);
        break;
      case 1: 
        paramParcel1.enforceInterface("com.google.android.gms.maps.internal.ILocationSourceDelegate");
        activate(h.a.aG(paramParcel1.readStrongBinder()));
        paramParcel2.writeNoException();
        break;
      case 2: 
        paramParcel1.enforceInterface("com.google.android.gms.maps.internal.ILocationSourceDelegate");
        deactivate();
        paramParcel2.writeNoException();
        break;
      case 1598968902: 
        paramParcel2.writeString("com.google.android.gms.maps.internal.ILocationSourceDelegate");
      }
      return bool;
    }
    
    private static class a
      implements ILocationSourceDelegate
    {
      private IBinder ko;
      
      a(IBinder paramIBinder)
      {
        this.ko = paramIBinder;
      }
      
      /* Error */
      public void activate(h paramh)
        throws RemoteException
      {
        // Byte code:
        //   0: invokestatic 28	android/os/Parcel:obtain	()Landroid/os/Parcel;
        //   3: astore_3
        //   4: invokestatic 28	android/os/Parcel:obtain	()Landroid/os/Parcel;
        //   7: astore_2
        //   8: aload_3
        //   9: ldc 30
        //   11: invokevirtual 34	android/os/Parcel:writeInterfaceToken	(Ljava/lang/String;)V
        //   14: aload_1
        //   15: ifnull +44 -> 59
        //   18: aload_1
        //   19: invokeinterface 40 1 0
        //   24: astore 4
        //   26: aload_3
        //   27: aload 4
        //   29: invokevirtual 43	android/os/Parcel:writeStrongBinder	(Landroid/os/IBinder;)V
        //   32: aload_0
        //   33: getfield 18	com/google/android/gms/maps/internal/ILocationSourceDelegate$a$a:ko	Landroid/os/IBinder;
        //   36: iconst_1
        //   37: aload_3
        //   38: aload_2
        //   39: iconst_0
        //   40: invokeinterface 49 5 0
        //   45: pop
        //   46: aload_2
        //   47: invokevirtual 52	android/os/Parcel:readException	()V
        //   50: aload_2
        //   51: invokevirtual 55	android/os/Parcel:recycle	()V
        //   54: aload_3
        //   55: invokevirtual 55	android/os/Parcel:recycle	()V
        //   58: return
        //   59: aconst_null
        //   60: astore 4
        //   62: goto -36 -> 26
        //   65: astore 4
        //   67: aload_2
        //   68: invokevirtual 55	android/os/Parcel:recycle	()V
        //   71: aload_3
        //   72: invokevirtual 55	android/os/Parcel:recycle	()V
        //   75: aload 4
        //   77: athrow
        // Local variable table:
        //   start	length	slot	name	signature
        //   0	78	0	this	a
        //   0	78	1	paramh	h
        //   7	61	2	localParcel1	Parcel
        //   3	69	3	localParcel2	Parcel
        //   24	37	4	localIBinder	IBinder
        //   65	11	4	localObject	Object
        // Exception table:
        //   from	to	target	type
        //   8	50	65	finally
      }
      
      public IBinder asBinder()
      {
        return this.ko;
      }
      
      public void deactivate()
        throws RemoteException
      {
        Parcel localParcel2 = Parcel.obtain();
        Parcel localParcel1 = Parcel.obtain();
        try
        {
          localParcel2.writeInterfaceToken("com.google.android.gms.maps.internal.ILocationSourceDelegate");
          this.ko.transact(2, localParcel2, localParcel1, 0);
          localParcel1.readException();
          return;
        }
        finally
        {
          localParcel1.recycle();
          localParcel2.recycle();
        }
      }
    }
  }
}


/* Location:           E:\android\Androidvn\dex2jar\classes_dex2jar.jar
 * Qualified Name:     com.google.android.gms.maps.internal.ILocationSourceDelegate
 * JD-Core Version:    0.7.0.1
 */