package com.google.android.gms.wearable.internal;

import android.net.Uri;
import android.os.Binder;
import android.os.IBinder;
import android.os.IInterface;
import android.os.Parcel;
import android.os.Parcelable.Creator;
import android.os.RemoteException;
import com.google.android.gms.wearable.Asset;
import com.google.android.gms.wearable.PutDataRequest;
import com.google.android.gms.wearable.c;

public abstract interface ad
  extends IInterface
{
  public abstract void a(ab paramab)
    throws RemoteException;
  
  public abstract void a(ab paramab, Uri paramUri)
    throws RemoteException;
  
  public abstract void a(ab paramab, Asset paramAsset)
    throws RemoteException;
  
  public abstract void a(ab paramab, PutDataRequest paramPutDataRequest)
    throws RemoteException;
  
  public abstract void a(ab paramab, c paramc)
    throws RemoteException;
  
  public abstract void a(ab paramab, ao paramao)
    throws RemoteException;
  
  public abstract void a(ab paramab, b paramb)
    throws RemoteException;
  
  public abstract void a(ab paramab, String paramString1, String paramString2, byte[] paramArrayOfByte)
    throws RemoteException;
  
  public abstract void b(ab paramab)
    throws RemoteException;
  
  public abstract void b(ab paramab, Uri paramUri)
    throws RemoteException;
  
  public abstract void c(ab paramab)
    throws RemoteException;
  
  public abstract void c(ab paramab, Uri paramUri)
    throws RemoteException;
  
  public abstract void d(ab paramab)
    throws RemoteException;
  
  public abstract void e(ab paramab)
    throws RemoteException;
  
  public abstract void f(ab paramab)
    throws RemoteException;
  
  public abstract void g(ab paramab)
    throws RemoteException;
  
  public abstract void h(ab paramab)
    throws RemoteException;
  
  public static abstract class a
    extends Binder
    implements ad
  {
    public static ad by(IBinder paramIBinder)
    {
      Object localObject;
      if (paramIBinder != null)
      {
        localObject = paramIBinder.queryLocalInterface("com.google.android.gms.wearable.internal.IWearableService");
        if ((localObject == null) || (!(localObject instanceof ad))) {
          localObject = new a(paramIBinder);
        } else {
          localObject = (ad)localObject;
        }
      }
      else
      {
        localObject = null;
      }
      return localObject;
    }
    
    public boolean onTransact(int paramInt1, Parcel paramParcel1, Parcel paramParcel2, int paramInt2)
      throws RemoteException
    {
      Object localObject = null;
      ab localab;
      int i;
      int k;
      int n;
      int i1;
      boolean bool2;
      switch (paramInt1)
      {
      default: 
        boolean bool1 = super.onTransact(paramInt1, paramParcel1, paramParcel2, paramInt2);
        break;
      case 2: 
        paramParcel1.enforceInterface("com.google.android.gms.wearable.internal.IWearableService");
        localab = ab.a.bw(paramParcel1.readStrongBinder());
        c localc;
        if (paramParcel1.readInt() != 0) {
          localc = (c)c.CREATOR.createFromParcel(paramParcel1);
        }
        a(localab, localc);
        paramParcel2.writeNoException();
        i = 1;
        break;
      case 3: 
        paramParcel1.enforceInterface("com.google.android.gms.wearable.internal.IWearableService");
        a(ab.a.bw(paramParcel1.readStrongBinder()));
        paramParcel2.writeNoException();
        i = 1;
        break;
      case 4: 
        paramParcel1.enforceInterface("com.google.android.gms.wearable.internal.IWearableService");
        b(ab.a.bw(paramParcel1.readStrongBinder()));
        paramParcel2.writeNoException();
        i = 1;
        break;
      case 5: 
        paramParcel1.enforceInterface("com.google.android.gms.wearable.internal.IWearableService");
        c(ab.a.bw(paramParcel1.readStrongBinder()));
        paramParcel2.writeNoException();
        i = 1;
        break;
      case 6: 
        paramParcel1.enforceInterface("com.google.android.gms.wearable.internal.IWearableService");
        localab = ab.a.bw(paramParcel1.readStrongBinder());
        PutDataRequest localPutDataRequest;
        if (paramParcel1.readInt() != 0) {
          localPutDataRequest = (PutDataRequest)PutDataRequest.CREATOR.createFromParcel(paramParcel1);
        }
        a(localab, localPutDataRequest);
        paramParcel2.writeNoException();
        int j = 1;
        break;
      case 7: 
        paramParcel1.enforceInterface("com.google.android.gms.wearable.internal.IWearableService");
        localab = ab.a.bw(paramParcel1.readStrongBinder());
        Uri localUri1;
        if (paramParcel1.readInt() != 0) {
          localUri1 = (Uri)Uri.CREATOR.createFromParcel(paramParcel1);
        }
        a(localab, localUri1);
        paramParcel2.writeNoException();
        k = 1;
        break;
      case 8: 
        paramParcel1.enforceInterface("com.google.android.gms.wearable.internal.IWearableService");
        d(ab.a.bw(paramParcel1.readStrongBinder()));
        paramParcel2.writeNoException();
        k = 1;
        break;
      case 9: 
        paramParcel1.enforceInterface("com.google.android.gms.wearable.internal.IWearableService");
        localab = ab.a.bw(paramParcel1.readStrongBinder());
        Uri localUri2;
        if (paramParcel1.readInt() != 0) {
          localUri2 = (Uri)Uri.CREATOR.createFromParcel(paramParcel1);
        }
        b(localab, localUri2);
        paramParcel2.writeNoException();
        int m = 1;
        break;
      case 11: 
        paramParcel1.enforceInterface("com.google.android.gms.wearable.internal.IWearableService");
        localab = ab.a.bw(paramParcel1.readStrongBinder());
        Uri localUri3;
        if (paramParcel1.readInt() != 0) {
          localUri3 = (Uri)Uri.CREATOR.createFromParcel(paramParcel1);
        }
        c(localab, localUri3);
        paramParcel2.writeNoException();
        n = 1;
        break;
      case 12: 
        paramParcel1.enforceInterface("com.google.android.gms.wearable.internal.IWearableService");
        a(ab.a.bw(paramParcel1.readStrongBinder()), paramParcel1.readString(), paramParcel1.readString(), paramParcel1.createByteArray());
        paramParcel2.writeNoException();
        n = 1;
        break;
      case 13: 
        paramParcel1.enforceInterface("com.google.android.gms.wearable.internal.IWearableService");
        localab = ab.a.bw(paramParcel1.readStrongBinder());
        Asset localAsset;
        if (paramParcel1.readInt() != 0) {
          localAsset = (Asset)Asset.CREATOR.createFromParcel(paramParcel1);
        }
        a(localab, localAsset);
        paramParcel2.writeNoException();
        i1 = 1;
        break;
      case 14: 
        paramParcel1.enforceInterface("com.google.android.gms.wearable.internal.IWearableService");
        e(ab.a.bw(paramParcel1.readStrongBinder()));
        paramParcel2.writeNoException();
        i1 = 1;
        break;
      case 15: 
        paramParcel1.enforceInterface("com.google.android.gms.wearable.internal.IWearableService");
        f(ab.a.bw(paramParcel1.readStrongBinder()));
        paramParcel2.writeNoException();
        i1 = 1;
        break;
      case 16: 
        paramParcel1.enforceInterface("com.google.android.gms.wearable.internal.IWearableService");
        localab = ab.a.bw(paramParcel1.readStrongBinder());
        b localb;
        if (paramParcel1.readInt() != 0) {
          localb = (b)b.CREATOR.createFromParcel(paramParcel1);
        }
        a(localab, localb);
        paramParcel2.writeNoException();
        int i2 = 1;
        break;
      case 17: 
        paramParcel1.enforceInterface("com.google.android.gms.wearable.internal.IWearableService");
        localab = ab.a.bw(paramParcel1.readStrongBinder());
        ao localao;
        if (paramParcel1.readInt() != 0) {
          localao = (ao)ao.CREATOR.createFromParcel(paramParcel1);
        }
        a(localab, localao);
        paramParcel2.writeNoException();
        bool2 = true;
        break;
      case 18: 
        paramParcel1.enforceInterface("com.google.android.gms.wearable.internal.IWearableService");
        g(ab.a.bw(paramParcel1.readStrongBinder()));
        paramParcel2.writeNoException();
        bool2 = true;
        break;
      case 19: 
        paramParcel1.enforceInterface("com.google.android.gms.wearable.internal.IWearableService");
        h(ab.a.bw(paramParcel1.readStrongBinder()));
        paramParcel2.writeNoException();
        bool2 = true;
        break;
      case 1598968902: 
        paramParcel2.writeString("com.google.android.gms.wearable.internal.IWearableService");
        bool2 = true;
      }
      return bool2;
    }
    
    private static class a
      implements ad
    {
      private IBinder ko;
      
      a(IBinder paramIBinder)
      {
        this.ko = paramIBinder;
      }
      
      /* Error */
      public void a(ab paramab)
        throws RemoteException
      {
        // Byte code:
        //   0: invokestatic 27	android/os/Parcel:obtain	()Landroid/os/Parcel;
        //   3: astore_3
        //   4: invokestatic 27	android/os/Parcel:obtain	()Landroid/os/Parcel;
        //   7: astore_2
        //   8: aload_3
        //   9: ldc 29
        //   11: invokevirtual 33	android/os/Parcel:writeInterfaceToken	(Ljava/lang/String;)V
        //   14: aload_1
        //   15: ifnull +44 -> 59
        //   18: aload_1
        //   19: invokeinterface 39 1 0
        //   24: astore 4
        //   26: aload_3
        //   27: aload 4
        //   29: invokevirtual 42	android/os/Parcel:writeStrongBinder	(Landroid/os/IBinder;)V
        //   32: aload_0
        //   33: getfield 18	com/google/android/gms/wearable/internal/ad$a$a:ko	Landroid/os/IBinder;
        //   36: iconst_3
        //   37: aload_3
        //   38: aload_2
        //   39: iconst_0
        //   40: invokeinterface 48 5 0
        //   45: pop
        //   46: aload_2
        //   47: invokevirtual 51	android/os/Parcel:readException	()V
        //   50: aload_2
        //   51: invokevirtual 54	android/os/Parcel:recycle	()V
        //   54: aload_3
        //   55: invokevirtual 54	android/os/Parcel:recycle	()V
        //   58: return
        //   59: aconst_null
        //   60: astore 4
        //   62: goto -36 -> 26
        //   65: astore 4
        //   67: aload_2
        //   68: invokevirtual 54	android/os/Parcel:recycle	()V
        //   71: aload_3
        //   72: invokevirtual 54	android/os/Parcel:recycle	()V
        //   75: aload 4
        //   77: athrow
        // Local variable table:
        //   start	length	slot	name	signature
        //   0	78	0	this	a
        //   0	78	1	paramab	ab
        //   7	61	2	localParcel1	Parcel
        //   3	69	3	localParcel2	Parcel
        //   24	37	4	localIBinder	IBinder
        //   65	11	4	localObject	Object
        // Exception table:
        //   from	to	target	type
        //   8	50	65	finally
      }
      
      /* Error */
      public void a(ab paramab, Uri paramUri)
        throws RemoteException
      {
        // Byte code:
        //   0: invokestatic 27	android/os/Parcel:obtain	()Landroid/os/Parcel;
        //   3: astore_3
        //   4: invokestatic 27	android/os/Parcel:obtain	()Landroid/os/Parcel;
        //   7: astore 4
        //   9: aload_3
        //   10: ldc 29
        //   12: invokevirtual 33	android/os/Parcel:writeInterfaceToken	(Ljava/lang/String;)V
        //   15: aload_1
        //   16: ifnull +63 -> 79
        //   19: aload_1
        //   20: invokeinterface 39 1 0
        //   25: astore 5
        //   27: aload_3
        //   28: aload 5
        //   30: invokevirtual 42	android/os/Parcel:writeStrongBinder	(Landroid/os/IBinder;)V
        //   33: aload_2
        //   34: ifnull +51 -> 85
        //   37: aload_3
        //   38: iconst_1
        //   39: invokevirtual 59	android/os/Parcel:writeInt	(I)V
        //   42: aload_2
        //   43: aload_3
        //   44: iconst_0
        //   45: invokevirtual 65	android/net/Uri:writeToParcel	(Landroid/os/Parcel;I)V
        //   48: aload_0
        //   49: getfield 18	com/google/android/gms/wearable/internal/ad$a$a:ko	Landroid/os/IBinder;
        //   52: bipush 7
        //   54: aload_3
        //   55: aload 4
        //   57: iconst_0
        //   58: invokeinterface 48 5 0
        //   63: pop
        //   64: aload 4
        //   66: invokevirtual 51	android/os/Parcel:readException	()V
        //   69: aload 4
        //   71: invokevirtual 54	android/os/Parcel:recycle	()V
        //   74: aload_3
        //   75: invokevirtual 54	android/os/Parcel:recycle	()V
        //   78: return
        //   79: aconst_null
        //   80: astore 5
        //   82: goto -55 -> 27
        //   85: aload_3
        //   86: iconst_0
        //   87: invokevirtual 59	android/os/Parcel:writeInt	(I)V
        //   90: goto -42 -> 48
        //   93: astore 5
        //   95: aload 4
        //   97: invokevirtual 54	android/os/Parcel:recycle	()V
        //   100: aload_3
        //   101: invokevirtual 54	android/os/Parcel:recycle	()V
        //   104: aload 5
        //   106: athrow
        // Local variable table:
        //   start	length	slot	name	signature
        //   0	107	0	this	a
        //   0	107	1	paramab	ab
        //   0	107	2	paramUri	Uri
        //   3	98	3	localParcel1	Parcel
        //   7	89	4	localParcel2	Parcel
        //   25	56	5	localIBinder	IBinder
        //   93	12	5	localObject	Object
        // Exception table:
        //   from	to	target	type
        //   9	69	93	finally
        //   85	90	93	finally
      }
      
      /* Error */
      public void a(ab paramab, Asset paramAsset)
        throws RemoteException
      {
        // Byte code:
        //   0: invokestatic 27	android/os/Parcel:obtain	()Landroid/os/Parcel;
        //   3: astore 4
        //   5: invokestatic 27	android/os/Parcel:obtain	()Landroid/os/Parcel;
        //   8: astore_3
        //   9: aload 4
        //   11: ldc 29
        //   13: invokevirtual 33	android/os/Parcel:writeInterfaceToken	(Ljava/lang/String;)V
        //   16: aload_1
        //   17: ifnull +65 -> 82
        //   20: aload_1
        //   21: invokeinterface 39 1 0
        //   26: astore 5
        //   28: aload 4
        //   30: aload 5
        //   32: invokevirtual 42	android/os/Parcel:writeStrongBinder	(Landroid/os/IBinder;)V
        //   35: aload_2
        //   36: ifnull +52 -> 88
        //   39: aload 4
        //   41: iconst_1
        //   42: invokevirtual 59	android/os/Parcel:writeInt	(I)V
        //   45: aload_2
        //   46: aload 4
        //   48: iconst_0
        //   49: invokevirtual 69	com/google/android/gms/wearable/Asset:writeToParcel	(Landroid/os/Parcel;I)V
        //   52: aload_0
        //   53: getfield 18	com/google/android/gms/wearable/internal/ad$a$a:ko	Landroid/os/IBinder;
        //   56: bipush 13
        //   58: aload 4
        //   60: aload_3
        //   61: iconst_0
        //   62: invokeinterface 48 5 0
        //   67: pop
        //   68: aload_3
        //   69: invokevirtual 51	android/os/Parcel:readException	()V
        //   72: aload_3
        //   73: invokevirtual 54	android/os/Parcel:recycle	()V
        //   76: aload 4
        //   78: invokevirtual 54	android/os/Parcel:recycle	()V
        //   81: return
        //   82: aconst_null
        //   83: astore 5
        //   85: goto -57 -> 28
        //   88: aload 4
        //   90: iconst_0
        //   91: invokevirtual 59	android/os/Parcel:writeInt	(I)V
        //   94: goto -42 -> 52
        //   97: astore 5
        //   99: aload_3
        //   100: invokevirtual 54	android/os/Parcel:recycle	()V
        //   103: aload 4
        //   105: invokevirtual 54	android/os/Parcel:recycle	()V
        //   108: aload 5
        //   110: athrow
        // Local variable table:
        //   start	length	slot	name	signature
        //   0	111	0	this	a
        //   0	111	1	paramab	ab
        //   0	111	2	paramAsset	Asset
        //   8	92	3	localParcel1	Parcel
        //   3	101	4	localParcel2	Parcel
        //   26	58	5	localIBinder	IBinder
        //   97	12	5	localObject	Object
        // Exception table:
        //   from	to	target	type
        //   9	72	97	finally
        //   88	94	97	finally
      }
      
      /* Error */
      public void a(ab paramab, PutDataRequest paramPutDataRequest)
        throws RemoteException
      {
        // Byte code:
        //   0: invokestatic 27	android/os/Parcel:obtain	()Landroid/os/Parcel;
        //   3: astore_3
        //   4: invokestatic 27	android/os/Parcel:obtain	()Landroid/os/Parcel;
        //   7: astore 4
        //   9: aload_3
        //   10: ldc 29
        //   12: invokevirtual 33	android/os/Parcel:writeInterfaceToken	(Ljava/lang/String;)V
        //   15: aload_1
        //   16: ifnull +63 -> 79
        //   19: aload_1
        //   20: invokeinterface 39 1 0
        //   25: astore 5
        //   27: aload_3
        //   28: aload 5
        //   30: invokevirtual 42	android/os/Parcel:writeStrongBinder	(Landroid/os/IBinder;)V
        //   33: aload_2
        //   34: ifnull +51 -> 85
        //   37: aload_3
        //   38: iconst_1
        //   39: invokevirtual 59	android/os/Parcel:writeInt	(I)V
        //   42: aload_2
        //   43: aload_3
        //   44: iconst_0
        //   45: invokevirtual 73	com/google/android/gms/wearable/PutDataRequest:writeToParcel	(Landroid/os/Parcel;I)V
        //   48: aload_0
        //   49: getfield 18	com/google/android/gms/wearable/internal/ad$a$a:ko	Landroid/os/IBinder;
        //   52: bipush 6
        //   54: aload_3
        //   55: aload 4
        //   57: iconst_0
        //   58: invokeinterface 48 5 0
        //   63: pop
        //   64: aload 4
        //   66: invokevirtual 51	android/os/Parcel:readException	()V
        //   69: aload 4
        //   71: invokevirtual 54	android/os/Parcel:recycle	()V
        //   74: aload_3
        //   75: invokevirtual 54	android/os/Parcel:recycle	()V
        //   78: return
        //   79: aconst_null
        //   80: astore 5
        //   82: goto -55 -> 27
        //   85: aload_3
        //   86: iconst_0
        //   87: invokevirtual 59	android/os/Parcel:writeInt	(I)V
        //   90: goto -42 -> 48
        //   93: astore 5
        //   95: aload 4
        //   97: invokevirtual 54	android/os/Parcel:recycle	()V
        //   100: aload_3
        //   101: invokevirtual 54	android/os/Parcel:recycle	()V
        //   104: aload 5
        //   106: athrow
        // Local variable table:
        //   start	length	slot	name	signature
        //   0	107	0	this	a
        //   0	107	1	paramab	ab
        //   0	107	2	paramPutDataRequest	PutDataRequest
        //   3	98	3	localParcel1	Parcel
        //   7	89	4	localParcel2	Parcel
        //   25	56	5	localIBinder	IBinder
        //   93	12	5	localObject	Object
        // Exception table:
        //   from	to	target	type
        //   9	69	93	finally
        //   85	90	93	finally
      }
      
      /* Error */
      public void a(ab paramab, c paramc)
        throws RemoteException
      {
        // Byte code:
        //   0: invokestatic 27	android/os/Parcel:obtain	()Landroid/os/Parcel;
        //   3: astore 4
        //   5: invokestatic 27	android/os/Parcel:obtain	()Landroid/os/Parcel;
        //   8: astore_3
        //   9: aload 4
        //   11: ldc 29
        //   13: invokevirtual 33	android/os/Parcel:writeInterfaceToken	(Ljava/lang/String;)V
        //   16: aload_1
        //   17: ifnull +64 -> 81
        //   20: aload_1
        //   21: invokeinterface 39 1 0
        //   26: astore 5
        //   28: aload 4
        //   30: aload 5
        //   32: invokevirtual 42	android/os/Parcel:writeStrongBinder	(Landroid/os/IBinder;)V
        //   35: aload_2
        //   36: ifnull +51 -> 87
        //   39: aload 4
        //   41: iconst_1
        //   42: invokevirtual 59	android/os/Parcel:writeInt	(I)V
        //   45: aload_2
        //   46: aload 4
        //   48: iconst_0
        //   49: invokevirtual 77	com/google/android/gms/wearable/c:writeToParcel	(Landroid/os/Parcel;I)V
        //   52: aload_0
        //   53: getfield 18	com/google/android/gms/wearable/internal/ad$a$a:ko	Landroid/os/IBinder;
        //   56: iconst_2
        //   57: aload 4
        //   59: aload_3
        //   60: iconst_0
        //   61: invokeinterface 48 5 0
        //   66: pop
        //   67: aload_3
        //   68: invokevirtual 51	android/os/Parcel:readException	()V
        //   71: aload_3
        //   72: invokevirtual 54	android/os/Parcel:recycle	()V
        //   75: aload 4
        //   77: invokevirtual 54	android/os/Parcel:recycle	()V
        //   80: return
        //   81: aconst_null
        //   82: astore 5
        //   84: goto -56 -> 28
        //   87: aload 4
        //   89: iconst_0
        //   90: invokevirtual 59	android/os/Parcel:writeInt	(I)V
        //   93: goto -41 -> 52
        //   96: astore 5
        //   98: aload_3
        //   99: invokevirtual 54	android/os/Parcel:recycle	()V
        //   102: aload 4
        //   104: invokevirtual 54	android/os/Parcel:recycle	()V
        //   107: aload 5
        //   109: athrow
        // Local variable table:
        //   start	length	slot	name	signature
        //   0	110	0	this	a
        //   0	110	1	paramab	ab
        //   0	110	2	paramc	c
        //   8	91	3	localParcel1	Parcel
        //   3	100	4	localParcel2	Parcel
        //   26	57	5	localIBinder	IBinder
        //   96	12	5	localObject	Object
        // Exception table:
        //   from	to	target	type
        //   9	71	96	finally
        //   87	93	96	finally
      }
      
      /* Error */
      public void a(ab paramab, ao paramao)
        throws RemoteException
      {
        // Byte code:
        //   0: invokestatic 27	android/os/Parcel:obtain	()Landroid/os/Parcel;
        //   3: astore 4
        //   5: invokestatic 27	android/os/Parcel:obtain	()Landroid/os/Parcel;
        //   8: astore_3
        //   9: aload 4
        //   11: ldc 29
        //   13: invokevirtual 33	android/os/Parcel:writeInterfaceToken	(Ljava/lang/String;)V
        //   16: aload_1
        //   17: ifnull +65 -> 82
        //   20: aload_1
        //   21: invokeinterface 39 1 0
        //   26: astore 5
        //   28: aload 4
        //   30: aload 5
        //   32: invokevirtual 42	android/os/Parcel:writeStrongBinder	(Landroid/os/IBinder;)V
        //   35: aload_2
        //   36: ifnull +52 -> 88
        //   39: aload 4
        //   41: iconst_1
        //   42: invokevirtual 59	android/os/Parcel:writeInt	(I)V
        //   45: aload_2
        //   46: aload 4
        //   48: iconst_0
        //   49: invokevirtual 81	com/google/android/gms/wearable/internal/ao:writeToParcel	(Landroid/os/Parcel;I)V
        //   52: aload_0
        //   53: getfield 18	com/google/android/gms/wearable/internal/ad$a$a:ko	Landroid/os/IBinder;
        //   56: bipush 17
        //   58: aload 4
        //   60: aload_3
        //   61: iconst_0
        //   62: invokeinterface 48 5 0
        //   67: pop
        //   68: aload_3
        //   69: invokevirtual 51	android/os/Parcel:readException	()V
        //   72: aload_3
        //   73: invokevirtual 54	android/os/Parcel:recycle	()V
        //   76: aload 4
        //   78: invokevirtual 54	android/os/Parcel:recycle	()V
        //   81: return
        //   82: aconst_null
        //   83: astore 5
        //   85: goto -57 -> 28
        //   88: aload 4
        //   90: iconst_0
        //   91: invokevirtual 59	android/os/Parcel:writeInt	(I)V
        //   94: goto -42 -> 52
        //   97: astore 5
        //   99: aload_3
        //   100: invokevirtual 54	android/os/Parcel:recycle	()V
        //   103: aload 4
        //   105: invokevirtual 54	android/os/Parcel:recycle	()V
        //   108: aload 5
        //   110: athrow
        // Local variable table:
        //   start	length	slot	name	signature
        //   0	111	0	this	a
        //   0	111	1	paramab	ab
        //   0	111	2	paramao	ao
        //   8	92	3	localParcel1	Parcel
        //   3	101	4	localParcel2	Parcel
        //   26	58	5	localIBinder	IBinder
        //   97	12	5	localObject	Object
        // Exception table:
        //   from	to	target	type
        //   9	72	97	finally
        //   88	94	97	finally
      }
      
      /* Error */
      public void a(ab paramab, b paramb)
        throws RemoteException
      {
        // Byte code:
        //   0: invokestatic 27	android/os/Parcel:obtain	()Landroid/os/Parcel;
        //   3: astore_3
        //   4: invokestatic 27	android/os/Parcel:obtain	()Landroid/os/Parcel;
        //   7: astore 4
        //   9: aload_3
        //   10: ldc 29
        //   12: invokevirtual 33	android/os/Parcel:writeInterfaceToken	(Ljava/lang/String;)V
        //   15: aload_1
        //   16: ifnull +63 -> 79
        //   19: aload_1
        //   20: invokeinterface 39 1 0
        //   25: astore 5
        //   27: aload_3
        //   28: aload 5
        //   30: invokevirtual 42	android/os/Parcel:writeStrongBinder	(Landroid/os/IBinder;)V
        //   33: aload_2
        //   34: ifnull +51 -> 85
        //   37: aload_3
        //   38: iconst_1
        //   39: invokevirtual 59	android/os/Parcel:writeInt	(I)V
        //   42: aload_2
        //   43: aload_3
        //   44: iconst_0
        //   45: invokevirtual 85	com/google/android/gms/wearable/internal/b:writeToParcel	(Landroid/os/Parcel;I)V
        //   48: aload_0
        //   49: getfield 18	com/google/android/gms/wearable/internal/ad$a$a:ko	Landroid/os/IBinder;
        //   52: bipush 16
        //   54: aload_3
        //   55: aload 4
        //   57: iconst_0
        //   58: invokeinterface 48 5 0
        //   63: pop
        //   64: aload 4
        //   66: invokevirtual 51	android/os/Parcel:readException	()V
        //   69: aload 4
        //   71: invokevirtual 54	android/os/Parcel:recycle	()V
        //   74: aload_3
        //   75: invokevirtual 54	android/os/Parcel:recycle	()V
        //   78: return
        //   79: aconst_null
        //   80: astore 5
        //   82: goto -55 -> 27
        //   85: aload_3
        //   86: iconst_0
        //   87: invokevirtual 59	android/os/Parcel:writeInt	(I)V
        //   90: goto -42 -> 48
        //   93: astore 5
        //   95: aload 4
        //   97: invokevirtual 54	android/os/Parcel:recycle	()V
        //   100: aload_3
        //   101: invokevirtual 54	android/os/Parcel:recycle	()V
        //   104: aload 5
        //   106: athrow
        // Local variable table:
        //   start	length	slot	name	signature
        //   0	107	0	this	a
        //   0	107	1	paramab	ab
        //   0	107	2	paramb	b
        //   3	98	3	localParcel1	Parcel
        //   7	89	4	localParcel2	Parcel
        //   25	56	5	localIBinder	IBinder
        //   93	12	5	localObject	Object
        // Exception table:
        //   from	to	target	type
        //   9	69	93	finally
        //   85	90	93	finally
      }
      
      /* Error */
      public void a(ab paramab, String paramString1, String paramString2, byte[] paramArrayOfByte)
        throws RemoteException
      {
        // Byte code:
        //   0: invokestatic 27	android/os/Parcel:obtain	()Landroid/os/Parcel;
        //   3: astore 5
        //   5: invokestatic 27	android/os/Parcel:obtain	()Landroid/os/Parcel;
        //   8: astore 6
        //   10: aload 5
        //   12: ldc 29
        //   14: invokevirtual 33	android/os/Parcel:writeInterfaceToken	(Ljava/lang/String;)V
        //   17: aload_1
        //   18: ifnull +70 -> 88
        //   21: aload_1
        //   22: invokeinterface 39 1 0
        //   27: astore 7
        //   29: aload 5
        //   31: aload 7
        //   33: invokevirtual 42	android/os/Parcel:writeStrongBinder	(Landroid/os/IBinder;)V
        //   36: aload 5
        //   38: aload_2
        //   39: invokevirtual 89	android/os/Parcel:writeString	(Ljava/lang/String;)V
        //   42: aload 5
        //   44: aload_3
        //   45: invokevirtual 89	android/os/Parcel:writeString	(Ljava/lang/String;)V
        //   48: aload 5
        //   50: aload 4
        //   52: invokevirtual 93	android/os/Parcel:writeByteArray	([B)V
        //   55: aload_0
        //   56: getfield 18	com/google/android/gms/wearable/internal/ad$a$a:ko	Landroid/os/IBinder;
        //   59: bipush 12
        //   61: aload 5
        //   63: aload 6
        //   65: iconst_0
        //   66: invokeinterface 48 5 0
        //   71: pop
        //   72: aload 6
        //   74: invokevirtual 51	android/os/Parcel:readException	()V
        //   77: aload 6
        //   79: invokevirtual 54	android/os/Parcel:recycle	()V
        //   82: aload 5
        //   84: invokevirtual 54	android/os/Parcel:recycle	()V
        //   87: return
        //   88: aconst_null
        //   89: astore 7
        //   91: goto -62 -> 29
        //   94: astore 7
        //   96: aload 6
        //   98: invokevirtual 54	android/os/Parcel:recycle	()V
        //   101: aload 5
        //   103: invokevirtual 54	android/os/Parcel:recycle	()V
        //   106: aload 7
        //   108: athrow
        // Local variable table:
        //   start	length	slot	name	signature
        //   0	109	0	this	a
        //   0	109	1	paramab	ab
        //   0	109	2	paramString1	String
        //   0	109	3	paramString2	String
        //   0	109	4	paramArrayOfByte	byte[]
        //   3	99	5	localParcel1	Parcel
        //   8	89	6	localParcel2	Parcel
        //   27	63	7	localIBinder	IBinder
        //   94	13	7	localObject	Object
        // Exception table:
        //   from	to	target	type
        //   10	77	94	finally
      }
      
      public IBinder asBinder()
      {
        return this.ko;
      }
      
      /* Error */
      public void b(ab paramab)
        throws RemoteException
      {
        // Byte code:
        //   0: invokestatic 27	android/os/Parcel:obtain	()Landroid/os/Parcel;
        //   3: astore_2
        //   4: invokestatic 27	android/os/Parcel:obtain	()Landroid/os/Parcel;
        //   7: astore_3
        //   8: aload_2
        //   9: ldc 29
        //   11: invokevirtual 33	android/os/Parcel:writeInterfaceToken	(Ljava/lang/String;)V
        //   14: aload_1
        //   15: ifnull +44 -> 59
        //   18: aload_1
        //   19: invokeinterface 39 1 0
        //   24: astore 4
        //   26: aload_2
        //   27: aload 4
        //   29: invokevirtual 42	android/os/Parcel:writeStrongBinder	(Landroid/os/IBinder;)V
        //   32: aload_0
        //   33: getfield 18	com/google/android/gms/wearable/internal/ad$a$a:ko	Landroid/os/IBinder;
        //   36: iconst_4
        //   37: aload_2
        //   38: aload_3
        //   39: iconst_0
        //   40: invokeinterface 48 5 0
        //   45: pop
        //   46: aload_3
        //   47: invokevirtual 51	android/os/Parcel:readException	()V
        //   50: aload_3
        //   51: invokevirtual 54	android/os/Parcel:recycle	()V
        //   54: aload_2
        //   55: invokevirtual 54	android/os/Parcel:recycle	()V
        //   58: return
        //   59: aconst_null
        //   60: astore 4
        //   62: goto -36 -> 26
        //   65: astore 4
        //   67: aload_3
        //   68: invokevirtual 54	android/os/Parcel:recycle	()V
        //   71: aload_2
        //   72: invokevirtual 54	android/os/Parcel:recycle	()V
        //   75: aload 4
        //   77: athrow
        // Local variable table:
        //   start	length	slot	name	signature
        //   0	78	0	this	a
        //   0	78	1	paramab	ab
        //   3	69	2	localParcel1	Parcel
        //   7	61	3	localParcel2	Parcel
        //   24	37	4	localIBinder	IBinder
        //   65	11	4	localObject	Object
        // Exception table:
        //   from	to	target	type
        //   8	50	65	finally
      }
      
      /* Error */
      public void b(ab paramab, Uri paramUri)
        throws RemoteException
      {
        // Byte code:
        //   0: invokestatic 27	android/os/Parcel:obtain	()Landroid/os/Parcel;
        //   3: astore 4
        //   5: invokestatic 27	android/os/Parcel:obtain	()Landroid/os/Parcel;
        //   8: astore_3
        //   9: aload 4
        //   11: ldc 29
        //   13: invokevirtual 33	android/os/Parcel:writeInterfaceToken	(Ljava/lang/String;)V
        //   16: aload_1
        //   17: ifnull +65 -> 82
        //   20: aload_1
        //   21: invokeinterface 39 1 0
        //   26: astore 5
        //   28: aload 4
        //   30: aload 5
        //   32: invokevirtual 42	android/os/Parcel:writeStrongBinder	(Landroid/os/IBinder;)V
        //   35: aload_2
        //   36: ifnull +52 -> 88
        //   39: aload 4
        //   41: iconst_1
        //   42: invokevirtual 59	android/os/Parcel:writeInt	(I)V
        //   45: aload_2
        //   46: aload 4
        //   48: iconst_0
        //   49: invokevirtual 65	android/net/Uri:writeToParcel	(Landroid/os/Parcel;I)V
        //   52: aload_0
        //   53: getfield 18	com/google/android/gms/wearable/internal/ad$a$a:ko	Landroid/os/IBinder;
        //   56: bipush 9
        //   58: aload 4
        //   60: aload_3
        //   61: iconst_0
        //   62: invokeinterface 48 5 0
        //   67: pop
        //   68: aload_3
        //   69: invokevirtual 51	android/os/Parcel:readException	()V
        //   72: aload_3
        //   73: invokevirtual 54	android/os/Parcel:recycle	()V
        //   76: aload 4
        //   78: invokevirtual 54	android/os/Parcel:recycle	()V
        //   81: return
        //   82: aconst_null
        //   83: astore 5
        //   85: goto -57 -> 28
        //   88: aload 4
        //   90: iconst_0
        //   91: invokevirtual 59	android/os/Parcel:writeInt	(I)V
        //   94: goto -42 -> 52
        //   97: astore 5
        //   99: aload_3
        //   100: invokevirtual 54	android/os/Parcel:recycle	()V
        //   103: aload 4
        //   105: invokevirtual 54	android/os/Parcel:recycle	()V
        //   108: aload 5
        //   110: athrow
        // Local variable table:
        //   start	length	slot	name	signature
        //   0	111	0	this	a
        //   0	111	1	paramab	ab
        //   0	111	2	paramUri	Uri
        //   8	92	3	localParcel1	Parcel
        //   3	101	4	localParcel2	Parcel
        //   26	58	5	localIBinder	IBinder
        //   97	12	5	localObject	Object
        // Exception table:
        //   from	to	target	type
        //   9	72	97	finally
        //   88	94	97	finally
      }
      
      /* Error */
      public void c(ab paramab)
        throws RemoteException
      {
        // Byte code:
        //   0: invokestatic 27	android/os/Parcel:obtain	()Landroid/os/Parcel;
        //   3: astore_3
        //   4: invokestatic 27	android/os/Parcel:obtain	()Landroid/os/Parcel;
        //   7: astore_2
        //   8: aload_3
        //   9: ldc 29
        //   11: invokevirtual 33	android/os/Parcel:writeInterfaceToken	(Ljava/lang/String;)V
        //   14: aload_1
        //   15: ifnull +44 -> 59
        //   18: aload_1
        //   19: invokeinterface 39 1 0
        //   24: astore 4
        //   26: aload_3
        //   27: aload 4
        //   29: invokevirtual 42	android/os/Parcel:writeStrongBinder	(Landroid/os/IBinder;)V
        //   32: aload_0
        //   33: getfield 18	com/google/android/gms/wearable/internal/ad$a$a:ko	Landroid/os/IBinder;
        //   36: iconst_5
        //   37: aload_3
        //   38: aload_2
        //   39: iconst_0
        //   40: invokeinterface 48 5 0
        //   45: pop
        //   46: aload_2
        //   47: invokevirtual 51	android/os/Parcel:readException	()V
        //   50: aload_2
        //   51: invokevirtual 54	android/os/Parcel:recycle	()V
        //   54: aload_3
        //   55: invokevirtual 54	android/os/Parcel:recycle	()V
        //   58: return
        //   59: aconst_null
        //   60: astore 4
        //   62: goto -36 -> 26
        //   65: astore 4
        //   67: aload_2
        //   68: invokevirtual 54	android/os/Parcel:recycle	()V
        //   71: aload_3
        //   72: invokevirtual 54	android/os/Parcel:recycle	()V
        //   75: aload 4
        //   77: athrow
        // Local variable table:
        //   start	length	slot	name	signature
        //   0	78	0	this	a
        //   0	78	1	paramab	ab
        //   7	61	2	localParcel1	Parcel
        //   3	69	3	localParcel2	Parcel
        //   24	37	4	localIBinder	IBinder
        //   65	11	4	localObject	Object
        // Exception table:
        //   from	to	target	type
        //   8	50	65	finally
      }
      
      /* Error */
      public void c(ab paramab, Uri paramUri)
        throws RemoteException
      {
        // Byte code:
        //   0: invokestatic 27	android/os/Parcel:obtain	()Landroid/os/Parcel;
        //   3: astore_3
        //   4: invokestatic 27	android/os/Parcel:obtain	()Landroid/os/Parcel;
        //   7: astore 4
        //   9: aload_3
        //   10: ldc 29
        //   12: invokevirtual 33	android/os/Parcel:writeInterfaceToken	(Ljava/lang/String;)V
        //   15: aload_1
        //   16: ifnull +63 -> 79
        //   19: aload_1
        //   20: invokeinterface 39 1 0
        //   25: astore 5
        //   27: aload_3
        //   28: aload 5
        //   30: invokevirtual 42	android/os/Parcel:writeStrongBinder	(Landroid/os/IBinder;)V
        //   33: aload_2
        //   34: ifnull +51 -> 85
        //   37: aload_3
        //   38: iconst_1
        //   39: invokevirtual 59	android/os/Parcel:writeInt	(I)V
        //   42: aload_2
        //   43: aload_3
        //   44: iconst_0
        //   45: invokevirtual 65	android/net/Uri:writeToParcel	(Landroid/os/Parcel;I)V
        //   48: aload_0
        //   49: getfield 18	com/google/android/gms/wearable/internal/ad$a$a:ko	Landroid/os/IBinder;
        //   52: bipush 11
        //   54: aload_3
        //   55: aload 4
        //   57: iconst_0
        //   58: invokeinterface 48 5 0
        //   63: pop
        //   64: aload 4
        //   66: invokevirtual 51	android/os/Parcel:readException	()V
        //   69: aload 4
        //   71: invokevirtual 54	android/os/Parcel:recycle	()V
        //   74: aload_3
        //   75: invokevirtual 54	android/os/Parcel:recycle	()V
        //   78: return
        //   79: aconst_null
        //   80: astore 5
        //   82: goto -55 -> 27
        //   85: aload_3
        //   86: iconst_0
        //   87: invokevirtual 59	android/os/Parcel:writeInt	(I)V
        //   90: goto -42 -> 48
        //   93: astore 5
        //   95: aload 4
        //   97: invokevirtual 54	android/os/Parcel:recycle	()V
        //   100: aload_3
        //   101: invokevirtual 54	android/os/Parcel:recycle	()V
        //   104: aload 5
        //   106: athrow
        // Local variable table:
        //   start	length	slot	name	signature
        //   0	107	0	this	a
        //   0	107	1	paramab	ab
        //   0	107	2	paramUri	Uri
        //   3	98	3	localParcel1	Parcel
        //   7	89	4	localParcel2	Parcel
        //   25	56	5	localIBinder	IBinder
        //   93	12	5	localObject	Object
        // Exception table:
        //   from	to	target	type
        //   9	69	93	finally
        //   85	90	93	finally
      }
      
      /* Error */
      public void d(ab paramab)
        throws RemoteException
      {
        // Byte code:
        //   0: invokestatic 27	android/os/Parcel:obtain	()Landroid/os/Parcel;
        //   3: astore_3
        //   4: invokestatic 27	android/os/Parcel:obtain	()Landroid/os/Parcel;
        //   7: astore_2
        //   8: aload_3
        //   9: ldc 29
        //   11: invokevirtual 33	android/os/Parcel:writeInterfaceToken	(Ljava/lang/String;)V
        //   14: aload_1
        //   15: ifnull +45 -> 60
        //   18: aload_1
        //   19: invokeinterface 39 1 0
        //   24: astore 4
        //   26: aload_3
        //   27: aload 4
        //   29: invokevirtual 42	android/os/Parcel:writeStrongBinder	(Landroid/os/IBinder;)V
        //   32: aload_0
        //   33: getfield 18	com/google/android/gms/wearable/internal/ad$a$a:ko	Landroid/os/IBinder;
        //   36: bipush 8
        //   38: aload_3
        //   39: aload_2
        //   40: iconst_0
        //   41: invokeinterface 48 5 0
        //   46: pop
        //   47: aload_2
        //   48: invokevirtual 51	android/os/Parcel:readException	()V
        //   51: aload_2
        //   52: invokevirtual 54	android/os/Parcel:recycle	()V
        //   55: aload_3
        //   56: invokevirtual 54	android/os/Parcel:recycle	()V
        //   59: return
        //   60: aconst_null
        //   61: astore 4
        //   63: goto -37 -> 26
        //   66: astore 4
        //   68: aload_2
        //   69: invokevirtual 54	android/os/Parcel:recycle	()V
        //   72: aload_3
        //   73: invokevirtual 54	android/os/Parcel:recycle	()V
        //   76: aload 4
        //   78: athrow
        // Local variable table:
        //   start	length	slot	name	signature
        //   0	79	0	this	a
        //   0	79	1	paramab	ab
        //   7	62	2	localParcel1	Parcel
        //   3	70	3	localParcel2	Parcel
        //   24	38	4	localIBinder	IBinder
        //   66	11	4	localObject	Object
        // Exception table:
        //   from	to	target	type
        //   8	51	66	finally
      }
      
      /* Error */
      public void e(ab paramab)
        throws RemoteException
      {
        // Byte code:
        //   0: invokestatic 27	android/os/Parcel:obtain	()Landroid/os/Parcel;
        //   3: astore_2
        //   4: invokestatic 27	android/os/Parcel:obtain	()Landroid/os/Parcel;
        //   7: astore_3
        //   8: aload_2
        //   9: ldc 29
        //   11: invokevirtual 33	android/os/Parcel:writeInterfaceToken	(Ljava/lang/String;)V
        //   14: aload_1
        //   15: ifnull +45 -> 60
        //   18: aload_1
        //   19: invokeinterface 39 1 0
        //   24: astore 4
        //   26: aload_2
        //   27: aload 4
        //   29: invokevirtual 42	android/os/Parcel:writeStrongBinder	(Landroid/os/IBinder;)V
        //   32: aload_0
        //   33: getfield 18	com/google/android/gms/wearable/internal/ad$a$a:ko	Landroid/os/IBinder;
        //   36: bipush 14
        //   38: aload_2
        //   39: aload_3
        //   40: iconst_0
        //   41: invokeinterface 48 5 0
        //   46: pop
        //   47: aload_3
        //   48: invokevirtual 51	android/os/Parcel:readException	()V
        //   51: aload_3
        //   52: invokevirtual 54	android/os/Parcel:recycle	()V
        //   55: aload_2
        //   56: invokevirtual 54	android/os/Parcel:recycle	()V
        //   59: return
        //   60: aconst_null
        //   61: astore 4
        //   63: goto -37 -> 26
        //   66: astore 4
        //   68: aload_3
        //   69: invokevirtual 54	android/os/Parcel:recycle	()V
        //   72: aload_2
        //   73: invokevirtual 54	android/os/Parcel:recycle	()V
        //   76: aload 4
        //   78: athrow
        // Local variable table:
        //   start	length	slot	name	signature
        //   0	79	0	this	a
        //   0	79	1	paramab	ab
        //   3	70	2	localParcel1	Parcel
        //   7	62	3	localParcel2	Parcel
        //   24	38	4	localIBinder	IBinder
        //   66	11	4	localObject	Object
        // Exception table:
        //   from	to	target	type
        //   8	51	66	finally
      }
      
      /* Error */
      public void f(ab paramab)
        throws RemoteException
      {
        // Byte code:
        //   0: invokestatic 27	android/os/Parcel:obtain	()Landroid/os/Parcel;
        //   3: astore_3
        //   4: invokestatic 27	android/os/Parcel:obtain	()Landroid/os/Parcel;
        //   7: astore_2
        //   8: aload_3
        //   9: ldc 29
        //   11: invokevirtual 33	android/os/Parcel:writeInterfaceToken	(Ljava/lang/String;)V
        //   14: aload_1
        //   15: ifnull +45 -> 60
        //   18: aload_1
        //   19: invokeinterface 39 1 0
        //   24: astore 4
        //   26: aload_3
        //   27: aload 4
        //   29: invokevirtual 42	android/os/Parcel:writeStrongBinder	(Landroid/os/IBinder;)V
        //   32: aload_0
        //   33: getfield 18	com/google/android/gms/wearable/internal/ad$a$a:ko	Landroid/os/IBinder;
        //   36: bipush 15
        //   38: aload_3
        //   39: aload_2
        //   40: iconst_0
        //   41: invokeinterface 48 5 0
        //   46: pop
        //   47: aload_2
        //   48: invokevirtual 51	android/os/Parcel:readException	()V
        //   51: aload_2
        //   52: invokevirtual 54	android/os/Parcel:recycle	()V
        //   55: aload_3
        //   56: invokevirtual 54	android/os/Parcel:recycle	()V
        //   59: return
        //   60: aconst_null
        //   61: astore 4
        //   63: goto -37 -> 26
        //   66: astore 4
        //   68: aload_2
        //   69: invokevirtual 54	android/os/Parcel:recycle	()V
        //   72: aload_3
        //   73: invokevirtual 54	android/os/Parcel:recycle	()V
        //   76: aload 4
        //   78: athrow
        // Local variable table:
        //   start	length	slot	name	signature
        //   0	79	0	this	a
        //   0	79	1	paramab	ab
        //   7	62	2	localParcel1	Parcel
        //   3	70	3	localParcel2	Parcel
        //   24	38	4	localIBinder	IBinder
        //   66	11	4	localObject	Object
        // Exception table:
        //   from	to	target	type
        //   8	51	66	finally
      }
      
      /* Error */
      public void g(ab paramab)
        throws RemoteException
      {
        // Byte code:
        //   0: invokestatic 27	android/os/Parcel:obtain	()Landroid/os/Parcel;
        //   3: astore_3
        //   4: invokestatic 27	android/os/Parcel:obtain	()Landroid/os/Parcel;
        //   7: astore_2
        //   8: aload_3
        //   9: ldc 29
        //   11: invokevirtual 33	android/os/Parcel:writeInterfaceToken	(Ljava/lang/String;)V
        //   14: aload_1
        //   15: ifnull +45 -> 60
        //   18: aload_1
        //   19: invokeinterface 39 1 0
        //   24: astore 4
        //   26: aload_3
        //   27: aload 4
        //   29: invokevirtual 42	android/os/Parcel:writeStrongBinder	(Landroid/os/IBinder;)V
        //   32: aload_0
        //   33: getfield 18	com/google/android/gms/wearable/internal/ad$a$a:ko	Landroid/os/IBinder;
        //   36: bipush 18
        //   38: aload_3
        //   39: aload_2
        //   40: iconst_0
        //   41: invokeinterface 48 5 0
        //   46: pop
        //   47: aload_2
        //   48: invokevirtual 51	android/os/Parcel:readException	()V
        //   51: aload_2
        //   52: invokevirtual 54	android/os/Parcel:recycle	()V
        //   55: aload_3
        //   56: invokevirtual 54	android/os/Parcel:recycle	()V
        //   59: return
        //   60: aconst_null
        //   61: astore 4
        //   63: goto -37 -> 26
        //   66: astore 4
        //   68: aload_2
        //   69: invokevirtual 54	android/os/Parcel:recycle	()V
        //   72: aload_3
        //   73: invokevirtual 54	android/os/Parcel:recycle	()V
        //   76: aload 4
        //   78: athrow
        // Local variable table:
        //   start	length	slot	name	signature
        //   0	79	0	this	a
        //   0	79	1	paramab	ab
        //   7	62	2	localParcel1	Parcel
        //   3	70	3	localParcel2	Parcel
        //   24	38	4	localIBinder	IBinder
        //   66	11	4	localObject	Object
        // Exception table:
        //   from	to	target	type
        //   8	51	66	finally
      }
      
      /* Error */
      public void h(ab paramab)
        throws RemoteException
      {
        // Byte code:
        //   0: invokestatic 27	android/os/Parcel:obtain	()Landroid/os/Parcel;
        //   3: astore_3
        //   4: invokestatic 27	android/os/Parcel:obtain	()Landroid/os/Parcel;
        //   7: astore_2
        //   8: aload_3
        //   9: ldc 29
        //   11: invokevirtual 33	android/os/Parcel:writeInterfaceToken	(Ljava/lang/String;)V
        //   14: aload_1
        //   15: ifnull +45 -> 60
        //   18: aload_1
        //   19: invokeinterface 39 1 0
        //   24: astore 4
        //   26: aload_3
        //   27: aload 4
        //   29: invokevirtual 42	android/os/Parcel:writeStrongBinder	(Landroid/os/IBinder;)V
        //   32: aload_0
        //   33: getfield 18	com/google/android/gms/wearable/internal/ad$a$a:ko	Landroid/os/IBinder;
        //   36: bipush 19
        //   38: aload_3
        //   39: aload_2
        //   40: iconst_0
        //   41: invokeinterface 48 5 0
        //   46: pop
        //   47: aload_2
        //   48: invokevirtual 51	android/os/Parcel:readException	()V
        //   51: aload_2
        //   52: invokevirtual 54	android/os/Parcel:recycle	()V
        //   55: aload_3
        //   56: invokevirtual 54	android/os/Parcel:recycle	()V
        //   59: return
        //   60: aconst_null
        //   61: astore 4
        //   63: goto -37 -> 26
        //   66: astore 4
        //   68: aload_2
        //   69: invokevirtual 54	android/os/Parcel:recycle	()V
        //   72: aload_3
        //   73: invokevirtual 54	android/os/Parcel:recycle	()V
        //   76: aload 4
        //   78: athrow
        // Local variable table:
        //   start	length	slot	name	signature
        //   0	79	0	this	a
        //   0	79	1	paramab	ab
        //   7	62	2	localParcel1	Parcel
        //   3	70	3	localParcel2	Parcel
        //   24	38	4	localIBinder	IBinder
        //   66	11	4	localObject	Object
        // Exception table:
        //   from	to	target	type
        //   8	51	66	finally
      }
    }
  }
}


/* Location:           E:\android\Androidvn\dex2jar\classes_dex2jar.jar
 * Qualified Name:     com.google.android.gms.wearable.internal.ad
 * JD-Core Version:    0.7.0.1
 */